Workbook

Sheet How it works
A1: How Bricks-ly uses RII values from published research
A4: What an RII is
B5: Relative Importance Index = sum of all ratings / (highest possible rating x number of respondents). Survey respondents rate each delay factor (e.g. 1-5); the RII runs from about 0.2 to 1. A higher RII means respondents judged the factor more important.
B6: An RII is NOT a probability and NOT a number of days of delay. It can only say which risks people consider more important than others.
A8: Where the values come from
B9: Sheet 'Studies' lists 11 published surveys; sheet 'RII_Data' holds every value recorded from them, as printed, with the table and page. Every factor is mapped to a library risk (only 4 unclear or group-level factors are left unmapped).
B10: Seed studies (used by the model): RII surveys from India and Sri Lanka, closest to Indian masonry sites: M01 (India, masonry), A02 (India, masonry), M06 (India), A14 (Sri Lanka), A15 (Sri Lanka).
B11: Validation studies (held out, never used by the model): M10 (Middle East meta-analysis of 10 surveys), M15 (Brazil), M14 (Indonesia, workers), plus A10, A21 and HAS25 with too few overlapping risks to test.
A13: Step by step (sheet 'Seed_Calculation' does this with live formulas)
B14: 1. Map each factor to one of the tool's library risks (38 risks in 11 categories, built from every factor in the studies). Direct = names the same cause (e.g. 'Material shortages' -> R-MAT). Related = overlaps but is broader, narrower or an outcome (e.g. 'Accidents' -> R-SAFE); Related values are shown but not used.
B15: 2. For each risk and seed study, average that study's Direct values, so one study counts once even if it lists two matching factors.
B16: 3. Seed mean RII for the risk = average across the seed studies that have a value.
B17: 4. Rank the seeded risks by seed mean RII and split them into five equal-count bands (with 30 seeded risks, six per band): top band -> class 5, ... bottom band -> class 1. Risks with no seed-study value (for example R-TRN, R-PRD, R-GOV) are not seeded.
B18: 5. In the app, a library risk with no probability or delay entered yet is placed on the 5x5 matrix at (class, class), drawn with a dashed outline and labelled 'literature seed'.
B19: 6. If a site-fact rule flags the risk (e.g. monsoon overlaps the work), its probability class goes up by one, to a maximum of 5.
B20: 7. As soon as the user enters a probability and a delay range (with a Source), the seed is replaced by those numbers.
A22: Worked example: R-WX (rain / monsoon stoppage)
B23: ="Study values: M01 "&TEXT(Seed_Calculation!C11,"0.000")&", A02 "&TEXT(Seed_Calculation!D11,"0.000")&", M06 "&TEXT(Seed_Calculation!E11,"0.000")&", A14 "&TEXT(Seed_Calculation!F11,"0.000") -> Study values: M01 0.764, A02 0.700, M06 0.657, A14 0.653
B24: ="Seed mean RII = "&TEXT(Seed_Calculation!I11,"0.0000")&" -> rank "&Seed_Calculation!J11&" of "&Seed_Calculation!C44&" -> class "&Seed_Calculation!K11&" -> matrix cell "&Seed_Calculation!L11 -> Seed mean RII = 0.6934 -> rank 24 of 30 -> class 2 -> matrix cell p2 × i2
A26: What the validation shows (sheet 'Validation')
B27: Spearman rank correlation between the seed order and each held-out study, over the risks both cover. Read the 'Reading' column; with only 7-9 shared risks, a result must be strong to be statistically significant.
A29: Limits to state in the report
B30: RII is a perception of importance, not a measured frequency or delay. Studies differ in country, project type, respondents (managers vs workers) and rating scale (1-4 vs 1-5). Several values come from research notes rather than a re-read of the PDF (column 'How the values were obtained').
B31: Most seed mean RIIs lie within a few hundredths of each other, so the order of the middle risks is fragile. The seed is a starting point until expert-survey or site data replace it.
A33: Colour key
B34: Blue text = value copied from a paper. Black = formula. Green = formula that pulls from another sheet. Yellow fill = a judgement you may change (study role, factor mapping); the sheets recalculate.
B35: Built by scripts/build_rii_workbook.py from data/literature_seed.json, the same file the app reads. Edit the JSON and rebuild to keep the app and this workbook in step.

Sheet Studies
A1: Studies the RII values come from
A2: Role and the mapping column on RII_Data (yellow) are judgements you may change; everything else is copied from the papers.
A4: ID | B4: Authors | C4: Year | D4: Title | E4: Venue | F4: DOI | G4: Country | H4: Context | I4: Masonry-specific? | J4: Respondents (N) | K4: Rating scale | L4: Where in the paper | M4: How the values were obtained | N4: Role | O4: Note
A5: M01 | B5: Karthik, D. & Rao, C.B.K. | C5: 2019 | D5: The analysis of essential factors responsible for loss of labour productivity in building construction projects in India | E5: Engineering Journal 23(2) | F5: 10.4186/ej.2019.23.2.55 | G5: India (Telangana) | H5: Multi-storey residential building, masonry wall construction | I5: Yes | J5: 44 | K5: 1-5 | L5: Table 3, p.61 | M5: Read from the PDF (Research_Papers/5_Masonry_Productivity_Delay) | N5: Seed | O5: N = 44 from the response counts in Table 3 (each row sums to 44).
A6: A02 | B6: Ponmalar, Aravindraj & Nandhini | C6: 2018 | D6: Study on factors influencing labour productivity in residential buildings in Indian scenario | E6: IJETMR 5(2): 239-248 | F6: 10.29121/ijetmr.v5.i2.2018.168 | G6: India (Chennai) | H6: Two 3-storey residential buildings, brick masonry activity | I6: Yes | J6: Not reported | K6: 1-4 | L6: Tables 1-2 and Fig. 1 | M6: From the research notes (full text read in an earlier session); PDF not in the project folder | N6: Seed | O6: Low-tier journal; respondent count not reported. Payment delays printed as 775.8 on a 1000 scale.
A7: M06 | B7: Dixit, Mandal, Thanikal & Saurabh | C7: 2019 | D7: Study of significant factors affecting construction productivity using relative importance index in Indian construction industry | E7: E3S Web of Conferences 140, 09010 | F7: 10.1051/e3sconf/201914009010 | G7: India | H7: Construction industry (general), consultants, contractors, developers, academia | I7: No | J7: 201 | K7: 1-5 | L7: Table 3, p.5 | M7: Read from the PDF (Research_Papers/5_Masonry_Productivity_Delay) | N7: Seed | O7: RII = total score / (5 x 201). 'Conflict of interest among team members' is printed twice with different values.
A8: A14 | B8: Abeysinghe & Jayathilaka | C8: 2022 | D8: Factors influencing the timely completion of construction projects in Sri Lanka | E8: PLoS ONE 17(12): e0278318 | F8: 10.1371/journal.pone.0278318 | G8: Sri Lanka | H8: Construction projects incl. buildings; clients, contractors, consultants | I8: No | J8: 163 | K8: Not recorded | L8: Table 2 | M8: From the research notes (rows quoted verbatim from the PMC full text) | N8: Seed | O8: Only the rows quoted in the notes are listed (39 factors in the paper).
A9: A15 | B9: Manoharan et al. | C9: 2022 | D9: Labour-related factors affecting construction productivity in Sri Lankan building projects: perspectives of engineers and managers | E9: Frontiers in Engineering and Built Environment | F9: 10.1108/FEBE-03-2022-0009 | G9: Sri Lanka | H9: Building projects, 90 upper-grade contractor firms | I9: No | J9: 90 firms | K9: Not recorded | L9: Top-ranked factors | M9: From the research notes (summary of the full text, two decimals; lower confidence) | N9: Seed | O9: Only the top five factors (of 32) are recorded.
A10: M10 | B10: Adebowale & Agumba | C10: 2023 | D10: A meta-analysis of factors affecting construction labour productivity in the Middle East | E10: Journal of Construction in Developing Countries 28(1): 193-220 | F10: 10.21315/jcdc-12-21-0192 | G10: Middle East (10 studies: Malaysia, Palestine, Kuwait, Qatar, Saudi Arabia, Egypt, Bahrain, Oman, Yemen, Vietnam) | H10: Meta-analysis: pooled RII ('effect summary', random model) of 35 factors | I10: No | J10: 10 studies | K10: Pooled RII | L10: Table 7, pp.210-211 | M10: Read from the PDF (Research_Papers/5_Masonry_Productivity_Delay) | N10: Validation | O10: Rows Man. 20 (delays responding to requests for information, overall rank 1) and Tec. 5 (type of project) were not captured by text extraction; neither maps to a tool risk.
A11: M15 | B11: de Almeida, Feitoza, Carvalho, Pina, Araujo et al. | C11: 2021 | D11: Study of delays in constructions: a managerial point of view of private companies in Brasilia, Brazil | E11: Gestao & Producao 28(3): e5194 | F11: 10.1590/1806-9649-2021v28e5194 | G11: Brazil (Brasilia) | H11: Private building companies; directors, managers, engineers | I11: No | J11: 47 | K11: 1-4 | L11: Table 3, p.8 | M11: Read from the PDF (Research_Papers/5_Masonry_Productivity_Delay) | N11: Validation | O11: RII printed as a percentage; converted to 0-1.
A12: M14 | B12: Loekito, Dani, Zulfikar, Triarso & Prasetyono | C12: 2026 | D12: Factors influencing construction worker productivity in Indonesia and strategies for improvement | E12: Multidisciplinary Science Journal 8: e2026243 | F12: 10.31893/multiscience.2026243 | G12: Indonesia (East Java) | H12: Construction WORKERS' perspective | I12: No | J12: 83 | K12: 1-4 | L12: Table 2, p.5 | M12: Read from the PDF (Research_Papers/5_Masonry_Productivity_Delay) | N12: Validation | O12: Published online 2025. Decimal commas in the PDF converted to points.
A13: A10 | B13: Pinky Devi & Sindhu | C13: 2025 | D13: Delay analysis of infrastructure construction projects in India | E13: Journal of The Institution of Engineers (India): Series A | F13: 10.1007/s40030-025-00899-5 | G13: India | H13: Infrastructure (roads, bridges), NOT buildings | I13: No | J13: 72 | K13: Not recorded | L13: RII table | M13: From the research notes (summary of the full text; lower confidence) | N13: Validation | O13: Only 2 tool risks overlap, too few for a rank correlation. Notes list the group 'material-related issues' as rank 1 although item values are higher; recheck the paper.
A14: A21 | B14: Ouansrimeang & Wisaeang | C14: 2024 | D14: Analyzing the critical delay factors for construction projects in the public sector using relative importance index and machine learning techniques | E14: Journal of Infrastructure, Policy and Development 8(8): 6208 | F14: 10.24294/jipd.v8i8.6208 | G14: Thailand | H14: 30 delayed public projects | I14: No | J14: 30 projects | K14: Not recorded | L14: Results section | M14: From the research notes (full text read) | N14: Validation | O14: Labour issues: 0.773 in the abstract but 0.733 in the results text; 0.733 is used here.
A15: HAS25 | B15: Hassoon et al. | C15: 2025 | D15: (brickwork / housing skeleton tasks, Iraq) | E15: Journal of Infrastructure Preservation and Resilience 6, art. 3 | F15: 10.1186/s43065-025-00116-4 | G15: Iraq | H15: Brickwork and housing skeleton tasks | I15: Yes | J15: Not recorded | K15: Not recorded | L15: Abstract | M15: From the research notes (abstract only) | N15: Validation | O15: Abstract gives only two values. Not in the tool's evidence store.

Sheet RII_Data
A1: Every RII value recorded, one row per factor as printed in the paper
A2: Blue = copied from the paper. Green = looked up from Studies. Black = formula. Yellow = mapping judgement (Direct / Related / blank).
A4: Study ID | B4: Country | C4: Role | D4: Factor (as printed) | E4: RII (0-1) | F4: Rank in study | G4: Tool risk | H4: Mapping | I4: Used by the model? | J4: Note | K4: z-score within study
A5: M01 | B5: =INDEX(Studies!$G$5:$G$15,MATCH(A5,Studies!$A$5:$A$15,0)) -> India (Telangana) | C5: =INDEX(Studies!$N$5:$N$15,MATCH(A5,Studies!$A$5:$A$15,0)) -> Seed | D5: Unsafe working conditions | E5: 0.809 | F5: 1 | G5: R-SAFE | H5: Direct | I5: =IF(AND(C5="Seed",H5="Direct",G5<>""),"Yes","No") -> Yes | K5: =IF(OR(INDEX(Standardised!$B$5:$B$15,MATCH(A5,Standardised!$A$5:$A$15,0))="Complete",INDEX(Standardised!$B$5:$B$15,MATCH(A5,Standardised!$A$5:$A$15,0))="Truncated"),(E5-INDEX(Standardised!$D$5:$D$15,MATCH(A5,Standardised!$A$5:$A$15,0)))/INDEX(Standardised!$E$5:$E$15,MATCH(A5,Standardised!$A$5:$A$15,0)),"") -> 2.2101465
A6: M01 | B6: =INDEX(Studies!$G$5:$G$15,MATCH(A6,Studies!$A$5:$A$15,0)) -> India (Telangana) | C6: =INDEX(Studies!$N$5:$N$15,MATCH(A6,Studies!$A$5:$A$15,0)) -> Seed | D6: Poor work planning | E6: 0.791 | F6: 2 | G6: R-PLAN | H6: Direct | I6: =IF(AND(C6="Seed",H6="Direct",G6<>""),"Yes","No") -> Yes | K6: =IF(OR(INDEX(Standardised!$B$5:$B$15,MATCH(A6,Standardised!$A$5:$A$15,0))="Complete",INDEX(Standardised!$B$5:$B$15,MATCH(A6,Standardised!$A$5:$A$15,0))="Truncated"),(E6-INDEX(Standardised!$D$5:$D$15,MATCH(A6,Standardised!$A$5:$A$15,0)))/INDEX(Standardised!$E$5:$E$15,MATCH(A6,Standardised!$A$5:$A$15,0)),"") -> 1.5552883
A7: M01 | B7: =INDEX(Studies!$G$5:$G$15,MATCH(A7,Studies!$A$5:$A$15,0)) -> India (Telangana) | C7: =INDEX(Studies!$N$5:$N$15,MATCH(A7,Studies!$A$5:$A$15,0)) -> Seed | D7: Unrealistic scheduling | E7: 0.791 | F7: 3 | G7: R-PLAN | H7: Direct | I7: =IF(AND(C7="Seed",H7="Direct",G7<>""),"Yes","No") -> Yes | K7: =IF(OR(INDEX(Standardised!$B$5:$B$15,MATCH(A7,Standardised!$A$5:$A$15,0))="Complete",INDEX(Standardised!$B$5:$B$15,MATCH(A7,Standardised!$A$5:$A$15,0))="Truncated"),(E7-INDEX(Standardised!$D$5:$D$15,MATCH(A7,Standardised!$A$5:$A$15,0)))/INDEX(Standardised!$E$5:$E$15,MATCH(A7,Standardised!$A$5:$A$15,0)),"") -> 1.5552883
A8: M01 | B8: =INDEX(Studies!$G$5:$G$15,MATCH(A8,Studies!$A$5:$A$15,0)) -> India (Telangana) | C8: =INDEX(Studies!$N$5:$N$15,MATCH(A8,Studies!$A$5:$A$15,0)) -> Seed | D8: Little or no financial rewards | E8: 0.777 | F8: 4 | G8: R-INC | H8: Direct | I8: =IF(AND(C8="Seed",H8="Direct",G8<>""),"Yes","No") -> Yes | K8: =IF(OR(INDEX(Standardised!$B$5:$B$15,MATCH(A8,Standardised!$A$5:$A$15,0))="Complete",INDEX(Standardised!$B$5:$B$15,MATCH(A8,Standardised!$A$5:$A$15,0))="Truncated"),(E8-INDEX(Standardised!$D$5:$D$15,MATCH(A8,Standardised!$A$5:$A$15,0)))/INDEX(Standardised!$E$5:$E$15,MATCH(A8,Standardised!$A$5:$A$15,0)),"") -> 1.0459541
A9: M01 | B9: =INDEX(Studies!$G$5:$G$15,MATCH(A9,Studies!$A$5:$A$15,0)) -> India (Telangana) | C9: =INDEX(Studies!$N$5:$N$15,MATCH(A9,Studies!$A$5:$A$15,0)) -> Seed | D9: Material shortages | E9: 0.777 | F9: 5 | G9: R-MAT | H9: Direct | I9: =IF(AND(C9="Seed",H9="Direct",G9<>""),"Yes","No") -> Yes | K9: =IF(OR(INDEX(Standardised!$B$5:$B$15,MATCH(A9,Standardised!$A$5:$A$15,0))="Complete",INDEX(Standardised!$B$5:$B$15,MATCH(A9,Standardised!$A$5:$A$15,0))="Truncated"),(E9-INDEX(Standardised!$D$5:$D$15,MATCH(A9,Standardised!$A$5:$A$15,0)))/INDEX(Standardised!$E$5:$E$15,MATCH(A9,Standardised!$A$5:$A$15,0)),"") -> 1.0459541
A10: M01 | B10: =INDEX(Studies!$G$5:$G$15,MATCH(A10,Studies!$A$5:$A$15,0)) -> India (Telangana) | C10: =INDEX(Studies!$N$5:$N$15,MATCH(A10,Studies!$A$5:$A$15,0)) -> Seed | D10: Payment delay | E10: 0.773 | F10: 6 | G10: R-PAY | H10: Direct | I10: =IF(AND(C10="Seed",H10="Direct",G10<>""),"Yes","No") -> Yes | K10: =IF(OR(INDEX(Standardised!$B$5:$B$15,MATCH(A10,Standardised!$A$5:$A$15,0))="Complete",INDEX(Standardised!$B$5:$B$15,MATCH(A10,Standardised!$A$5:$A$15,0))="Truncated"),(E10-INDEX(Standardised!$D$5:$D$15,MATCH(A10,Standardised!$A$5:$A$15,0)))/INDEX(Standardised!$E$5:$E$15,MATCH(A10,Standardised!$A$5:$A$15,0)),"") -> 0.90043006
A11: M01 | B11: =INDEX(Studies!$G$5:$G$15,MATCH(A11,Studies!$A$5:$A$15,0)) -> India (Telangana) | C11: =INDEX(Studies!$N$5:$N$15,MATCH(A11,Studies!$A$5:$A$15,0)) -> Seed | D11: Working at heights | E11: 0.764 | F11: 7 | G11: R-SAFE | H11: Direct | I11: =IF(AND(C11="Seed",H11="Direct",G11<>""),"Yes","No") -> Yes | K11: =IF(OR(INDEX(Standardised!$B$5:$B$15,MATCH(A11,Standardised!$A$5:$A$15,0))="Complete",INDEX(Standardised!$B$5:$B$15,MATCH(A11,Standardised!$A$5:$A$15,0))="Truncated"),(E11-INDEX(Standardised!$D$5:$D$15,MATCH(A11,Standardised!$A$5:$A$15,0)))/INDEX(Standardised!$E$5:$E$15,MATCH(A11,Standardised!$A$5:$A$15,0)),"") -> 0.57300095
A12: M01 | B12: =INDEX(Studies!$G$5:$G$15,MATCH(A12,Studies!$A$5:$A$15,0)) -> India (Telangana) | C12: =INDEX(Studies!$N$5:$N$15,MATCH(A12,Studies!$A$5:$A$15,0)) -> Seed | D12: Weather conditions | E12: 0.764 | F12: 8 | G12: R-WX | H12: Direct | I12: =IF(AND(C12="Seed",H12="Direct",G12<>""),"Yes","No") -> Yes | K12: =IF(OR(INDEX(Standardised!$B$5:$B$15,MATCH(A12,Standardised!$A$5:$A$15,0))="Complete",INDEX(Standardised!$B$5:$B$15,MATCH(A12,Standardised!$A$5:$A$15,0))="Truncated"),(E12-INDEX(Standardised!$D$5:$D$15,MATCH(A12,Standardised!$A$5:$A$15,0)))/INDEX(Standardised!$E$5:$E$15,MATCH(A12,Standardised!$A$5:$A$15,0)),"") -> 0.57300095
A13: M01 | B13: =INDEX(Studies!$G$5:$G$15,MATCH(A13,Studies!$A$5:$A$15,0)) -> India (Telangana) | C13: =INDEX(Studies!$N$5:$N$15,MATCH(A13,Studies!$A$5:$A$15,0)) -> Seed | D13: Lack of skill and experience of worker | E13: 0.759 | F13: 9 | G13: R-SKILL | H13: Direct | I13: =IF(AND(C13="Seed",H13="Direct",G13<>""),"Yes","No") -> Yes | K13: =IF(OR(INDEX(Standardised!$B$5:$B$15,MATCH(A13,Standardised!$A$5:$A$15,0))="Complete",INDEX(Standardised!$B$5:$B$15,MATCH(A13,Standardised!$A$5:$A$15,0))="Truncated"),(E13-INDEX(Standardised!$D$5:$D$15,MATCH(A13,Standardised!$A$5:$A$15,0)))/INDEX(Standardised!$E$5:$E$15,MATCH(A13,Standardised!$A$5:$A$15,0)),"") -> 0.39109588
A14: M01 | B14: =INDEX(Studies!$G$5:$G$15,MATCH(A14,Studies!$A$5:$A$15,0)) -> India (Telangana) | C14: =INDEX(Studies!$N$5:$N$15,MATCH(A14,Studies!$A$5:$A$15,0)) -> Seed | D14: Poor or no supervision method | E14: 0.759 | F14: 10 | G14: R-SUP | H14: Direct | I14: =IF(AND(C14="Seed",H14="Direct",G14<>""),"Yes","No") -> Yes | K14: =IF(OR(INDEX(Standardised!$B$5:$B$15,MATCH(A14,Standardised!$A$5:$A$15,0))="Complete",INDEX(Standardised!$B$5:$B$15,MATCH(A14,Standardised!$A$5:$A$15,0))="Truncated"),(E14-INDEX(Standardised!$D$5:$D$15,MATCH(A14,Standardised!$A$5:$A$15,0)))/INDEX(Standardised!$E$5:$E$15,MATCH(A14,Standardised!$A$5:$A$15,0)),"") -> 0.39109588
A15: M01 | B15: =INDEX(Studies!$G$5:$G$15,MATCH(A15,Studies!$A$5:$A$15,0)) -> India (Telangana) | C15: =INDEX(Studies!$N$5:$N$15,MATCH(A15,Studies!$A$5:$A$15,0)) -> Seed | D15: Incompetent supervisors | E15: 0.759 | F15: 11 | G15: R-SUP | H15: Direct | I15: =IF(AND(C15="Seed",H15="Direct",G15<>""),"Yes","No") -> Yes | K15: =IF(OR(INDEX(Standardised!$B$5:$B$15,MATCH(A15,Standardised!$A$5:$A$15,0))="Complete",INDEX(Standardised!$B$5:$B$15,MATCH(A15,Standardised!$A$5:$A$15,0))="Truncated"),(E15-INDEX(Standardised!$D$5:$D$15,MATCH(A15,Standardised!$A$5:$A$15,0)))/INDEX(Standardised!$E$5:$E$15,MATCH(A15,Standardised!$A$5:$A$15,0)),"") -> 0.39109588
A16: M01 | B16: =INDEX(Studies!$G$5:$G$15,MATCH(A16,Studies!$A$5:$A$15,0)) -> India (Telangana) | C16: =INDEX(Studies!$N$5:$N$15,MATCH(A16,Studies!$A$5:$A$15,0)) -> Seed | D16: Accidents | E16: 0.759 | F16: 12 | G16: R-ACC | H16: Direct | I16: =IF(AND(C16="Seed",H16="Direct",G16<>""),"Yes","No") -> Yes | J16: an outcome of unsafe conditions, not the condition itself | K16: =IF(OR(INDEX(Standardised!$B$5:$B$15,MATCH(A16,Standardised!$A$5:$A$15,0))="Complete",INDEX(Standardised!$B$5:$B$15,MATCH(A16,Standardised!$A$5:$A$15,0))="Truncated"),(E16-INDEX(Standardised!$D$5:$D$15,MATCH(A16,Standardised!$A$5:$A$15,0)))/INDEX(Standardised!$E$5:$E$15,MATCH(A16,Standardised!$A$5:$A$15,0)),"") -> 0.39109588
A17: M01 | B17: =INDEX(Studies!$G$5:$G$15,MATCH(A17,Studies!$A$5:$A$15,0)) -> India (Telangana) | C17: =INDEX(Studies!$N$5:$N$15,MATCH(A17,Studies!$A$5:$A$15,0)) -> Seed | D17: Poor relation between labour and superintendents | E17: 0.755 | F17: 13 | G17: R-COM | H17: Related | I17: =IF(AND(C17="Seed",H17="Direct",G17<>""),"Yes","No") -> No | K17: =IF(OR(INDEX(Standardised!$B$5:$B$15,MATCH(A17,Standardised!$A$5:$A$15,0))="Complete",INDEX(Standardised!$B$5:$B$15,MATCH(A17,Standardised!$A$5:$A$15,0))="Truncated"),(E17-INDEX(Standardised!$D$5:$D$15,MATCH(A17,Standardised!$A$5:$A$15,0)))/INDEX(Standardised!$E$5:$E$15,MATCH(A17,Standardised!$A$5:$A$15,0)),"") -> 0.24557183
A18: M01 | B18: =INDEX(Studies!$G$5:$G$15,MATCH(A18,Studies!$A$5:$A$15,0)) -> India (Telangana) | C18: =INDEX(Studies!$N$5:$N$15,MATCH(A18,Studies!$A$5:$A$15,0)) -> Seed | D18: Poor condition of equipment and tools | E18: 0.75 | F18: 14 | G18: R-TOOL | H18: Direct | I18: =IF(AND(C18="Seed",H18="Direct",G18<>""),"Yes","No") -> Yes | K18: =IF(OR(INDEX(Standardised!$B$5:$B$15,MATCH(A18,Standardised!$A$5:$A$15,0))="Complete",INDEX(Standardised!$B$5:$B$15,MATCH(A18,Standardised!$A$5:$A$15,0))="Truncated"),(E18-INDEX(Standardised!$D$5:$D$15,MATCH(A18,Standardised!$A$5:$A$15,0)))/INDEX(Standardised!$E$5:$E$15,MATCH(A18,Standardised!$A$5:$A$15,0)),"") -> 0.063666772
A19: M01 | B19: =INDEX(Studies!$G$5:$G$15,MATCH(A19,Studies!$A$5:$A$15,0)) -> India (Telangana) | C19: =INDEX(Studies!$N$5:$N$15,MATCH(A19,Studies!$A$5:$A$15,0)) -> Seed | D19: Bad leadership skill | E19: 0.75 | F19: 15 | G19: R-DIS | H19: Direct | I19: =IF(AND(C19="Seed",H19="Direct",G19<>""),"Yes","No") -> Yes | K19: =IF(OR(INDEX(Standardised!$B$5:$B$15,MATCH(A19,Standardised!$A$5:$A$15,0))="Complete",INDEX(Standardised!$B$5:$B$15,MATCH(A19,Standardised!$A$5:$A$15,0))="Truncated"),(E19-INDEX(Standardised!$D$5:$D$15,MATCH(A19,Standardised!$A$5:$A$15,0)))/INDEX(Standardised!$E$5:$E$15,MATCH(A19,Standardised!$A$5:$A$15,0)),"") -> 0.063666772
A20: M01 | B20: =INDEX(Studies!$G$5:$G$15,MATCH(A20,Studies!$A$5:$A$15,0)) -> India (Telangana) | C20: =INDEX(Studies!$N$5:$N$15,MATCH(A20,Studies!$A$5:$A$15,0)) -> Seed | D20: Working 7 days per week | E20: 0.741 | F20: 16 | G20: R-OVT | H20: Direct | I20: =IF(AND(C20="Seed",H20="Direct",G20<>""),"Yes","No") -> Yes | K20: =IF(OR(INDEX(Standardised!$B$5:$B$15,MATCH(A20,Standardised!$A$5:$A$15,0))="Complete",INDEX(Standardised!$B$5:$B$15,MATCH(A20,Standardised!$A$5:$A$15,0))="Truncated"),(E20-INDEX(Standardised!$D$5:$D$15,MATCH(A20,Standardised!$A$5:$A$15,0)))/INDEX(Standardised!$E$5:$E$15,MATCH(A20,Standardised!$A$5:$A$15,0)),"") -> -0.26376234
A21: M01 | B21: =INDEX(Studies!$G$5:$G$15,MATCH(A21,Studies!$A$5:$A$15,0)) -> India (Telangana) | C21: =INDEX(Studies!$N$5:$N$15,MATCH(A21,Studies!$A$5:$A$15,0)) -> Seed | D21: Equipment and tools shortages | E21: 0.741 | F21: 17 | G21: R-TOOL | H21: Direct | I21: =IF(AND(C21="Seed",H21="Direct",G21<>""),"Yes","No") -> Yes | K21: =IF(OR(INDEX(Standardised!$B$5:$B$15,MATCH(A21,Standardised!$A$5:$A$15,0))="Complete",INDEX(Standardised!$B$5:$B$15,MATCH(A21,Standardised!$A$5:$A$15,0))="Truncated"),(E21-INDEX(Standardised!$D$5:$D$15,MATCH(A21,Standardised!$A$5:$A$15,0)))/INDEX(Standardised!$E$5:$E$15,MATCH(A21,Standardised!$A$5:$A$15,0)),"") -> -0.26376234
A22: M01 | B22: =INDEX(Studies!$G$5:$G$15,MATCH(A22,Studies!$A$5:$A$15,0)) -> India (Telangana) | C22: =INDEX(Studies!$N$5:$N$15,MATCH(A22,Studies!$A$5:$A$15,0)) -> Seed | D22: Low labour morale/commitment | E22: 0.736 | F22: 18 | G22: R-MOT | H22: Direct | I22: =IF(AND(C22="Seed",H22="Direct",G22<>""),"Yes","No") -> Yes | K22: =IF(OR(INDEX(Standardised!$B$5:$B$15,MATCH(A22,Standardised!$A$5:$A$15,0))="Complete",INDEX(Standardised!$B$5:$B$15,MATCH(A22,Standardised!$A$5:$A$15,0))="Truncated"),(E22-INDEX(Standardised!$D$5:$D$15,MATCH(A22,Standardised!$A$5:$A$15,0)))/INDEX(Standardised!$E$5:$E$15,MATCH(A22,Standardised!$A$5:$A$15,0)),"") -> -0.4456674
A23: M01 | B23: =INDEX(Studies!$G$5:$G$15,MATCH(A23,Studies!$A$5:$A$15,0)) -> India (Telangana) | C23: =INDEX(Studies!$N$5:$N$15,MATCH(A23,Studies!$A$5:$A$15,0)) -> Seed | D23: Rework | E23: 0.736 | F23: 19 | G23: R-RWK | H23: Direct | I23: =IF(AND(C23="Seed",H23="Direct",G23<>""),"Yes","No") -> Yes | K23: =IF(OR(INDEX(Standardised!$B$5:$B$15,MATCH(A23,Standardised!$A$5:$A$15,0))="Complete",INDEX(Standardised!$B$5:$B$15,MATCH(A23,Standardised!$A$5:$A$15,0))="Truncated"),(E23-INDEX(Standardised!$D$5:$D$15,MATCH(A23,Standardised!$A$5:$A$15,0)))/INDEX(Standardised!$E$5:$E$15,MATCH(A23,Standardised!$A$5:$A$15,0)),"") -> -0.4456674
A24: M01 | B24: =INDEX(Studies!$G$5:$G$15,MATCH(A24,Studies!$A$5:$A$15,0)) -> India (Telangana) | C24: =INDEX(Studies!$N$5:$N$15,MATCH(A24,Studies!$A$5:$A$15,0)) -> Seed | D24: Lack of empowerment | E24: 0.732 | F24: 20 | G24: R-MOT | H24: Related | I24: =IF(AND(C24="Seed",H24="Direct",G24<>""),"Yes","No") -> No | K24: =IF(OR(INDEX(Standardised!$B$5:$B$15,MATCH(A24,Standardised!$A$5:$A$15,0))="Complete",INDEX(Standardised!$B$5:$B$15,MATCH(A24,Standardised!$A$5:$A$15,0))="Truncated"),(E24-INDEX(Standardised!$D$5:$D$15,MATCH(A24,Standardised!$A$5:$A$15,0)))/INDEX(Standardised!$E$5:$E$15,MATCH(A24,Standardised!$A$5:$A$15,0)),"") -> -0.59119145
A25: M01 | B25: =INDEX(Studies!$G$5:$G$15,MATCH(A25,Studies!$A$5:$A$15,0)) -> India (Telangana) | C25: =INDEX(Studies!$N$5:$N$15,MATCH(A25,Studies!$A$5:$A$15,0)) -> Seed | D25: Change order during execution | E25: 0.732 | F25: 21 | G25: R-DES | H25: Direct | I25: =IF(AND(C25="Seed",H25="Direct",G25<>""),"Yes","No") -> Yes | K25: =IF(OR(INDEX(Standardised!$B$5:$B$15,MATCH(A25,Standardised!$A$5:$A$15,0))="Complete",INDEX(Standardised!$B$5:$B$15,MATCH(A25,Standardised!$A$5:$A$15,0))="Truncated"),(E25-INDEX(Standardised!$D$5:$D$15,MATCH(A25,Standardised!$A$5:$A$15,0)))/INDEX(Standardised!$E$5:$E$15,MATCH(A25,Standardised!$A$5:$A$15,0)),"") -> -0.59119145
A26: M01 | B26: =INDEX(Studies!$G$5:$G$15,MATCH(A26,Studies!$A$5:$A$15,0)) -> India (Telangana) | C26: =INDEX(Studies!$N$5:$N$15,MATCH(A26,Studies!$A$5:$A$15,0)) -> Seed | D26: Low amount of pay | E26: 0.727 | F26: 22 | G26: R-INC | H26: Direct | I26: =IF(AND(C26="Seed",H26="Direct",G26<>""),"Yes","No") -> Yes | K26: =IF(OR(INDEX(Standardised!$B$5:$B$15,MATCH(A26,Standardised!$A$5:$A$15,0))="Complete",INDEX(Standardised!$B$5:$B$15,MATCH(A26,Standardised!$A$5:$A$15,0))="Truncated"),(E26-INDEX(Standardised!$D$5:$D$15,MATCH(A26,Standardised!$A$5:$A$15,0)))/INDEX(Standardised!$E$5:$E$15,MATCH(A26,Standardised!$A$5:$A$15,0)),"") -> -0.77309652
A27: M01 | B27: =INDEX(Studies!$G$5:$G$15,MATCH(A27,Studies!$A$5:$A$15,0)) -> India (Telangana) | C27: =INDEX(Studies!$N$5:$N$15,MATCH(A27,Studies!$A$5:$A$15,0)) -> Seed | D27: High workforce absenteeism | E27: 0.723 | F27: 23 | G27: R-LAB | H27: Direct | I27: =IF(AND(C27="Seed",H27="Direct",G27<>""),"Yes","No") -> Yes | K27: =IF(OR(INDEX(Standardised!$B$5:$B$15,MATCH(A27,Standardised!$A$5:$A$15,0))="Complete",INDEX(Standardised!$B$5:$B$15,MATCH(A27,Standardised!$A$5:$A$15,0))="Truncated"),(E27-INDEX(Standardised!$D$5:$D$15,MATCH(A27,Standardised!$A$5:$A$15,0)))/INDEX(Standardised!$E$5:$E$15,MATCH(A27,Standardised!$A$5:$A$15,0)),"") -> -0.91862057
A28: M01 | B28: =INDEX(Studies!$G$5:$G$15,MATCH(A28,Studies!$A$5:$A$15,0)) -> India (Telangana) | C28: =INDEX(Studies!$N$5:$N$15,MATCH(A28,Studies!$A$5:$A$15,0)) -> Seed | D28: Lack of labour surveillance | E28: 0.714 | F28: 24 | G28: R-SUP | H28: Direct | I28: =IF(AND(C28="Seed",H28="Direct",G28<>""),"Yes","No") -> Yes | K28: =IF(OR(INDEX(Standardised!$B$5:$B$15,MATCH(A28,Standardised!$A$5:$A$15,0))="Complete",INDEX(Standardised!$B$5:$B$15,MATCH(A28,Standardised!$A$5:$A$15,0))="Truncated"),(E28-INDEX(Standardised!$D$5:$D$15,MATCH(A28,Standardised!$A$5:$A$15,0)))/INDEX(Standardised!$E$5:$E$15,MATCH(A28,Standardised!$A$5:$A$15,0)),"") -> -1.2460497
A29: M01 | B29: =INDEX(Studies!$G$5:$G$15,MATCH(A29,Studies!$A$5:$A$15,0)) -> India (Telangana) | C29: =INDEX(Studies!$N$5:$N$15,MATCH(A29,Studies!$A$5:$A$15,0)) -> Seed | D29: Inadequate safety plan | E29: 0.714 | F29: 25 | G29: R-SAFE | H29: Related | I29: =IF(AND(C29="Seed",H29="Direct",G29<>""),"Yes","No") -> No | J29: a management cause, broader than the site condition | K29: =IF(OR(INDEX(Standardised!$B$5:$B$15,MATCH(A29,Standardised!$A$5:$A$15,0))="Complete",INDEX(Standardised!$B$5:$B$15,MATCH(A29,Standardised!$A$5:$A$15,0))="Truncated"),(E29-INDEX(Standardised!$D$5:$D$15,MATCH(A29,Standardised!$A$5:$A$15,0)))/INDEX(Standardised!$E$5:$E$15,MATCH(A29,Standardised!$A$5:$A$15,0)),"") -> -1.2460497
A30: M01 | B30: =INDEX(Studies!$G$5:$G$15,MATCH(A30,Studies!$A$5:$A$15,0)) -> India (Telangana) | C30: =INDEX(Studies!$N$5:$N$15,MATCH(A30,Studies!$A$5:$A$15,0)) -> Seed | D30: Frequency of working overtime | E30: 0.709 | F30: 26 | G30: R-OVT | H30: Direct | I30: =IF(AND(C30="Seed",H30="Direct",G30<>""),"Yes","No") -> Yes | K30: =IF(OR(INDEX(Standardised!$B$5:$B$15,MATCH(A30,Standardised!$A$5:$A$15,0))="Complete",INDEX(Standardised!$B$5:$B$15,MATCH(A30,Standardised!$A$5:$A$15,0))="Truncated"),(E30-INDEX(Standardised!$D$5:$D$15,MATCH(A30,Standardised!$A$5:$A$15,0)))/INDEX(Standardised!$E$5:$E$15,MATCH(A30,Standardised!$A$5:$A$15,0)),"") -> -1.4279547
A31: M01 | B31: =INDEX(Studies!$G$5:$G$15,MATCH(A31,Studies!$A$5:$A$15,0)) -> India (Telangana) | C31: =INDEX(Studies!$N$5:$N$15,MATCH(A31,Studies!$A$5:$A$15,0)) -> Seed | D31: Effectiveness of management system | E31: 0.709 | F31: 27 | G31: R-MGT | H31: Direct | I31: =IF(AND(C31="Seed",H31="Direct",G31<>""),"Yes","No") -> Yes | K31: =IF(OR(INDEX(Standardised!$B$5:$B$15,MATCH(A31,Standardised!$A$5:$A$15,0))="Complete",INDEX(Standardised!$B$5:$B$15,MATCH(A31,Standardised!$A$5:$A$15,0))="Truncated"),(E31-INDEX(Standardised!$D$5:$D$15,MATCH(A31,Standardised!$A$5:$A$15,0)))/INDEX(Standardised!$E$5:$E$15,MATCH(A31,Standardised!$A$5:$A$15,0)),"") -> -1.4279547
A32: M01 | B32: =INDEX(Studies!$G$5:$G$15,MATCH(A32,Studies!$A$5:$A$15,0)) -> India (Telangana) | C32: =INDEX(Studies!$N$5:$N$15,MATCH(A32,Studies!$A$5:$A$15,0)) -> Seed | D32: Method of construction | E32: 0.7 | F32: 28 | G32: R-MTH | H32: Direct | I32: =IF(AND(C32="Seed",H32="Direct",G32<>""),"Yes","No") -> Yes | K32: =IF(OR(INDEX(Standardised!$B$5:$B$15,MATCH(A32,Standardised!$A$5:$A$15,0))="Complete",INDEX(Standardised!$B$5:$B$15,MATCH(A32,Standardised!$A$5:$A$15,0))="Truncated"),(E32-INDEX(Standardised!$D$5:$D$15,MATCH(A32,Standardised!$A$5:$A$15,0)))/INDEX(Standardised!$E$5:$E$15,MATCH(A32,Standardised!$A$5:$A$15,0)),"") -> -1.7553839
A33: A02 | B33: =INDEX(Studies!$G$5:$G$15,MATCH(A33,Studies!$A$5:$A$15,0)) -> India (Chennai) | C33: =INDEX(Studies!$N$5:$N$15,MATCH(A33,Studies!$A$5:$A$15,0)) -> Seed | D33: Lack of experience (manpower) | E33: 0.787 | F33: 1 | G33: R-SKILL | H33: Direct | I33: =IF(AND(C33="Seed",H33="Direct",G33<>""),"Yes","No") -> Yes | J33: rank within Table 1 (manpower) | K33: =IF(OR(INDEX(Standardised!$B$5:$B$15,MATCH(A33,Standardised!$A$5:$A$15,0))="Complete",INDEX(Standardised!$B$5:$B$15,MATCH(A33,Standardised!$A$5:$A$15,0))="Truncated"),(E33-INDEX(Standardised!$D$5:$D$15,MATCH(A33,Standardised!$A$5:$A$15,0)))/INDEX(Standardised!$E$5:$E$15,MATCH(A33,Standardised!$A$5:$A$15,0)),"")
A34: A02 | B34: =INDEX(Studies!$G$5:$G$15,MATCH(A34,Studies!$A$5:$A$15,0)) -> India (Chennai) | C34: =INDEX(Studies!$N$5:$N$15,MATCH(A34,Studies!$A$5:$A$15,0)) -> Seed | D34: Absenteeism | E34: 0.751 | F34: 2 | G34: R-LAB | H34: Direct | I34: =IF(AND(C34="Seed",H34="Direct",G34<>""),"Yes","No") -> Yes | J34: rank within Table 1 (manpower) | K34: =IF(OR(INDEX(Standardised!$B$5:$B$15,MATCH(A34,Standardised!$A$5:$A$15,0))="Complete",INDEX(Standardised!$B$5:$B$15,MATCH(A34,Standardised!$A$5:$A$15,0))="Truncated"),(E34-INDEX(Standardised!$D$5:$D$15,MATCH(A34,Standardised!$A$5:$A$15,0)))/INDEX(Standardised!$E$5:$E$15,MATCH(A34,Standardised!$A$5:$A$15,0)),"")
A35: A02 | B35: =INDEX(Studies!$G$5:$G$15,MATCH(A35,Studies!$A$5:$A$15,0)) -> India (Chennai) | C35: =INDEX(Studies!$N$5:$N$15,MATCH(A35,Studies!$A$5:$A$15,0)) -> Seed | D35: Age | E35: 0.73 | G35: R-FAT | H35: Related | I35: =IF(AND(C35="Seed",H35="Direct",G35<>""),"Yes","No") -> No | J35: Table 1 (manpower) | K35: =IF(OR(INDEX(Standardised!$B$5:$B$15,MATCH(A35,Standardised!$A$5:$A$15,0))="Complete",INDEX(Standardised!$B$5:$B$15,MATCH(A35,Standardised!$A$5:$A$15,0))="Truncated"),(E35-INDEX(Standardised!$D$5:$D$15,MATCH(A35,Standardised!$A$5:$A$15,0)))/INDEX(Standardised!$E$5:$E$15,MATCH(A35,Standardised!$A$5:$A$15,0)),"")
A36: A02 | B36: =INDEX(Studies!$G$5:$G$15,MATCH(A36,Studies!$A$5:$A$15,0)) -> India (Chennai) | C36: =INDEX(Studies!$N$5:$N$15,MATCH(A36,Studies!$A$5:$A$15,0)) -> Seed | D36: Misunderstanding among labourers | E36: 0.68 | G36: R-COM | H36: Direct | I36: =IF(AND(C36="Seed",H36="Direct",G36<>""),"Yes","No") -> Yes | J36: Table 1 (manpower) | K36: =IF(OR(INDEX(Standardised!$B$5:$B$15,MATCH(A36,Standardised!$A$5:$A$15,0))="Complete",INDEX(Standardised!$B$5:$B$15,MATCH(A36,Standardised!$A$5:$A$15,0))="Truncated"),(E36-INDEX(Standardised!$D$5:$D$15,MATCH(A36,Standardised!$A$5:$A$15,0)))/INDEX(Standardised!$E$5:$E$15,MATCH(A36,Standardised!$A$5:$A$15,0)),"")
A37: A02 | B37: =INDEX(Studies!$G$5:$G$15,MATCH(A37,Studies!$A$5:$A$15,0)) -> India (Chennai) | C37: =INDEX(Studies!$N$5:$N$15,MATCH(A37,Studies!$A$5:$A$15,0)) -> Seed | D37: Accidents | E37: 0.65 | G37: R-ACC | H37: Direct | I37: =IF(AND(C37="Seed",H37="Direct",G37<>""),"Yes","No") -> Yes | J37: Table 1; an outcome, not the condition | K37: =IF(OR(INDEX(Standardised!$B$5:$B$15,MATCH(A37,Standardised!$A$5:$A$15,0))="Complete",INDEX(Standardised!$B$5:$B$15,MATCH(A37,Standardised!$A$5:$A$15,0))="Truncated"),(E37-INDEX(Standardised!$D$5:$D$15,MATCH(A37,Standardised!$A$5:$A$15,0)))/INDEX(Standardised!$E$5:$E$15,MATCH(A37,Standardised!$A$5:$A$15,0)),"")
A38: A02 | B38: =INDEX(Studies!$G$5:$G$15,MATCH(A38,Studies!$A$5:$A$15,0)) -> India (Chennai) | C38: =INDEX(Studies!$N$5:$N$15,MATCH(A38,Studies!$A$5:$A$15,0)) -> Seed | D38: Personal problems | E38: 0.61 | G38: R-FAT | H38: Direct | I38: =IF(AND(C38="Seed",H38="Direct",G38<>""),"Yes","No") -> Yes | J38: Table 1 (manpower) | K38: =IF(OR(INDEX(Standardised!$B$5:$B$15,MATCH(A38,Standardised!$A$5:$A$15,0))="Complete",INDEX(Standardised!$B$5:$B$15,MATCH(A38,Standardised!$A$5:$A$15,0))="Truncated"),(E38-INDEX(Standardised!$D$5:$D$15,MATCH(A38,Standardised!$A$5:$A$15,0)))/INDEX(Standardised!$E$5:$E$15,MATCH(A38,Standardised!$A$5:$A$15,0)),"")
A39: A02 | B39: =INDEX(Studies!$G$5:$G$15,MATCH(A39,Studies!$A$5:$A$15,0)) -> India (Chennai) | C39: =INDEX(Studies!$N$5:$N$15,MATCH(A39,Studies!$A$5:$A$15,0)) -> Seed | D39: Lack of required construction material | E39: 0.78 | F39: 1 | G39: R-MAT | H39: Direct | I39: =IF(AND(C39="Seed",H39="Direct",G39<>""),"Yes","No") -> Yes | J39: rank within Table 2 (resources) | K39: =IF(OR(INDEX(Standardised!$B$5:$B$15,MATCH(A39,Standardised!$A$5:$A$15,0))="Complete",INDEX(Standardised!$B$5:$B$15,MATCH(A39,Standardised!$A$5:$A$15,0))="Truncated"),(E39-INDEX(Standardised!$D$5:$D$15,MATCH(A39,Standardised!$A$5:$A$15,0)))/INDEX(Standardised!$E$5:$E$15,MATCH(A39,Standardised!$A$5:$A$15,0)),"")
A40: A02 | B40: =INDEX(Studies!$G$5:$G$15,MATCH(A40,Studies!$A$5:$A$15,0)) -> India (Chennai) | C40: =INDEX(Studies!$N$5:$N$15,MATCH(A40,Studies!$A$5:$A$15,0)) -> Seed | D40: Lack of tools/equipment | E40: 0.76 | G40: R-TOOL | H40: Direct | I40: =IF(AND(C40="Seed",H40="Direct",G40<>""),"Yes","No") -> Yes | J40: Table 2 (resources) | K40: =IF(OR(INDEX(Standardised!$B$5:$B$15,MATCH(A40,Standardised!$A$5:$A$15,0))="Complete",INDEX(Standardised!$B$5:$B$15,MATCH(A40,Standardised!$A$5:$A$15,0))="Truncated"),(E40-INDEX(Standardised!$D$5:$D$15,MATCH(A40,Standardised!$A$5:$A$15,0)))/INDEX(Standardised!$E$5:$E$15,MATCH(A40,Standardised!$A$5:$A$15,0)),"")
A41: A02 | B41: =INDEX(Studies!$G$5:$G$15,MATCH(A41,Studies!$A$5:$A$15,0)) -> India (Chennai) | C41: =INDEX(Studies!$N$5:$N$15,MATCH(A41,Studies!$A$5:$A$15,0)) -> Seed | D41: Poor site condition | E41: 0.751 | G41: R-SITE | H41: Direct | I41: =IF(AND(C41="Seed",H41="Direct",G41<>""),"Yes","No") -> Yes | J41: Table 2 (resources) | K41: =IF(OR(INDEX(Standardised!$B$5:$B$15,MATCH(A41,Standardised!$A$5:$A$15,0))="Complete",INDEX(Standardised!$B$5:$B$15,MATCH(A41,Standardised!$A$5:$A$15,0))="Truncated"),(E41-INDEX(Standardised!$D$5:$D$15,MATCH(A41,Standardised!$A$5:$A$15,0)))/INDEX(Standardised!$E$5:$E$15,MATCH(A41,Standardised!$A$5:$A$15,0)),"")
A42: A02 | B42: =INDEX(Studies!$G$5:$G$15,MATCH(A42,Studies!$A$5:$A$15,0)) -> India (Chennai) | C42: =INDEX(Studies!$N$5:$N$15,MATCH(A42,Studies!$A$5:$A$15,0)) -> Seed | D42: Material storage location | E42: 0.7 | G42: R-STO | H42: Direct | I42: =IF(AND(C42="Seed",H42="Direct",G42<>""),"Yes","No") -> Yes | J42: Table 2 (resources) | K42: =IF(OR(INDEX(Standardised!$B$5:$B$15,MATCH(A42,Standardised!$A$5:$A$15,0))="Complete",INDEX(Standardised!$B$5:$B$15,MATCH(A42,Standardised!$A$5:$A$15,0))="Truncated"),(E42-INDEX(Standardised!$D$5:$D$15,MATCH(A42,Standardised!$A$5:$A$15,0)))/INDEX(Standardised!$E$5:$E$15,MATCH(A42,Standardised!$A$5:$A$15,0)),"")
A43: A02 | B43: =INDEX(Studies!$G$5:$G$15,MATCH(A43,Studies!$A$5:$A$15,0)) -> India (Chennai) | C43: =INDEX(Studies!$N$5:$N$15,MATCH(A43,Studies!$A$5:$A$15,0)) -> Seed | D43: Increase in price of material | E43: 0.55 | F43: 9 | G43: R-PRC | H43: Direct | I43: =IF(AND(C43="Seed",H43="Direct",G43<>""),"Yes","No") -> Yes | J43: rank within Table 2 (resources) | K43: =IF(OR(INDEX(Standardised!$B$5:$B$15,MATCH(A43,Standardised!$A$5:$A$15,0))="Complete",INDEX(Standardised!$B$5:$B$15,MATCH(A43,Standardised!$A$5:$A$15,0))="Truncated"),(E43-INDEX(Standardised!$D$5:$D$15,MATCH(A43,Standardised!$A$5:$A$15,0)))/INDEX(Standardised!$E$5:$E$15,MATCH(A43,Standardised!$A$5:$A$15,0)),"")
A44: A02 | B44: =INDEX(Studies!$G$5:$G$15,MATCH(A44,Studies!$A$5:$A$15,0)) -> India (Chennai) | C44: =INDEX(Studies!$N$5:$N$15,MATCH(A44,Studies!$A$5:$A$15,0)) -> Seed | D44: Payment delays | E44: 0.7758 | G44: R-PAY | H44: Direct | I44: =IF(AND(C44="Seed",H44="Direct",G44<>""),"Yes","No") -> Yes | J44: Fig. 1, printed as 775.8 on a 1000 scale | K44: =IF(OR(INDEX(Standardised!$B$5:$B$15,MATCH(A44,Standardised!$A$5:$A$15,0))="Complete",INDEX(Standardised!$B$5:$B$15,MATCH(A44,Standardised!$A$5:$A$15,0))="Truncated"),(E44-INDEX(Standardised!$D$5:$D$15,MATCH(A44,Standardised!$A$5:$A$15,0)))/INDEX(Standardised!$E$5:$E$15,MATCH(A44,Standardised!$A$5:$A$15,0)),"")
A45: A02 | B45: =INDEX(Studies!$G$5:$G$15,MATCH(A45,Studies!$A$5:$A$15,0)) -> India (Chennai) | C45: =INDEX(Studies!$N$5:$N$15,MATCH(A45,Studies!$A$5:$A$15,0)) -> Seed | D45: Weather condition | E45: 0.7 | F45: 3 | G45: R-WX | H45: Direct | I45: =IF(AND(C45="Seed",H45="Direct",G45<>""),"Yes","No") -> Yes | J45: Fig. 1, printed as 700 on a 1000 scale; rank within Fig. 1 | K45: =IF(OR(INDEX(Standardised!$B$5:$B$15,MATCH(A45,Standardised!$A$5:$A$15,0))="Complete",INDEX(Standardised!$B$5:$B$15,MATCH(A45,Standardised!$A$5:$A$15,0))="Truncated"),(E45-INDEX(Standardised!$D$5:$D$15,MATCH(A45,Standardised!$A$5:$A$15,0)))/INDEX(Standardised!$E$5:$E$15,MATCH(A45,Standardised!$A$5:$A$15,0)),"")
A46: A02 | B46: =INDEX(Studies!$G$5:$G$15,MATCH(A46,Studies!$A$5:$A$15,0)) -> India (Chennai) | C46: =INDEX(Studies!$N$5:$N$15,MATCH(A46,Studies!$A$5:$A$15,0)) -> Seed | D46: Shortage of water | E46: 0.65 | F46: 5 | G46: R-WAT | H46: Direct | I46: =IF(AND(C46="Seed",H46="Direct",G46<>""),"Yes","No") -> Yes | J46: Fig. 1; water is a mortar input but not brick/block supply | K46: =IF(OR(INDEX(Standardised!$B$5:$B$15,MATCH(A46,Standardised!$A$5:$A$15,0))="Complete",INDEX(Standardised!$B$5:$B$15,MATCH(A46,Standardised!$A$5:$A$15,0))="Truncated"),(E46-INDEX(Standardised!$D$5:$D$15,MATCH(A46,Standardised!$A$5:$A$15,0)))/INDEX(Standardised!$E$5:$E$15,MATCH(A46,Standardised!$A$5:$A$15,0)),"")
A47: M06 | B47: =INDEX(Studies!$G$5:$G$15,MATCH(A47,Studies!$A$5:$A$15,0)) -> India | C47: =INDEX(Studies!$N$5:$N$15,MATCH(A47,Studies!$A$5:$A$15,0)) -> Seed | D47: Availability of resources | E47: 0.80199 | F47: 1 | G47: R-MAT | H47: Related | I47: =IF(AND(C47="Seed",H47="Direct",G47<>""),"Yes","No") -> No | J47: covers material, labour and equipment together | K47: =IF(OR(INDEX(Standardised!$B$5:$B$15,MATCH(A47,Standardised!$A$5:$A$15,0))="Complete",INDEX(Standardised!$B$5:$B$15,MATCH(A47,Standardised!$A$5:$A$15,0))="Truncated"),(E47-INDEX(Standardised!$D$5:$D$15,MATCH(A47,Standardised!$A$5:$A$15,0)))/INDEX(Standardised!$E$5:$E$15,MATCH(A47,Standardised!$A$5:$A$15,0)),"") -> 1.5873283
A48: M06 | B48: =INDEX(Studies!$G$5:$G$15,MATCH(A48,Studies!$A$5:$A$15,0)) -> India | C48: =INDEX(Studies!$N$5:$N$15,MATCH(A48,Studies!$A$5:$A$15,0)) -> Seed | D48: Contractual disputes | E48: 0.799005 | F48: 2 | G48: R-CTR | H48: Direct | I48: =IF(AND(C48="Seed",H48="Direct",G48<>""),"Yes","No") -> Yes | K48: =IF(OR(INDEX(Standardised!$B$5:$B$15,MATCH(A48,Standardised!$A$5:$A$15,0))="Complete",INDEX(Standardised!$B$5:$B$15,MATCH(A48,Standardised!$A$5:$A$15,0))="Truncated"),(E48-INDEX(Standardised!$D$5:$D$15,MATCH(A48,Standardised!$A$5:$A$15,0)))/INDEX(Standardised!$E$5:$E$15,MATCH(A48,Standardised!$A$5:$A$15,0)),"") -> 1.5272227
A49: M06 | B49: =INDEX(Studies!$G$5:$G$15,MATCH(A49,Studies!$A$5:$A$15,0)) -> India | C49: =INDEX(Studies!$N$5:$N$15,MATCH(A49,Studies!$A$5:$A$15,0)) -> Seed | D49: Scope clarity of the project | E49: 0.79005 | F49: 3 | G49: R-SCP | H49: Direct | I49: =IF(AND(C49="Seed",H49="Direct",G49<>""),"Yes","No") -> Yes | K49: =IF(OR(INDEX(Standardised!$B$5:$B$15,MATCH(A49,Standardised!$A$5:$A$15,0))="Complete",INDEX(Standardised!$B$5:$B$15,MATCH(A49,Standardised!$A$5:$A$15,0))="Truncated"),(E49-INDEX(Standardised!$D$5:$D$15,MATCH(A49,Standardised!$A$5:$A$15,0)))/INDEX(Standardised!$E$5:$E$15,MATCH(A49,Standardised!$A$5:$A$15,0)),"") -> 1.3469058
A50: M06 | B50: =INDEX(Studies!$G$5:$G$15,MATCH(A50,Studies!$A$5:$A$15,0)) -> India | C50: =INDEX(Studies!$N$5:$N$15,MATCH(A50,Studies!$A$5:$A$15,0)) -> Seed | D50: Design capability and frequent design changes | E50: 0.785075 | F50: 4 | G50: R-DES | H50: Direct | I50: =IF(AND(C50="Seed",H50="Direct",G50<>""),"Yes","No") -> Yes | K50: =IF(OR(INDEX(Standardised!$B$5:$B$15,MATCH(A50,Standardised!$A$5:$A$15,0))="Complete",INDEX(Standardised!$B$5:$B$15,MATCH(A50,Standardised!$A$5:$A$15,0))="Truncated"),(E50-INDEX(Standardised!$D$5:$D$15,MATCH(A50,Standardised!$A$5:$A$15,0)))/INDEX(Standardised!$E$5:$E$15,MATCH(A50,Standardised!$A$5:$A$15,0)),"") -> 1.2467298
A51: M06 | B51: =INDEX(Studies!$G$5:$G$15,MATCH(A51,Studies!$A$5:$A$15,0)) -> India | C51: =INDEX(Studies!$N$5:$N$15,MATCH(A51,Studies!$A$5:$A$15,0)) -> Seed | D51: Rework | E51: 0.776119 | F51: 5 | G51: R-RWK | H51: Direct | I51: =IF(AND(C51="Seed",H51="Direct",G51<>""),"Yes","No") -> Yes | K51: =IF(OR(INDEX(Standardised!$B$5:$B$15,MATCH(A51,Standardised!$A$5:$A$15,0))="Complete",INDEX(Standardised!$B$5:$B$15,MATCH(A51,Standardised!$A$5:$A$15,0))="Truncated"),(E51-INDEX(Standardised!$D$5:$D$15,MATCH(A51,Standardised!$A$5:$A$15,0)))/INDEX(Standardised!$E$5:$E$15,MATCH(A51,Standardised!$A$5:$A$15,0)),"") -> 1.0663928
A52: M06 | B52: =INDEX(Studies!$G$5:$G$15,MATCH(A52,Studies!$A$5:$A$15,0)) -> India | C52: =INDEX(Studies!$N$5:$N$15,MATCH(A52,Studies!$A$5:$A$15,0)) -> Seed | D52: Coordination between all stakeholders | E52: 0.774129 | F52: 6 | G52: R-MGT | H52: Direct | I52: =IF(AND(C52="Seed",H52="Direct",G52<>""),"Yes","No") -> Yes | K52: =IF(OR(INDEX(Standardised!$B$5:$B$15,MATCH(A52,Standardised!$A$5:$A$15,0))="Complete",INDEX(Standardised!$B$5:$B$15,MATCH(A52,Standardised!$A$5:$A$15,0))="Truncated"),(E52-INDEX(Standardised!$D$5:$D$15,MATCH(A52,Standardised!$A$5:$A$15,0)))/INDEX(Standardised!$E$5:$E$15,MATCH(A52,Standardised!$A$5:$A$15,0)),"") -> 1.0263224
A53: M06 | B53: =INDEX(Studies!$G$5:$G$15,MATCH(A53,Studies!$A$5:$A$15,0)) -> India | C53: =INDEX(Studies!$N$5:$N$15,MATCH(A53,Studies!$A$5:$A$15,0)) -> Seed | D53: Project manager's authority to take financial decisions and select key team members | E53: 0.772139 | F53: 7 | G53: R-MGT | H53: Related | I53: =IF(AND(C53="Seed",H53="Direct",G53<>""),"Yes","No") -> No | K53: =IF(OR(INDEX(Standardised!$B$5:$B$15,MATCH(A53,Standardised!$A$5:$A$15,0))="Complete",INDEX(Standardised!$B$5:$B$15,MATCH(A53,Standardised!$A$5:$A$15,0))="Truncated"),(E53-INDEX(Standardised!$D$5:$D$15,MATCH(A53,Standardised!$A$5:$A$15,0)))/INDEX(Standardised!$E$5:$E$15,MATCH(A53,Standardised!$A$5:$A$15,0)),"") -> 0.98625203
A54: M06 | B54: =INDEX(Studies!$G$5:$G$15,MATCH(A54,Studies!$A$5:$A$15,0)) -> India | C54: =INDEX(Studies!$N$5:$N$15,MATCH(A54,Studies!$A$5:$A$15,0)) -> Seed | D54: Timely payment of completed works | E54: 0.771144 | F54: 8 | G54: R-PAY | H54: Direct | I54: =IF(AND(C54="Seed",H54="Direct",G54<>""),"Yes","No") -> Yes | K54: =IF(OR(INDEX(Standardised!$B$5:$B$15,MATCH(A54,Standardised!$A$5:$A$15,0))="Complete",INDEX(Standardised!$B$5:$B$15,MATCH(A54,Standardised!$A$5:$A$15,0))="Truncated"),(E54-INDEX(Standardised!$D$5:$D$15,MATCH(A54,Standardised!$A$5:$A$15,0)))/INDEX(Standardised!$E$5:$E$15,MATCH(A54,Standardised!$A$5:$A$15,0)),"") -> 0.96621683
A55: M06 | B55: =INDEX(Studies!$G$5:$G$15,MATCH(A55,Studies!$A$5:$A$15,0)) -> India | C55: =INDEX(Studies!$N$5:$N$15,MATCH(A55,Studies!$A$5:$A$15,0)) -> Seed | D55: Site clearance/availability | E55: 0.771144 | F55: 9 | G55: R-SITE | H55: Direct | I55: =IF(AND(C55="Seed",H55="Direct",G55<>""),"Yes","No") -> Yes | K55: =IF(OR(INDEX(Standardised!$B$5:$B$15,MATCH(A55,Standardised!$A$5:$A$15,0))="Complete",INDEX(Standardised!$B$5:$B$15,MATCH(A55,Standardised!$A$5:$A$15,0))="Truncated"),(E55-INDEX(Standardised!$D$5:$D$15,MATCH(A55,Standardised!$A$5:$A$15,0)))/INDEX(Standardised!$E$5:$E$15,MATCH(A55,Standardised!$A$5:$A$15,0)),"") -> 0.96621683
A56: M06 | B56: =INDEX(Studies!$G$5:$G$15,MATCH(A56,Studies!$A$5:$A$15,0)) -> India | C56: =INDEX(Studies!$N$5:$N$15,MATCH(A56,Studies!$A$5:$A$15,0)) -> Seed | D56: Ability to handle the crisis by the PM | E56: 0.771144 | F56: 10 | G56: R-MGT | H56: Related | I56: =IF(AND(C56="Seed",H56="Direct",G56<>""),"Yes","No") -> No | K56: =IF(OR(INDEX(Standardised!$B$5:$B$15,MATCH(A56,Standardised!$A$5:$A$15,0))="Complete",INDEX(Standardised!$B$5:$B$15,MATCH(A56,Standardised!$A$5:$A$15,0))="Truncated"),(E56-INDEX(Standardised!$D$5:$D$15,MATCH(A56,Standardised!$A$5:$A$15,0)))/INDEX(Standardised!$E$5:$E$15,MATCH(A56,Standardised!$A$5:$A$15,0)),"") -> 0.96621683
A57: M06 | B57: =INDEX(Studies!$G$5:$G$15,MATCH(A57,Studies!$A$5:$A$15,0)) -> India | C57: =INDEX(Studies!$N$5:$N$15,MATCH(A57,Studies!$A$5:$A$15,0)) -> Seed | D57: Use of inappropriate planning tools and techniques | E57: 0.763184 | F57: 11 | G57: R-PLAN | H57: Direct | I57: =IF(AND(C57="Seed",H57="Direct",G57<>""),"Yes","No") -> Yes | K57: =IF(OR(INDEX(Standardised!$B$5:$B$15,MATCH(A57,Standardised!$A$5:$A$15,0))="Complete",INDEX(Standardised!$B$5:$B$15,MATCH(A57,Standardised!$A$5:$A$15,0))="Truncated"),(E57-INDEX(Standardised!$D$5:$D$15,MATCH(A57,Standardised!$A$5:$A$15,0)))/INDEX(Standardised!$E$5:$E$15,MATCH(A57,Standardised!$A$5:$A$15,0)),"") -> 0.8059352
A58: M06 | B58: =INDEX(Studies!$G$5:$G$15,MATCH(A58,Studies!$A$5:$A$15,0)) -> India | C58: =INDEX(Studies!$N$5:$N$15,MATCH(A58,Studies!$A$5:$A$15,0)) -> Seed | D58: Quality | E58: 0.754229 | F58: 12 | G58: R-QLT | H58: Related | I58: =IF(AND(C58="Seed",H58="Direct",G58<>""),"Yes","No") -> No | K58: =IF(OR(INDEX(Standardised!$B$5:$B$15,MATCH(A58,Standardised!$A$5:$A$15,0))="Complete",INDEX(Standardised!$B$5:$B$15,MATCH(A58,Standardised!$A$5:$A$15,0))="Truncated"),(E58-INDEX(Standardised!$D$5:$D$15,MATCH(A58,Standardised!$A$5:$A$15,0)))/INDEX(Standardised!$E$5:$E$15,MATCH(A58,Standardised!$A$5:$A$15,0)),"") -> 0.62561837
A59: M06 | B59: =INDEX(Studies!$G$5:$G$15,MATCH(A59,Studies!$A$5:$A$15,0)) -> India | C59: =INDEX(Studies!$N$5:$N$15,MATCH(A59,Studies!$A$5:$A$15,0)) -> Seed | D59: Leadership qualities | E59: 0.752239 | F59: 13 | G59: R-DIS | H59: Related | I59: =IF(AND(C59="Seed",H59="Direct",G59<>""),"Yes","No") -> No | K59: =IF(OR(INDEX(Standardised!$B$5:$B$15,MATCH(A59,Standardised!$A$5:$A$15,0))="Complete",INDEX(Standardised!$B$5:$B$15,MATCH(A59,Standardised!$A$5:$A$15,0))="Truncated"),(E59-INDEX(Standardised!$D$5:$D$15,MATCH(A59,Standardised!$A$5:$A$15,0)))/INDEX(Standardised!$E$5:$E$15,MATCH(A59,Standardised!$A$5:$A$15,0)),"") -> 0.58554796
A60: M06 | B60: =INDEX(Studies!$G$5:$G$15,MATCH(A60,Studies!$A$5:$A$15,0)) -> India | C60: =INDEX(Studies!$N$5:$N$15,MATCH(A60,Studies!$A$5:$A$15,0)) -> Seed | D60: Top management support to PM | E60: 0.752239 | F60: 14 | G60: R-MGT | H60: Related | I60: =IF(AND(C60="Seed",H60="Direct",G60<>""),"Yes","No") -> No | K60: =IF(OR(INDEX(Standardised!$B$5:$B$15,MATCH(A60,Standardised!$A$5:$A$15,0))="Complete",INDEX(Standardised!$B$5:$B$15,MATCH(A60,Standardised!$A$5:$A$15,0))="Truncated"),(E60-INDEX(Standardised!$D$5:$D$15,MATCH(A60,Standardised!$A$5:$A$15,0)))/INDEX(Standardised!$E$5:$E$15,MATCH(A60,Standardised!$A$5:$A$15,0)),"") -> 0.58554796
A61: M06 | B61: =INDEX(Studies!$G$5:$G$15,MATCH(A61,Studies!$A$5:$A$15,0)) -> India | C61: =INDEX(Studies!$N$5:$N$15,MATCH(A61,Studies!$A$5:$A$15,0)) -> Seed | D61: Human resource and labour strike | E61: 0.749254 | F61: 15 | G61: R-STR | H61: Direct | I61: =IF(AND(C61="Seed",H61="Direct",G61<>""),"Yes","No") -> Yes | J61: strikes are narrower than absenteeism/shortage | K61: =IF(OR(INDEX(Standardised!$B$5:$B$15,MATCH(A61,Standardised!$A$5:$A$15,0))="Complete",INDEX(Standardised!$B$5:$B$15,MATCH(A61,Standardised!$A$5:$A$15,0))="Truncated"),(E61-INDEX(Standardised!$D$5:$D$15,MATCH(A61,Standardised!$A$5:$A$15,0)))/INDEX(Standardised!$E$5:$E$15,MATCH(A61,Standardised!$A$5:$A$15,0)),"") -> 0.52544235
A62: M06 | B62: =INDEX(Studies!$G$5:$G$15,MATCH(A62,Studies!$A$5:$A$15,0)) -> India | C62: =INDEX(Studies!$N$5:$N$15,MATCH(A62,Studies!$A$5:$A$15,0)) -> Seed | D62: Cost | E62: 0.744279 | F62: 16 | G62: R-CST | H62: Direct | I62: =IF(AND(C62="Seed",H62="Direct",G62<>""),"Yes","No") -> Yes | K62: =IF(OR(INDEX(Standardised!$B$5:$B$15,MATCH(A62,Standardised!$A$5:$A$15,0))="Complete",INDEX(Standardised!$B$5:$B$15,MATCH(A62,Standardised!$A$5:$A$15,0))="Truncated"),(E62-INDEX(Standardised!$D$5:$D$15,MATCH(A62,Standardised!$A$5:$A$15,0)))/INDEX(Standardised!$E$5:$E$15,MATCH(A62,Standardised!$A$5:$A$15,0)),"") -> 0.42526633
A63: M06 | B63: =INDEX(Studies!$G$5:$G$15,MATCH(A63,Studies!$A$5:$A$15,0)) -> India | C63: =INDEX(Studies!$N$5:$N$15,MATCH(A63,Studies!$A$5:$A$15,0)) -> Seed | D63: Project coordination meetings | E63: 0.740299 | F63: 17 | G63: R-MGT | H63: Direct | I63: =IF(AND(C63="Seed",H63="Direct",G63<>""),"Yes","No") -> Yes | K63: =IF(OR(INDEX(Standardised!$B$5:$B$15,MATCH(A63,Standardised!$A$5:$A$15,0))="Complete",INDEX(Standardised!$B$5:$B$15,MATCH(A63,Standardised!$A$5:$A$15,0))="Truncated"),(E63-INDEX(Standardised!$D$5:$D$15,MATCH(A63,Standardised!$A$5:$A$15,0)))/INDEX(Standardised!$E$5:$E$15,MATCH(A63,Standardised!$A$5:$A$15,0)),"") -> 0.34512551
A64: M06 | B64: =INDEX(Studies!$G$5:$G$15,MATCH(A64,Studies!$A$5:$A$15,0)) -> India | C64: =INDEX(Studies!$N$5:$N$15,MATCH(A64,Studies!$A$5:$A$15,0)) -> Seed | D64: Inadequate project formulation in the beginning | E64: 0.738308 | F64: 18 | G64: R-SCP | H64: Direct | I64: =IF(AND(C64="Seed",H64="Direct",G64<>""),"Yes","No") -> Yes | K64: =IF(OR(INDEX(Standardised!$B$5:$B$15,MATCH(A64,Standardised!$A$5:$A$15,0))="Complete",INDEX(Standardised!$B$5:$B$15,MATCH(A64,Standardised!$A$5:$A$15,0))="Truncated"),(E64-INDEX(Standardised!$D$5:$D$15,MATCH(A64,Standardised!$A$5:$A$15,0)))/INDEX(Standardised!$E$5:$E$15,MATCH(A64,Standardised!$A$5:$A$15,0)),"") -> 0.30503497
A65: M06 | B65: =INDEX(Studies!$G$5:$G$15,MATCH(A65,Studies!$A$5:$A$15,0)) -> India | C65: =INDEX(Studies!$N$5:$N$15,MATCH(A65,Studies!$A$5:$A$15,0)) -> Seed | D65: Obsolete construction equipment, methods and technology | E65: 0.738308 | F65: 19 | G65: R-TOOL | H65: Related | I65: =IF(AND(C65="Seed",H65="Direct",G65<>""),"Yes","No") -> No | J65: includes methods and technology | K65: =IF(OR(INDEX(Standardised!$B$5:$B$15,MATCH(A65,Standardised!$A$5:$A$15,0))="Complete",INDEX(Standardised!$B$5:$B$15,MATCH(A65,Standardised!$A$5:$A$15,0))="Truncated"),(E65-INDEX(Standardised!$D$5:$D$15,MATCH(A65,Standardised!$A$5:$A$15,0)))/INDEX(Standardised!$E$5:$E$15,MATCH(A65,Standardised!$A$5:$A$15,0)),"") -> 0.30503497
A66: M06 | B66: =INDEX(Studies!$G$5:$G$15,MATCH(A66,Studies!$A$5:$A$15,0)) -> India | C66: =INDEX(Studies!$N$5:$N$15,MATCH(A66,Studies!$A$5:$A$15,0)) -> Seed | D66: Conflict of interest among team members | E66: 0.737313 | F66: 20 | G66: R-CTR | H66: Related | I66: =IF(AND(C66="Seed",H66="Direct",G66<>""),"Yes","No") -> No | J66: printed twice in the paper | K66: =IF(OR(INDEX(Standardised!$B$5:$B$15,MATCH(A66,Standardised!$A$5:$A$15,0))="Complete",INDEX(Standardised!$B$5:$B$15,MATCH(A66,Standardised!$A$5:$A$15,0))="Truncated"),(E66-INDEX(Standardised!$D$5:$D$15,MATCH(A66,Standardised!$A$5:$A$15,0)))/INDEX(Standardised!$E$5:$E$15,MATCH(A66,Standardised!$A$5:$A$15,0)),"") -> 0.28499977
A67: M06 | B67: =INDEX(Studies!$G$5:$G$15,MATCH(A67,Studies!$A$5:$A$15,0)) -> India | C67: =INDEX(Studies!$N$5:$N$15,MATCH(A67,Studies!$A$5:$A$15,0)) -> Seed | D67: Customer/client satisfaction | E67: 0.730348 | F67: 21 | G67: R-CLI | H67: Related | I67: =IF(AND(C67="Seed",H67="Direct",G67<>""),"Yes","No") -> No | K67: =IF(OR(INDEX(Standardised!$B$5:$B$15,MATCH(A67,Standardised!$A$5:$A$15,0))="Complete",INDEX(Standardised!$B$5:$B$15,MATCH(A67,Standardised!$A$5:$A$15,0))="Truncated"),(E67-INDEX(Standardised!$D$5:$D$15,MATCH(A67,Standardised!$A$5:$A$15,0)))/INDEX(Standardised!$E$5:$E$15,MATCH(A67,Standardised!$A$5:$A$15,0)),"") -> 0.14475334
A68: M06 | B68: =INDEX(Studies!$G$5:$G$15,MATCH(A68,Studies!$A$5:$A$15,0)) -> India | C68: =INDEX(Studies!$N$5:$N$15,MATCH(A68,Studies!$A$5:$A$15,0)) -> Seed | D68: Conflict of interest among team members (second entry) | E68: 0.730348 | F68: 22 | G68: R-CTR | H68: Related | I68: =IF(AND(C68="Seed",H68="Direct",G68<>""),"Yes","No") -> No | J68: printed twice in the paper | K68: =IF(OR(INDEX(Standardised!$B$5:$B$15,MATCH(A68,Standardised!$A$5:$A$15,0))="Complete",INDEX(Standardised!$B$5:$B$15,MATCH(A68,Standardised!$A$5:$A$15,0))="Truncated"),(E68-INDEX(Standardised!$D$5:$D$15,MATCH(A68,Standardised!$A$5:$A$15,0)))/INDEX(Standardised!$E$5:$E$15,MATCH(A68,Standardised!$A$5:$A$15,0)),"") -> 0.14475334
A69: M06 | B69: =INDEX(Studies!$G$5:$G$15,MATCH(A69,Studies!$A$5:$A$15,0)) -> India | C69: =INDEX(Studies!$N$5:$N$15,MATCH(A69,Studies!$A$5:$A$15,0)) -> Seed | D69: Availability of training and development for enhancing skills | E69: 0.727363 | F69: 23 | G69: R-SKILL | H69: Related | I69: =IF(AND(C69="Seed",H69="Direct",G69<>""),"Yes","No") -> No | J69: training availability, not labour skill itself | K69: =IF(OR(INDEX(Standardised!$B$5:$B$15,MATCH(A69,Standardised!$A$5:$A$15,0))="Complete",INDEX(Standardised!$B$5:$B$15,MATCH(A69,Standardised!$A$5:$A$15,0))="Truncated"),(E69-INDEX(Standardised!$D$5:$D$15,MATCH(A69,Standardised!$A$5:$A$15,0)))/INDEX(Standardised!$E$5:$E$15,MATCH(A69,Standardised!$A$5:$A$15,0)),"") -> 0.084647729
A70: M06 | B70: =INDEX(Studies!$G$5:$G$15,MATCH(A70,Studies!$A$5:$A$15,0)) -> India | C70: =INDEX(Studies!$N$5:$N$15,MATCH(A70,Studies!$A$5:$A$15,0)) -> Seed | D70: Selection of PM with proven track record | E70: 0.724378 | F70: 24 | G70: R-MGT | H70: Related | I70: =IF(AND(C70="Seed",H70="Direct",G70<>""),"Yes","No") -> No | K70: =IF(OR(INDEX(Standardised!$B$5:$B$15,MATCH(A70,Standardised!$A$5:$A$15,0))="Complete",INDEX(Standardised!$B$5:$B$15,MATCH(A70,Standardised!$A$5:$A$15,0))="Truncated"),(E70-INDEX(Standardised!$D$5:$D$15,MATCH(A70,Standardised!$A$5:$A$15,0)))/INDEX(Standardised!$E$5:$E$15,MATCH(A70,Standardised!$A$5:$A$15,0)),"") -> 0.024542118
A71: M06 | B71: =INDEX(Studies!$G$5:$G$15,MATCH(A71,Studies!$A$5:$A$15,0)) -> India | C71: =INDEX(Studies!$N$5:$N$15,MATCH(A71,Studies!$A$5:$A$15,0)) -> Seed | D71: Supply chain | E71: 0.700498 | F71: 25 | G71: R-MAT | H71: Related | I71: =IF(AND(C71="Seed",H71="Direct",G71<>""),"Yes","No") -> No | J71: broader than material shortage | K71: =IF(OR(INDEX(Standardised!$B$5:$B$15,MATCH(A71,Standardised!$A$5:$A$15,0))="Complete",INDEX(Standardised!$B$5:$B$15,MATCH(A71,Standardised!$A$5:$A$15,0))="Truncated"),(E71-INDEX(Standardised!$D$5:$D$15,MATCH(A71,Standardised!$A$5:$A$15,0)))/INDEX(Standardised!$E$5:$E$15,MATCH(A71,Standardised!$A$5:$A$15,0)),"") -> -0.45630277
A72: M06 | B72: =INDEX(Studies!$G$5:$G$15,MATCH(A72,Studies!$A$5:$A$15,0)) -> India | C72: =INDEX(Studies!$N$5:$N$15,MATCH(A72,Studies!$A$5:$A$15,0)) -> Seed | D72: Willingness to adopt change | E72: 0.700498 | F72: 26 | G72: R-MGT | H72: Related | I72: =IF(AND(C72="Seed",H72="Direct",G72<>""),"Yes","No") -> No | K72: =IF(OR(INDEX(Standardised!$B$5:$B$15,MATCH(A72,Standardised!$A$5:$A$15,0))="Complete",INDEX(Standardised!$B$5:$B$15,MATCH(A72,Standardised!$A$5:$A$15,0))="Truncated"),(E72-INDEX(Standardised!$D$5:$D$15,MATCH(A72,Standardised!$A$5:$A$15,0)))/INDEX(Standardised!$E$5:$E$15,MATCH(A72,Standardised!$A$5:$A$15,0)),"") -> -0.45630277
A73: M06 | B73: =INDEX(Studies!$G$5:$G$15,MATCH(A73,Studies!$A$5:$A$15,0)) -> India | C73: =INDEX(Studies!$N$5:$N$15,MATCH(A73,Studies!$A$5:$A$15,0)) -> Seed | D73: Claim genuineness | E73: 0.694527 | F73: 27 | G73: R-CTR | H73: Direct | I73: =IF(AND(C73="Seed",H73="Direct",G73<>""),"Yes","No") -> Yes | K73: =IF(OR(INDEX(Standardised!$B$5:$B$15,MATCH(A73,Standardised!$A$5:$A$15,0))="Complete",INDEX(Standardised!$B$5:$B$15,MATCH(A73,Standardised!$A$5:$A$15,0))="Truncated"),(E73-INDEX(Standardised!$D$5:$D$15,MATCH(A73,Standardised!$A$5:$A$15,0)))/INDEX(Standardised!$E$5:$E$15,MATCH(A73,Standardised!$A$5:$A$15,0)),"") -> -0.57653413
A74: M06 | B74: =INDEX(Studies!$G$5:$G$15,MATCH(A74,Studies!$A$5:$A$15,0)) -> India | C74: =INDEX(Studies!$N$5:$N$15,MATCH(A74,Studies!$A$5:$A$15,0)) -> Seed | D74: Regular budget update | E74: 0.692537 | F74: 28 | G74: R-CST | H74: Direct | I74: =IF(AND(C74="Seed",H74="Direct",G74<>""),"Yes","No") -> Yes | K74: =IF(OR(INDEX(Standardised!$B$5:$B$15,MATCH(A74,Standardised!$A$5:$A$15,0))="Complete",INDEX(Standardised!$B$5:$B$15,MATCH(A74,Standardised!$A$5:$A$15,0))="Truncated"),(E74-INDEX(Standardised!$D$5:$D$15,MATCH(A74,Standardised!$A$5:$A$15,0)))/INDEX(Standardised!$E$5:$E$15,MATCH(A74,Standardised!$A$5:$A$15,0)),"") -> -0.61660454
A75: M06 | B75: =INDEX(Studies!$G$5:$G$15,MATCH(A75,Studies!$A$5:$A$15,0)) -> India | C75: =INDEX(Studies!$N$5:$N$15,MATCH(A75,Studies!$A$5:$A$15,0)) -> Seed | D75: Social skills of key team managers | E75: 0.691542 | F75: 29 | G75: R-COM | H75: Related | I75: =IF(AND(C75="Seed",H75="Direct",G75<>""),"Yes","No") -> No | K75: =IF(OR(INDEX(Standardised!$B$5:$B$15,MATCH(A75,Standardised!$A$5:$A$15,0))="Complete",INDEX(Standardised!$B$5:$B$15,MATCH(A75,Standardised!$A$5:$A$15,0))="Truncated"),(E75-INDEX(Standardised!$D$5:$D$15,MATCH(A75,Standardised!$A$5:$A$15,0)))/INDEX(Standardised!$E$5:$E$15,MATCH(A75,Standardised!$A$5:$A$15,0)),"") -> -0.63663974
A76: M06 | B76: =INDEX(Studies!$G$5:$G$15,MATCH(A76,Studies!$A$5:$A$15,0)) -> India | C76: =INDEX(Studies!$N$5:$N$15,MATCH(A76,Studies!$A$5:$A$15,0)) -> Seed | D76: Working hours | E76: 0.687562 | F76: 30 | G76: R-OVT | H76: Direct | I76: =IF(AND(C76="Seed",H76="Direct",G76<>""),"Yes","No") -> Yes | K76: =IF(OR(INDEX(Standardised!$B$5:$B$15,MATCH(A76,Standardised!$A$5:$A$15,0))="Complete",INDEX(Standardised!$B$5:$B$15,MATCH(A76,Standardised!$A$5:$A$15,0))="Truncated"),(E76-INDEX(Standardised!$D$5:$D$15,MATCH(A76,Standardised!$A$5:$A$15,0)))/INDEX(Standardised!$E$5:$E$15,MATCH(A76,Standardised!$A$5:$A$15,0)),"") -> -0.71678056
A77: M06 | B77: =INDEX(Studies!$G$5:$G$15,MATCH(A77,Studies!$A$5:$A$15,0)) -> India | C77: =INDEX(Studies!$N$5:$N$15,MATCH(A77,Studies!$A$5:$A$15,0)) -> Seed | D77: Developing and maintaining a short and informal line of communication | E77: 0.678607 | F77: 31 | G77: R-COM | H77: Direct | I77: =IF(AND(C77="Seed",H77="Direct",G77<>""),"Yes","No") -> Yes | K77: =IF(OR(INDEX(Standardised!$B$5:$B$15,MATCH(A77,Standardised!$A$5:$A$15,0))="Complete",INDEX(Standardised!$B$5:$B$15,MATCH(A77,Standardised!$A$5:$A$15,0))="Truncated"),(E77-INDEX(Standardised!$D$5:$D$15,MATCH(A77,Standardised!$A$5:$A$15,0)))/INDEX(Standardised!$E$5:$E$15,MATCH(A77,Standardised!$A$5:$A$15,0)),"") -> -0.89709739
A78: M06 | B78: =INDEX(Studies!$G$5:$G$15,MATCH(A78,Studies!$A$5:$A$15,0)) -> India | C78: =INDEX(Studies!$N$5:$N$15,MATCH(A78,Studies!$A$5:$A$15,0)) -> Seed | D78: Urgency emphasized by the owner while issuing tender | E78: 0.673632 | F78: 32 | G78: R-CLI | H78: Related | I78: =IF(AND(C78="Seed",H78="Direct",G78<>""),"Yes","No") -> No | K78: =IF(OR(INDEX(Standardised!$B$5:$B$15,MATCH(A78,Standardised!$A$5:$A$15,0))="Complete",INDEX(Standardised!$B$5:$B$15,MATCH(A78,Standardised!$A$5:$A$15,0))="Truncated"),(E78-INDEX(Standardised!$D$5:$D$15,MATCH(A78,Standardised!$A$5:$A$15,0)))/INDEX(Standardised!$E$5:$E$15,MATCH(A78,Standardised!$A$5:$A$15,0)),"") -> -0.99727341
A79: M06 | B79: =INDEX(Studies!$G$5:$G$15,MATCH(A79,Studies!$A$5:$A$15,0)) -> India | C79: =INDEX(Studies!$N$5:$N$15,MATCH(A79,Studies!$A$5:$A$15,0)) -> Seed | D79: Ability to delegate authority | E79: 0.669652 | F79: 33 | G79: R-MGT | H79: Related | I79: =IF(AND(C79="Seed",H79="Direct",G79<>""),"Yes","No") -> No | K79: =IF(OR(INDEX(Standardised!$B$5:$B$15,MATCH(A79,Standardised!$A$5:$A$15,0))="Complete",INDEX(Standardised!$B$5:$B$15,MATCH(A79,Standardised!$A$5:$A$15,0))="Truncated"),(E79-INDEX(Standardised!$D$5:$D$15,MATCH(A79,Standardised!$A$5:$A$15,0)))/INDEX(Standardised!$E$5:$E$15,MATCH(A79,Standardised!$A$5:$A$15,0)),"") -> -1.0774142
A80: M06 | B80: =INDEX(Studies!$G$5:$G$15,MATCH(A80,Studies!$A$5:$A$15,0)) -> India | C80: =INDEX(Studies!$N$5:$N$15,MATCH(A80,Studies!$A$5:$A$15,0)) -> Seed | D80: Political and economic environment | E80: 0.665672 | F80: 34 | G80: R-ECO | H80: Direct | I80: =IF(AND(C80="Seed",H80="Direct",G80<>""),"Yes","No") -> Yes | K80: =IF(OR(INDEX(Standardised!$B$5:$B$15,MATCH(A80,Standardised!$A$5:$A$15,0))="Complete",INDEX(Standardised!$B$5:$B$15,MATCH(A80,Standardised!$A$5:$A$15,0))="Truncated"),(E80-INDEX(Standardised!$D$5:$D$15,MATCH(A80,Standardised!$A$5:$A$15,0)))/INDEX(Standardised!$E$5:$E$15,MATCH(A80,Standardised!$A$5:$A$15,0)),"") -> -1.157555
A81: M06 | B81: =INDEX(Studies!$G$5:$G$15,MATCH(A81,Studies!$A$5:$A$15,0)) -> India | C81: =INDEX(Studies!$N$5:$N$15,MATCH(A81,Studies!$A$5:$A$15,0)) -> Seed | D81: Exceptional difference between client and architect | E81: 0.665672 | F81: 35 | G81: R-CTR | H81: Related | I81: =IF(AND(C81="Seed",H81="Direct",G81<>""),"Yes","No") -> No | K81: =IF(OR(INDEX(Standardised!$B$5:$B$15,MATCH(A81,Standardised!$A$5:$A$15,0))="Complete",INDEX(Standardised!$B$5:$B$15,MATCH(A81,Standardised!$A$5:$A$15,0))="Truncated"),(E81-INDEX(Standardised!$D$5:$D$15,MATCH(A81,Standardised!$A$5:$A$15,0)))/INDEX(Standardised!$E$5:$E$15,MATCH(A81,Standardised!$A$5:$A$15,0)),"") -> -1.157555
A82: M06 | B82: =INDEX(Studies!$G$5:$G$15,MATCH(A82,Studies!$A$5:$A$15,0)) -> India | C82: =INDEX(Studies!$N$5:$N$15,MATCH(A82,Studies!$A$5:$A$15,0)) -> Seed | D82: Interpersonal skills | E82: 0.662687 | F82: 36 | G82: R-COM | H82: Related | I82: =IF(AND(C82="Seed",H82="Direct",G82<>""),"Yes","No") -> No | K82: =IF(OR(INDEX(Standardised!$B$5:$B$15,MATCH(A82,Standardised!$A$5:$A$15,0))="Complete",INDEX(Standardised!$B$5:$B$15,MATCH(A82,Standardised!$A$5:$A$15,0))="Truncated"),(E82-INDEX(Standardised!$D$5:$D$15,MATCH(A82,Standardised!$A$5:$A$15,0)))/INDEX(Standardised!$E$5:$E$15,MATCH(A82,Standardised!$A$5:$A$15,0)),"") -> -1.2176607
A83: M06 | B83: =INDEX(Studies!$G$5:$G$15,MATCH(A83,Studies!$A$5:$A$15,0)) -> India | C83: =INDEX(Studies!$N$5:$N$15,MATCH(A83,Studies!$A$5:$A$15,0)) -> Seed | D83: Climate conditions | E83: 0.656716 | F83: 37 | G83: R-WX | H83: Direct | I83: =IF(AND(C83="Seed",H83="Direct",G83<>""),"Yes","No") -> Yes | K83: =IF(OR(INDEX(Standardised!$B$5:$B$15,MATCH(A83,Standardised!$A$5:$A$15,0))="Complete",INDEX(Standardised!$B$5:$B$15,MATCH(A83,Standardised!$A$5:$A$15,0))="Truncated"),(E83-INDEX(Standardised!$D$5:$D$15,MATCH(A83,Standardised!$A$5:$A$15,0)))/INDEX(Standardised!$E$5:$E$15,MATCH(A83,Standardised!$A$5:$A$15,0)),"") -> -1.337892
... A86: M06 | B86: =INDEX(Studies!$G$5:$G$15,MATCH(A86,Studies!$A$5:$A$15,0)) -> India | C86: =INDEX(Studies!$N$5:$N$15,MATCH(A86,Studies!$A$5:$A$15,0)) -> Seed | D86: Social environment | E86: 0.59403 | F86: 40 | G86: R-SOC | H86: Direct | I86: =IF(AND(C86="Seed",H86="Direct",G86<>""),"Yes","No") -> Yes | K86: =IF(OR(INDEX(Standardised!$B$5:$B$15,MATCH(A86,Standardised!$A$5:$A$15,0))="Complete",INDEX(Standardised!$B$5:$B$15,MATCH(A86,Standardised!$A$5:$A$15,0))="Truncated"),(E86-INDEX(Standardised!$D$5:$D$15,MATCH(A86,Standardised!$A$5:$A$15,0)))/INDEX(Standardised!$E$5:$E$15,MATCH(A86,Standardised!$A$5:$A$15,0)),"") -> -2.60013
A87: A14 | B87: =INDEX(Studies!$G$5:$G$15,MATCH(A87,Studies!$A$5:$A$15,0)) -> Sri Lanka | C87: =INDEX(Studies!$N$5:$N$15,MATCH(A87,Studies!$A$5:$A$15,0)) -> Seed | D87: Shortage of skilled subcontractors/suppliers | E87: 0.8294 | F87: 1 | G87: R-MAT | H87: Related | I87: =IF(AND(C87="Seed",H87="Direct",G87<>""),"Yes","No") -> No | J87: suppliers and subcontractors together | K87: =IF(OR(INDEX(Standardised!$B$5:$B$15,MATCH(A87,Standardised!$A$5:$A$15,0))="Complete",INDEX(Standardised!$B$5:$B$15,MATCH(A87,Standardised!$A$5:$A$15,0))="Truncated"),(E87-INDEX(Standardised!$D$5:$D$15,MATCH(A87,Standardised!$A$5:$A$15,0)))/INDEX(Standardised!$E$5:$E$15,MATCH(A87,Standardised!$A$5:$A$15,0)),"")
A88: A14 | B88: =INDEX(Studies!$G$5:$G$15,MATCH(A88,Studies!$A$5:$A$15,0)) -> Sri Lanka | C88: =INDEX(Studies!$N$5:$N$15,MATCH(A88,Studies!$A$5:$A$15,0)) -> Seed | D88: Shortage of labourers (skilled, semi-skilled, unskilled) | E88: 0.8245 | F88: 2 | G88: R-LAB | H88: Direct | I88: =IF(AND(C88="Seed",H88="Direct",G88<>""),"Yes","No") -> Yes | K88: =IF(OR(INDEX(Standardised!$B$5:$B$15,MATCH(A88,Standardised!$A$5:$A$15,0))="Complete",INDEX(Standardised!$B$5:$B$15,MATCH(A88,Standardised!$A$5:$A$15,0))="Truncated"),(E88-INDEX(Standardised!$D$5:$D$15,MATCH(A88,Standardised!$A$5:$A$15,0)))/INDEX(Standardised!$E$5:$E$15,MATCH(A88,Standardised!$A$5:$A$15,0)),"")
A89: A14 | B89: =INDEX(Studies!$G$5:$G$15,MATCH(A89,Studies!$A$5:$A$15,0)) -> Sri Lanka | C89: =INDEX(Studies!$N$5:$N$15,MATCH(A89,Studies!$A$5:$A$15,0)) -> Seed | D89: Delay of delivering materials to the site | E89: 0.8098 | F89: 4 | G89: R-MAT | H89: Direct | I89: =IF(AND(C89="Seed",H89="Direct",G89<>""),"Yes","No") -> Yes | K89: =IF(OR(INDEX(Standardised!$B$5:$B$15,MATCH(A89,Standardised!$A$5:$A$15,0))="Complete",INDEX(Standardised!$B$5:$B$15,MATCH(A89,Standardised!$A$5:$A$15,0))="Truncated"),(E89-INDEX(Standardised!$D$5:$D$15,MATCH(A89,Standardised!$A$5:$A$15,0)))/INDEX(Standardised!$E$5:$E$15,MATCH(A89,Standardised!$A$5:$A$15,0)),"")
A90: A14 | B90: =INDEX(Studies!$G$5:$G$15,MATCH(A90,Studies!$A$5:$A$15,0)) -> Sri Lanka | C90: =INDEX(Studies!$N$5:$N$15,MATCH(A90,Studies!$A$5:$A$15,0)) -> Seed | D90: Fluctuation of material prices in the market | E90: 0.789 | F90: 6 | G90: R-PRC | H90: Direct | I90: =IF(AND(C90="Seed",H90="Direct",G90<>""),"Yes","No") -> Yes | K90: =IF(OR(INDEX(Standardised!$B$5:$B$15,MATCH(A90,Standardised!$A$5:$A$15,0))="Complete",INDEX(Standardised!$B$5:$B$15,MATCH(A90,Standardised!$A$5:$A$15,0))="Truncated"),(E90-INDEX(Standardised!$D$5:$D$15,MATCH(A90,Standardised!$A$5:$A$15,0)))/INDEX(Standardised!$E$5:$E$15,MATCH(A90,Standardised!$A$5:$A$15,0)),"")
A91: A14 | B91: =INDEX(Studies!$G$5:$G$15,MATCH(A91,Studies!$A$5:$A$15,0)) -> Sri Lanka | C91: =INDEX(Studies!$N$5:$N$15,MATCH(A91,Studies!$A$5:$A$15,0)) -> Seed | D91: Bad weather conditions | E91: 0.6528 | F91: 30 | G91: R-WX | H91: Direct | I91: =IF(AND(C91="Seed",H91="Direct",G91<>""),"Yes","No") -> Yes | K91: =IF(OR(INDEX(Standardised!$B$5:$B$15,MATCH(A91,Standardised!$A$5:$A$15,0))="Complete",INDEX(Standardised!$B$5:$B$15,MATCH(A91,Standardised!$A$5:$A$15,0))="Truncated"),(E91-INDEX(Standardised!$D$5:$D$15,MATCH(A91,Standardised!$A$5:$A$15,0)))/INDEX(Standardised!$E$5:$E$15,MATCH(A91,Standardised!$A$5:$A$15,0)),"")
A92: A15 | B92: =INDEX(Studies!$G$5:$G$15,MATCH(A92,Studies!$A$5:$A$15,0)) -> Sri Lanka | C92: =INDEX(Studies!$N$5:$N$15,MATCH(A92,Studies!$A$5:$A$15,0)) -> Seed | D92: Skills shortage | E92: 0.82 | F92: 1 | G92: R-SKILL | H92: Direct | I92: =IF(AND(C92="Seed",H92="Direct",G92<>""),"Yes","No") -> Yes | K92: =IF(OR(INDEX(Standardised!$B$5:$B$15,MATCH(A92,Standardised!$A$5:$A$15,0))="Complete",INDEX(Standardised!$B$5:$B$15,MATCH(A92,Standardised!$A$5:$A$15,0))="Truncated"),(E92-INDEX(Standardised!$D$5:$D$15,MATCH(A92,Standardised!$A$5:$A$15,0)))/INDEX(Standardised!$E$5:$E$15,MATCH(A92,Standardised!$A$5:$A$15,0)),"")
A93: A15 | B93: =INDEX(Studies!$G$5:$G$15,MATCH(A93,Studies!$A$5:$A$15,0)) -> Sri Lanka | C93: =INDEX(Studies!$N$5:$N$15,MATCH(A93,Studies!$A$5:$A$15,0)) -> Seed | D93: Lack of thinking abilities | E93: 0.81 | F93: 2 | G93: R-SKILL | H93: Related | I93: =IF(AND(C93="Seed",H93="Direct",G93<>""),"Yes","No") -> No | K93: =IF(OR(INDEX(Standardised!$B$5:$B$15,MATCH(A93,Standardised!$A$5:$A$15,0))="Complete",INDEX(Standardised!$B$5:$B$15,MATCH(A93,Standardised!$A$5:$A$15,0))="Truncated"),(E93-INDEX(Standardised!$D$5:$D$15,MATCH(A93,Standardised!$A$5:$A$15,0)))/INDEX(Standardised!$E$5:$E$15,MATCH(A93,Standardised!$A$5:$A$15,0)),"")
A94: A15 | B94: =INDEX(Studies!$G$5:$G$15,MATCH(A94,Studies!$A$5:$A$15,0)) -> Sri Lanka | C94: =INDEX(Studies!$N$5:$N$15,MATCH(A94,Studies!$A$5:$A$15,0)) -> Seed | D94: Lack of work experience | E94: 0.8 | F94: 3 | G94: R-SKILL | H94: Direct | I94: =IF(AND(C94="Seed",H94="Direct",G94<>""),"Yes","No") -> Yes | K94: =IF(OR(INDEX(Standardised!$B$5:$B$15,MATCH(A94,Standardised!$A$5:$A$15,0))="Complete",INDEX(Standardised!$B$5:$B$15,MATCH(A94,Standardised!$A$5:$A$15,0))="Truncated"),(E94-INDEX(Standardised!$D$5:$D$15,MATCH(A94,Standardised!$A$5:$A$15,0)))/INDEX(Standardised!$E$5:$E$15,MATCH(A94,Standardised!$A$5:$A$15,0)),"")
A95: A15 | B95: =INDEX(Studies!$G$5:$G$15,MATCH(A95,Studies!$A$5:$A$15,0)) -> Sri Lanka | C95: =INDEX(Studies!$N$5:$N$15,MATCH(A95,Studies!$A$5:$A$15,0)) -> Seed | D95: Lack of knowledge in construction works | E95: 0.79 | F95: 4 | G95: R-SKILL | H95: Direct | I95: =IF(AND(C95="Seed",H95="Direct",G95<>""),"Yes","No") -> Yes | K95: =IF(OR(INDEX(Standardised!$B$5:$B$15,MATCH(A95,Standardised!$A$5:$A$15,0))="Complete",INDEX(Standardised!$B$5:$B$15,MATCH(A95,Standardised!$A$5:$A$15,0))="Truncated"),(E95-INDEX(Standardised!$D$5:$D$15,MATCH(A95,Standardised!$A$5:$A$15,0)))/INDEX(Standardised!$E$5:$E$15,MATCH(A95,Standardised!$A$5:$A$15,0)),"")
A96: A15 | B96: =INDEX(Studies!$G$5:$G$15,MATCH(A96,Studies!$A$5:$A$15,0)) -> Sri Lanka | C96: =INDEX(Studies!$N$5:$N$15,MATCH(A96,Studies!$A$5:$A$15,0)) -> Seed | D96: Poor labour discipline | E96: 0.79 | F96: 5 | G96: R-DIS | H96: Direct | I96: =IF(AND(C96="Seed",H96="Direct",G96<>""),"Yes","No") -> Yes | K96: =IF(OR(INDEX(Standardised!$B$5:$B$15,MATCH(A96,Standardised!$A$5:$A$15,0))="Complete",INDEX(Standardised!$B$5:$B$15,MATCH(A96,Standardised!$A$5:$A$15,0))="Truncated"),(E96-INDEX(Standardised!$D$5:$D$15,MATCH(A96,Standardised!$A$5:$A$15,0)))/INDEX(Standardised!$E$5:$E$15,MATCH(A96,Standardised!$A$5:$A$15,0)),"")
A97: M10 | B97: =INDEX(Studies!$G$5:$G$15,MATCH(A97,Studies!$A$5:$A$15,0)) -> Middle East (10 studies: Malaysia, Palestine, Kuwait, Qatar, Saudi Arabia, Egypt, Bahrain, Oman, Yemen, Vietnam) | C97: =INDEX(Studies!$N$5:$N$15,MATCH(A97,Studies!$A$5:$A$15,0)) -> Validation | D97: Inadequate workers' supervision | E97: 0.816 | F97: 2 | G97: R-SUP | H97: Direct | I97: =IF(AND(C97="Seed",H97="Direct",G97<>""),"Yes","No") -> No | K97: =IF(OR(INDEX(Standardised!$B$5:$B$15,MATCH(A97,Standardised!$A$5:$A$15,0))="Complete",INDEX(Standardised!$B$5:$B$15,MATCH(A97,Standardised!$A$5:$A$15,0))="Truncated"),(E97-INDEX(Standardised!$D$5:$D$15,MATCH(A97,Standardised!$A$5:$A$15,0)))/INDEX(Standardised!$E$5:$E$15,MATCH(A97,Standardised!$A$5:$A$15,0)),"") -> 1.4008213
A98: M10 | B98: =INDEX(Studies!$G$5:$G$15,MATCH(A98,Studies!$A$5:$A$15,0)) -> Middle East (10 studies: Malaysia, Palestine, Kuwait, Qatar, Saudi Arabia, Egypt, Bahrain, Oman, Yemen, Vietnam) | C98: =INDEX(Studies!$N$5:$N$15,MATCH(A98,Studies!$A$5:$A$15,0)) -> Validation | D98: A shortage of skilled labour | E98: 0.801 | F98: 3 | G98: R-SKILL | H98: Direct | I98: =IF(AND(C98="Seed",H98="Direct",G98<>""),"Yes","No") -> No | K98: =IF(OR(INDEX(Standardised!$B$5:$B$15,MATCH(A98,Standardised!$A$5:$A$15,0))="Complete",INDEX(Standardised!$B$5:$B$15,MATCH(A98,Standardised!$A$5:$A$15,0))="Truncated"),(E98-INDEX(Standardised!$D$5:$D$15,MATCH(A98,Standardised!$A$5:$A$15,0)))/INDEX(Standardised!$E$5:$E$15,MATCH(A98,Standardised!$A$5:$A$15,0)),"") -> 1.2095367
A99: M10 | B99: =INDEX(Studies!$G$5:$G$15,MATCH(A99,Studies!$A$5:$A$15,0)) -> Middle East (10 studies: Malaysia, Palestine, Kuwait, Qatar, Saudi Arabia, Egypt, Bahrain, Oman, Yemen, Vietnam) | C99: =INDEX(Studies!$N$5:$N$15,MATCH(A99,Studies!$A$5:$A$15,0)) -> Validation | D99: Extent of change orders | E99: 0.793 | F99: 4 | G99: R-DES | H99: Direct | I99: =IF(AND(C99="Seed",H99="Direct",G99<>""),"Yes","No") -> No | K99: =IF(OR(INDEX(Standardised!$B$5:$B$15,MATCH(A99,Standardised!$A$5:$A$15,0))="Complete",INDEX(Standardised!$B$5:$B$15,MATCH(A99,Standardised!$A$5:$A$15,0))="Truncated"),(E99-INDEX(Standardised!$D$5:$D$15,MATCH(A99,Standardised!$A$5:$A$15,0)))/INDEX(Standardised!$E$5:$E$15,MATCH(A99,Standardised!$A$5:$A$15,0)),"") -> 1.1075183
A100: M10 | B100: =INDEX(Studies!$G$5:$G$15,MATCH(A100,Studies!$A$5:$A$15,0)) -> Middle East (10 studies: Malaysia, Palestine, Kuwait, Qatar, Saudi Arabia, Egypt, Bahrain, Oman, Yemen, Vietnam) | C100: =INDEX(Studies!$N$5:$N$15,MATCH(A100,Studies!$A$5:$A$15,0)) -> Validation | D100: Clarity of technical specifications | E100: 0.791 | F100: 5 | G100: R-DES | H100: Related | I100: =IF(AND(C100="Seed",H100="Direct",G100<>""),"Yes","No") -> No | J100: specification clarity, not drawings or changes | K100: =IF(OR(INDEX(Standardised!$B$5:$B$15,MATCH(A100,Standardised!$A$5:$A$15,0))="Complete",INDEX(Standardised!$B$5:$B$15,MATCH(A100,Standardised!$A$5:$A$15,0))="Truncated"),(E100-INDEX(Standardised!$D$5:$D$15,MATCH(A100,Standardised!$A$5:$A$15,0)))/INDEX(Standardised!$E$5:$E$15,MATCH(A100,Standardised!$A$5:$A$15,0)),"") -> 1.0820137
A101: M10 | B101: =INDEX(Studies!$G$5:$G$15,MATCH(A101,Studies!$A$5:$A$15,0)) -> Middle East (10 studies: Malaysia, Palestine, Kuwait, Qatar, Saudi Arabia, Egypt, Bahrain, Oman, Yemen, Vietnam) | C101: =INDEX(Studies!$N$5:$N$15,MATCH(A101,Studies!$A$5:$A$15,0)) -> Validation | D101: Coordination among design disciplines | E101: 0.785 | F101: 6 | G101: R-DES | H101: Related | I101: =IF(AND(C101="Seed",H101="Direct",G101<>""),"Yes","No") -> No | K101: =IF(OR(INDEX(Standardised!$B$5:$B$15,MATCH(A101,Standardised!$A$5:$A$15,0))="Complete",INDEX(Standardised!$B$5:$B$15,MATCH(A101,Standardised!$A$5:$A$15,0))="Truncated"),(E101-INDEX(Standardised!$D$5:$D$15,MATCH(A101,Standardised!$A$5:$A$15,0)))/INDEX(Standardised!$E$5:$E$15,MATCH(A101,Standardised!$A$5:$A$15,0)),"") -> 1.0054998
A102: M10 | B102: =INDEX(Studies!$G$5:$G$15,MATCH(A102,Studies!$A$5:$A$15,0)) -> Middle East (10 studies: Malaysia, Palestine, Kuwait, Qatar, Saudi Arabia, Egypt, Bahrain, Oman, Yemen, Vietnam) | C102: =INDEX(Studies!$N$5:$N$15,MATCH(A102,Studies!$A$5:$A$15,0)) -> Validation | D102: Lack of incentive schemes | E102: 0.783 | F102: 7 | G102: R-INC | H102: Direct | I102: =IF(AND(C102="Seed",H102="Direct",G102<>""),"Yes","No") -> No | K102: =IF(OR(INDEX(Standardised!$B$5:$B$15,MATCH(A102,Standardised!$A$5:$A$15,0))="Complete",INDEX(Standardised!$B$5:$B$15,MATCH(A102,Standardised!$A$5:$A$15,0))="Truncated"),(E102-INDEX(Standardised!$D$5:$D$15,MATCH(A102,Standardised!$A$5:$A$15,0)))/INDEX(Standardised!$E$5:$E$15,MATCH(A102,Standardised!$A$5:$A$15,0)),"") -> 0.97999524
A103: M10 | B103: =INDEX(Studies!$G$5:$G$15,MATCH(A103,Studies!$A$5:$A$15,0)) -> Middle East (10 studies: Malaysia, Palestine, Kuwait, Qatar, Saudi Arabia, Egypt, Bahrain, Oman, Yemen, Vietnam) | C103: =INDEX(Studies!$N$5:$N$15,MATCH(A103,Studies!$A$5:$A$15,0)) -> Validation | D103: Economic conditions | E103: 0.778 | F103: 8 | G103: R-ECO | H103: Direct | I103: =IF(AND(C103="Seed",H103="Direct",G103<>""),"Yes","No") -> No | K103: =IF(OR(INDEX(Standardised!$B$5:$B$15,MATCH(A103,Standardised!$A$5:$A$15,0))="Complete",INDEX(Standardised!$B$5:$B$15,MATCH(A103,Standardised!$A$5:$A$15,0))="Truncated"),(E103-INDEX(Standardised!$D$5:$D$15,MATCH(A103,Standardised!$A$5:$A$15,0)))/INDEX(Standardised!$E$5:$E$15,MATCH(A103,Standardised!$A$5:$A$15,0)),"") -> 0.91623372
...

Sheet Seed_Calculation
A1: Literature seed: how the model turns RII values into a place on the risk matrix
A2: Each study cell = average of that study's DIRECT values for the risk. Seed mean = average across studies. Rank -> five equal bands -> class.
A4: Risk ID | B4: Risk | C4: M01 | D4: A02 | E4: M06 | F4: A14 | G4: A15 | H4: Studies with a value | I4: Seed mean RII | J4: Rank | K4: Class (1-5) | L4: Matrix cell (p × impact) | M4: Level
A5: R-MAT | B5: Brick / block / mortar material shortage or late delivery | C5: =IFERROR(AVERAGEIFS(RII_Data!$E$5:$E$186,RII_Data!$A$5:$A$186,C$4,RII_Data!$G$5:$G$186,$A5,RII_Data!$H$5:$H$186,"Direct",RII_Data!$C$5:$C$186,"Seed"),"") -> 0.777 | D5: =IFERROR(AVERAGEIFS(RII_Data!$E$5:$E$186,RII_Data!$A$5:$A$186,D$4,RII_Data!$G$5:$G$186,$A5,RII_Data!$H$5:$H$186,"Direct",RII_Data!$C$5:$C$186,"Seed"),"") -> 0.78 | E5: =IFERROR(AVERAGEIFS(RII_Data!$E$5:$E$186,RII_Data!$A$5:$A$186,E$4,RII_Data!$G$5:$G$186,$A5,RII_Data!$H$5:$H$186,"Direct",RII_Data!$C$5:$C$186,"Seed"),"") | F5: =IFERROR(AVERAGEIFS(RII_Data!$E$5:$E$186,RII_Data!$A$5:$A$186,F$4,RII_Data!$G$5:$G$186,$A5,RII_Data!$H$5:$H$186,"Direct",RII_Data!$C$5:$C$186,"Seed"),"") -> 0.8098 | G5: =IFERROR(AVERAGEIFS(RII_Data!$E$5:$E$186,RII_Data!$A$5:$A$186,G$4,RII_Data!$G$5:$G$186,$A5,RII_Data!$H$5:$H$186,"Direct",RII_Data!$C$5:$C$186,"Seed"),"") | H5: =COUNT(C5:G5) -> 3 | I5: =IF(H5=0,"",AVERAGE(C5:G5)) -> 0.78893333 | J5: =IF(I5="","",RANK(I5,$I$5:$I$42,0)+COUNTIFS($I$5:$I$42,I5,$A$5:$A$42,"<"&$A5)) -> 1 | K5: =IF(J5="","",5-INT((J5-1)*5/$C$44)) -> 5 | L5: =IF(K5="","not seeded","p"&K5&" × i"&K5) -> p5 × i5 | M5: =IF(K5="","",IF(K5^2<=5,"Low",IF(K5^2<=10,"Moderate",IF(K5^2<=15,"High","Extreme")))) -> Extreme
A6: R-TOOL | B6: Tools and equipment delay | C6: =IFERROR(AVERAGEIFS(RII_Data!$E$5:$E$186,RII_Data!$A$5:$A$186,C$4,RII_Data!$G$5:$G$186,$A6,RII_Data!$H$5:$H$186,"Direct",RII_Data!$C$5:$C$186,"Seed"),"") -> 0.7455 | D6: =IFERROR(AVERAGEIFS(RII_Data!$E$5:$E$186,RII_Data!$A$5:$A$186,D$4,RII_Data!$G$5:$G$186,$A6,RII_Data!$H$5:$H$186,"Direct",RII_Data!$C$5:$C$186,"Seed"),"") -> 0.76 | E6: =IFERROR(AVERAGEIFS(RII_Data!$E$5:$E$186,RII_Data!$A$5:$A$186,E$4,RII_Data!$G$5:$G$186,$A6,RII_Data!$H$5:$H$186,"Direct",RII_Data!$C$5:$C$186,"Seed"),"") | F6: =IFERROR(AVERAGEIFS(RII_Data!$E$5:$E$186,RII_Data!$A$5:$A$186,F$4,RII_Data!$G$5:$G$186,$A6,RII_Data!$H$5:$H$186,"Direct",RII_Data!$C$5:$C$186,"Seed"),"") | G6: =IFERROR(AVERAGEIFS(RII_Data!$E$5:$E$186,RII_Data!$A$5:$A$186,G$4,RII_Data!$G$5:$G$186,$A6,RII_Data!$H$5:$H$186,"Direct",RII_Data!$C$5:$C$186,"Seed"),"") | H6: =COUNT(C6:G6) -> 2 | I6: =IF(H6=0,"",AVERAGE(C6:G6)) -> 0.75275 | J6: =IF(I6="","",RANK(I6,$I$5:$I$42,0)+COUNTIFS($I$5:$I$42,I6,$A$5:$A$42,"<"&$A6)) -> 12 | K6: =IF(J6="","",5-INT((J6-1)*5/$C$44)) -> 4 | L6: =IF(K6="","not seeded","p"&K6&" × i"&K6) -> p4 × i4 | M6: =IF(K6="","",IF(K6^2<=5,"Low",IF(K6^2<=10,"Moderate",IF(K6^2<=15,"High","Extreme")))) -> Extreme
A7: R-LAB | B7: Labour absenteeism or shortage | C7: =IFERROR(AVERAGEIFS(RII_Data!$E$5:$E$186,RII_Data!$A$5:$A$186,C$4,RII_Data!$G$5:$G$186,$A7,RII_Data!$H$5:$H$186,"Direct",RII_Data!$C$5:$C$186,"Seed"),"") -> 0.723 | D7: =IFERROR(AVERAGEIFS(RII_Data!$E$5:$E$186,RII_Data!$A$5:$A$186,D$4,RII_Data!$G$5:$G$186,$A7,RII_Data!$H$5:$H$186,"Direct",RII_Data!$C$5:$C$186,"Seed"),"") -> 0.751 | E7: =IFERROR(AVERAGEIFS(RII_Data!$E$5:$E$186,RII_Data!$A$5:$A$186,E$4,RII_Data!$G$5:$G$186,$A7,RII_Data!$H$5:$H$186,"Direct",RII_Data!$C$5:$C$186,"Seed"),"") | F7: =IFERROR(AVERAGEIFS(RII_Data!$E$5:$E$186,RII_Data!$A$5:$A$186,F$4,RII_Data!$G$5:$G$186,$A7,RII_Data!$H$5:$H$186,"Direct",RII_Data!$C$5:$C$186,"Seed"),"") -> 0.8245 | G7: =IFERROR(AVERAGEIFS(RII_Data!$E$5:$E$186,RII_Data!$A$5:$A$186,G$4,RII_Data!$G$5:$G$186,$A7,RII_Data!$H$5:$H$186,"Direct",RII_Data!$C$5:$C$186,"Seed"),"") | H7: =COUNT(C7:G7) -> 3 | I7: =IF(H7=0,"",AVERAGE(C7:G7)) -> 0.76616667 | J7: =IF(I7="","",RANK(I7,$I$5:$I$42,0)+COUNTIFS($I$5:$I$42,I7,$A$5:$A$42,"<"&$A7)) -> 7 | K7: =IF(J7="","",5-INT((J7-1)*5/$C$44)) -> 4 | L7: =IF(K7="","not seeded","p"&K7&" × i"&K7) -> p4 × i4 | M7: =IF(K7="","",IF(K7^2<=5,"Low",IF(K7^2<=10,"Moderate",IF(K7^2<=15,"High","Extreme")))) -> Extreme
A8: R-SKILL | B8: Unskilled or unqualified labour | C8: =IFERROR(AVERAGEIFS(RII_Data!$E$5:$E$186,RII_Data!$A$5:$A$186,C$4,RII_Data!$G$5:$G$186,$A8,RII_Data!$H$5:$H$186,"Direct",RII_Data!$C$5:$C$186,"Seed"),"") -> 0.759 | D8: =IFERROR(AVERAGEIFS(RII_Data!$E$5:$E$186,RII_Data!$A$5:$A$186,D$4,RII_Data!$G$5:$G$186,$A8,RII_Data!$H$5:$H$186,"Direct",RII_Data!$C$5:$C$186,"Seed"),"") -> 0.787 | E8: =IFERROR(AVERAGEIFS(RII_Data!$E$5:$E$186,RII_Data!$A$5:$A$186,E$4,RII_Data!$G$5:$G$186,$A8,RII_Data!$H$5:$H$186,"Direct",RII_Data!$C$5:$C$186,"Seed"),"") | F8: =IFERROR(AVERAGEIFS(RII_Data!$E$5:$E$186,RII_Data!$A$5:$A$186,F$4,RII_Data!$G$5:$G$186,$A8,RII_Data!$H$5:$H$186,"Direct",RII_Data!$C$5:$C$186,"Seed"),"") | G8: =IFERROR(AVERAGEIFS(RII_Data!$E$5:$E$186,RII_Data!$A$5:$A$186,G$4,RII_Data!$G$5:$G$186,$A8,RII_Data!$H$5:$H$186,"Direct",RII_Data!$C$5:$C$186,"Seed"),"") -> 0.80333333 | H8: =COUNT(C8:G8) -> 3 | I8: =IF(H8=0,"",AVERAGE(C8:G8)) -> 0.78311111 | J8: =IF(I8="","",RANK(I8,$I$5:$I$42,0)+COUNTIFS($I$5:$I$42,I8,$A$5:$A$42,"<"&$A8)) -> 3 | K8: =IF(J8="","",5-INT((J8-1)*5/$C$44)) -> 5 | L8: =IF(K8="","not seeded","p"&K8&" × i"&K8) -> p5 × i5 | M8: =IF(K8="","",IF(K8^2<=5,"Low",IF(K8^2<=10,"Moderate",IF(K8^2<=15,"High","Extreme")))) -> Extreme
A9: R-PLAN | B9: Poor planning or unrealistic scheduling | C9: =IFERROR(AVERAGEIFS(RII_Data!$E$5:$E$186,RII_Data!$A$5:$A$186,C$4,RII_Data!$G$5:$G$186,$A9,RII_Data!$H$5:$H$186,"Direct",RII_Data!$C$5:$C$186,"Seed"),"") -> 0.791 | D9: =IFERROR(AVERAGEIFS(RII_Data!$E$5:$E$186,RII_Data!$A$5:$A$186,D$4,RII_Data!$G$5:$G$186,$A9,RII_Data!$H$5:$H$186,"Direct",RII_Data!$C$5:$C$186,"Seed"),"") | E9: =IFERROR(AVERAGEIFS(RII_Data!$E$5:$E$186,RII_Data!$A$5:$A$186,E$4,RII_Data!$G$5:$G$186,$A9,RII_Data!$H$5:$H$186,"Direct",RII_Data!$C$5:$C$186,"Seed"),"") -> 0.763184 | F9: =IFERROR(AVERAGEIFS(RII_Data!$E$5:$E$186,RII_Data!$A$5:$A$186,F$4,RII_Data!$G$5:$G$186,$A9,RII_Data!$H$5:$H$186,"Direct",RII_Data!$C$5:$C$186,"Seed"),"") | G9: =IFERROR(AVERAGEIFS(RII_Data!$E$5:$E$186,RII_Data!$A$5:$A$186,G$4,RII_Data!$G$5:$G$186,$A9,RII_Data!$H$5:$H$186,"Direct",RII_Data!$C$5:$C$186,"Seed"),"") | H9: =COUNT(C9:G9) -> 2 | I9: =IF(H9=0,"",AVERAGE(C9:G9)) -> 0.777092 | J9: =IF(I9="","",RANK(I9,$I$5:$I$42,0)+COUNTIFS($I$5:$I$42,I9,$A$5:$A$42,"<"&$A9)) -> 4 | K9: =IF(J9="","",5-INT((J9-1)*5/$C$44)) -> 5 | L9: =IF(K9="","not seeded","p"&K9&" × i"&K9) -> p5 × i5 | M9: =IF(K9="","",IF(K9^2<=5,"Low",IF(K9^2<=10,"Moderate",IF(K9^2<=15,"High","Extreme")))) -> Extreme
A10: R-SAFE | B10: Unsafe conditions or work at height | C10: =IFERROR(AVERAGEIFS(RII_Data!$E$5:$E$186,RII_Data!$A$5:$A$186,C$4,RII_Data!$G$5:$G$186,$A10,RII_Data!$H$5:$H$186,"Direct",RII_Data!$C$5:$C$186,"Seed"),"") -> 0.7865 | D10: =IFERROR(AVERAGEIFS(RII_Data!$E$5:$E$186,RII_Data!$A$5:$A$186,D$4,RII_Data!$G$5:$G$186,$A10,RII_Data!$H$5:$H$186,"Direct",RII_Data!$C$5:$C$186,"Seed"),"") | E10: =IFERROR(AVERAGEIFS(RII_Data!$E$5:$E$186,RII_Data!$A$5:$A$186,E$4,RII_Data!$G$5:$G$186,$A10,RII_Data!$H$5:$H$186,"Direct",RII_Data!$C$5:$C$186,"Seed"),"") | F10: =IFERROR(AVERAGEIFS(RII_Data!$E$5:$E$186,RII_Data!$A$5:$A$186,F$4,RII_Data!$G$5:$G$186,$A10,RII_Data!$H$5:$H$186,"Direct",RII_Data!$C$5:$C$186,"Seed"),"") | G10: =IFERROR(AVERAGEIFS(RII_Data!$E$5:$E$186,RII_Data!$A$5:$A$186,G$4,RII_Data!$G$5:$G$186,$A10,RII_Data!$H$5:$H$186,"Direct",RII_Data!$C$5:$C$186,"Seed"),"") | H10: =COUNT(C10:G10) -> 1 | I10: =IF(H10=0,"",AVERAGE(C10:G10)) -> 0.7865 | J10: =IF(I10="","",RANK(I10,$I$5:$I$42,0)+COUNTIFS($I$5:$I$42,I10,$A$5:$A$42,"<"&$A10)) -> 2 | K10: =IF(J10="","",5-INT((J10-1)*5/$C$44)) -> 5 | L10: =IF(K10="","not seeded","p"&K10&" × i"&K10) -> p5 × i5 | M10: =IF(K10="","",IF(K10^2<=5,"Low",IF(K10^2<=10,"Moderate",IF(K10^2<=15,"High","Extreme")))) -> Extreme
A11: R-WX | B11: Rain / monsoon stoppage | C11: =IFERROR(AVERAGEIFS(RII_Data!$E$5:$E$186,RII_Data!$A$5:$A$186,C$4,RII_Data!$G$5:$G$186,$A11,RII_Data!$H$5:$H$186,"Direct",RII_Data!$C$5:$C$186,"Seed"),"") -> 0.764 | D11: =IFERROR(AVERAGEIFS(RII_Data!$E$5:$E$186,RII_Data!$A$5:$A$186,D$4,RII_Data!$G$5:$G$186,$A11,RII_Data!$H$5:$H$186,"Direct",RII_Data!$C$5:$C$186,"Seed"),"") -> 0.7 | E11: =IFERROR(AVERAGEIFS(RII_Data!$E$5:$E$186,RII_Data!$A$5:$A$186,E$4,RII_Data!$G$5:$G$186,$A11,RII_Data!$H$5:$H$186,"Direct",RII_Data!$C$5:$C$186,"Seed"),"") -> 0.656716 | F11: =IFERROR(AVERAGEIFS(RII_Data!$E$5:$E$186,RII_Data!$A$5:$A$186,F$4,RII_Data!$G$5:$G$186,$A11,RII_Data!$H$5:$H$186,"Direct",RII_Data!$C$5:$C$186,"Seed"),"") -> 0.6528 | G11: =IFERROR(AVERAGEIFS(RII_Data!$E$5:$E$186,RII_Data!$A$5:$A$186,G$4,RII_Data!$G$5:$G$186,$A11,RII_Data!$H$5:$H$186,"Direct",RII_Data!$C$5:$C$186,"Seed"),"") | H11: =COUNT(C11:G11) -> 4 | I11: =IF(H11=0,"",AVERAGE(C11:G11)) -> 0.693379 | J11: =IF(I11="","",RANK(I11,$I$5:$I$42,0)+COUNTIFS($I$5:$I$42,I11,$A$5:$A$42,"<"&$A11)) -> 24 | K11: =IF(J11="","",5-INT((J11-1)*5/$C$44)) -> 2 | L11: =IF(K11="","not seeded","p"&K11&" × i"&K11) -> p2 × i2 | M11: =IF(K11="","",IF(K11^2<=5,"Low",IF(K11^2<=10,"Moderate",IF(K11^2<=15,"High","Extreme")))) -> Low
A12: R-RWK | B12: Rework due to workmanship or defects | C12: =IFERROR(AVERAGEIFS(RII_Data!$E$5:$E$186,RII_Data!$A$5:$A$186,C$4,RII_Data!$G$5:$G$186,$A12,RII_Data!$H$5:$H$186,"Direct",RII_Data!$C$5:$C$186,"Seed"),"") -> 0.736 | D12: =IFERROR(AVERAGEIFS(RII_Data!$E$5:$E$186,RII_Data!$A$5:$A$186,D$4,RII_Data!$G$5:$G$186,$A12,RII_Data!$H$5:$H$186,"Direct",RII_Data!$C$5:$C$186,"Seed"),"") | E12: =IFERROR(AVERAGEIFS(RII_Data!$E$5:$E$186,RII_Data!$A$5:$A$186,E$4,RII_Data!$G$5:$G$186,$A12,RII_Data!$H$5:$H$186,"Direct",RII_Data!$C$5:$C$186,"Seed"),"") -> 0.776119 | F12: =IFERROR(AVERAGEIFS(RII_Data!$E$5:$E$186,RII_Data!$A$5:$A$186,F$4,RII_Data!$G$5:$G$186,$A12,RII_Data!$H$5:$H$186,"Direct",RII_Data!$C$5:$C$186,"Seed"),"") | G12: =IFERROR(AVERAGEIFS(RII_Data!$E$5:$E$186,RII_Data!$A$5:$A$186,G$4,RII_Data!$G$5:$G$186,$A12,RII_Data!$H$5:$H$186,"Direct",RII_Data!$C$5:$C$186,"Seed"),"") | H12: =COUNT(C12:G12) -> 2 | I12: =IF(H12=0,"",AVERAGE(C12:G12)) -> 0.7560595 | J12: =IF(I12="","",RANK(I12,$I$5:$I$42,0)+COUNTIFS($I$5:$I$42,I12,$A$5:$A$42,"<"&$A12)) -> 11 | K12: =IF(J12="","",5-INT((J12-1)*5/$C$44)) -> 4 | L12: =IF(K12="","not seeded","p"&K12&" × i"&K12) -> p4 × i4 | M12: =IF(K12="","",IF(K12^2<=5,"Low",IF(K12^2<=10,"Moderate",IF(K12^2<=15,"High","Extreme")))) -> Extreme
A13: R-PAY | B13: Payment delay | C13: =IFERROR(AVERAGEIFS(RII_Data!$E$5:$E$186,RII_Data!$A$5:$A$186,C$4,RII_Data!$G$5:$G$186,$A13,RII_Data!$H$5:$H$186,"Direct",RII_Data!$C$5:$C$186,"Seed"),"") -> 0.773 | D13: =IFERROR(AVERAGEIFS(RII_Data!$E$5:$E$186,RII_Data!$A$5:$A$186,D$4,RII_Data!$G$5:$G$186,$A13,RII_Data!$H$5:$H$186,"Direct",RII_Data!$C$5:$C$186,"Seed"),"") -> 0.7758 | E13: =IFERROR(AVERAGEIFS(RII_Data!$E$5:$E$186,RII_Data!$A$5:$A$186,E$4,RII_Data!$G$5:$G$186,$A13,RII_Data!$H$5:$H$186,"Direct",RII_Data!$C$5:$C$186,"Seed"),"") -> 0.771144 | F13: =IFERROR(AVERAGEIFS(RII_Data!$E$5:$E$186,RII_Data!$A$5:$A$186,F$4,RII_Data!$G$5:$G$186,$A13,RII_Data!$H$5:$H$186,"Direct",RII_Data!$C$5:$C$186,"Seed"),"") | G13: =IFERROR(AVERAGEIFS(RII_Data!$E$5:$E$186,RII_Data!$A$5:$A$186,G$4,RII_Data!$G$5:$G$186,$A13,RII_Data!$H$5:$H$186,"Direct",RII_Data!$C$5:$C$186,"Seed"),"") | H13: =COUNT(C13:G13) -> 3 | I13: =IF(H13=0,"",AVERAGE(C13:G13)) -> 0.77331467 | J13: =IF(I13="","",RANK(I13,$I$5:$I$42,0)+COUNTIFS($I$5:$I$42,I13,$A$5:$A$42,"<"&$A13)) -> 5 | K13: =IF(J13="","",5-INT((J13-1)*5/$C$44)) -> 5 | L13: =IF(K13="","not seeded","p"&K13&" × i"&K13) -> p5 × i5 | M13: =IF(K13="","",IF(K13^2<=5,"Low",IF(K13^2<=10,"Moderate",IF(K13^2<=15,"High","Extreme")))) -> Extreme
A14: R-DES | B14: Design changes or incomplete documentation | C14: =IFERROR(AVERAGEIFS(RII_Data!$E$5:$E$186,RII_Data!$A$5:$A$186,C$4,RII_Data!$G$5:$G$186,$A14,RII_Data!$H$5:$H$186,"Direct",RII_Data!$C$5:$C$186,"Seed"),"") -> 0.732 | D14: =IFERROR(AVERAGEIFS(RII_Data!$E$5:$E$186,RII_Data!$A$5:$A$186,D$4,RII_Data!$G$5:$G$186,$A14,RII_Data!$H$5:$H$186,"Direct",RII_Data!$C$5:$C$186,"Seed"),"") | E14: =IFERROR(AVERAGEIFS(RII_Data!$E$5:$E$186,RII_Data!$A$5:$A$186,E$4,RII_Data!$G$5:$G$186,$A14,RII_Data!$H$5:$H$186,"Direct",RII_Data!$C$5:$C$186,"Seed"),"") -> 0.785075 | F14: =IFERROR(AVERAGEIFS(RII_Data!$E$5:$E$186,RII_Data!$A$5:$A$186,F$4,RII_Data!$G$5:$G$186,$A14,RII_Data!$H$5:$H$186,"Direct",RII_Data!$C$5:$C$186,"Seed"),"") | G14: =IFERROR(AVERAGEIFS(RII_Data!$E$5:$E$186,RII_Data!$A$5:$A$186,G$4,RII_Data!$G$5:$G$186,$A14,RII_Data!$H$5:$H$186,"Direct",RII_Data!$C$5:$C$186,"Seed"),"") | H14: =COUNT(C14:G14) -> 2 | I14: =IF(H14=0,"",AVERAGE(C14:G14)) -> 0.7585375 | J14: =IF(I14="","",RANK(I14,$I$5:$I$42,0)+COUNTIFS($I$5:$I$42,I14,$A$5:$A$42,"<"&$A14)) -> 10 | K14: =IF(J14="","",5-INT((J14-1)*5/$C$44)) -> 4 | L14: =IF(K14="","not seeded","p"&K14&" × i"&K14) -> p4 × i4 | M14: =IF(K14="","",IF(K14^2<=5,"Low",IF(K14^2<=10,"Moderate",IF(K14^2<=15,"High","Extreme")))) -> Extreme
A15: R-SUP | B15: Inadequate supervision or monitoring of workers | C15: =IFERROR(AVERAGEIFS(RII_Data!$E$5:$E$186,RII_Data!$A$5:$A$186,C$4,RII_Data!$G$5:$G$186,$A15,RII_Data!$H$5:$H$186,"Direct",RII_Data!$C$5:$C$186,"Seed"),"") -> 0.744 | D15: =IFERROR(AVERAGEIFS(RII_Data!$E$5:$E$186,RII_Data!$A$5:$A$186,D$4,RII_Data!$G$5:$G$186,$A15,RII_Data!$H$5:$H$186,"Direct",RII_Data!$C$5:$C$186,"Seed"),"") | E15: =IFERROR(AVERAGEIFS(RII_Data!$E$5:$E$186,RII_Data!$A$5:$A$186,E$4,RII_Data!$G$5:$G$186,$A15,RII_Data!$H$5:$H$186,"Direct",RII_Data!$C$5:$C$186,"Seed"),"") | F15: =IFERROR(AVERAGEIFS(RII_Data!$E$5:$E$186,RII_Data!$A$5:$A$186,F$4,RII_Data!$G$5:$G$186,$A15,RII_Data!$H$5:$H$186,"Direct",RII_Data!$C$5:$C$186,"Seed"),"") | G15: =IFERROR(AVERAGEIFS(RII_Data!$E$5:$E$186,RII_Data!$A$5:$A$186,G$4,RII_Data!$G$5:$G$186,$A15,RII_Data!$H$5:$H$186,"Direct",RII_Data!$C$5:$C$186,"Seed"),"") | H15: =COUNT(C15:G15) -> 1 | I15: =IF(H15=0,"",AVERAGE(C15:G15)) -> 0.744 | J15: =IF(I15="","",RANK(I15,$I$5:$I$42,0)+COUNTIFS($I$5:$I$42,I15,$A$5:$A$42,"<"&$A15)) -> 16 | K15: =IF(J15="","",5-INT((J15-1)*5/$C$44)) -> 3 | L15: =IF(K15="","not seeded","p"&K15&" × i"&K15) -> p3 × i3 | M15: =IF(K15="","",IF(K15^2<=5,"Low",IF(K15^2<=10,"Moderate",IF(K15^2<=15,"High","Extreme")))) -> Moderate
A16: R-MOT | B16: Low motivation, morale or labour turnover | C16: =IFERROR(AVERAGEIFS(RII_Data!$E$5:$E$186,RII_Data!$A$5:$A$186,C$4,RII_Data!$G$5:$G$186,$A16,RII_Data!$H$5:$H$186,"Direct",RII_Data!$C$5:$C$186,"Seed"),"") -> 0.736 | D16: =IFERROR(AVERAGEIFS(RII_Data!$E$5:$E$186,RII_Data!$A$5:$A$186,D$4,RII_Data!$G$5:$G$186,$A16,RII_Data!$H$5:$H$186,"Direct",RII_Data!$C$5:$C$186,"Seed"),"") | E16: =IFERROR(AVERAGEIFS(RII_Data!$E$5:$E$186,RII_Data!$A$5:$A$186,E$4,RII_Data!$G$5:$G$186,$A16,RII_Data!$H$5:$H$186,"Direct",RII_Data!$C$5:$C$186,"Seed"),"") | F16: =IFERROR(AVERAGEIFS(RII_Data!$E$5:$E$186,RII_Data!$A$5:$A$186,F$4,RII_Data!$G$5:$G$186,$A16,RII_Data!$H$5:$H$186,"Direct",RII_Data!$C$5:$C$186,"Seed"),"") | G16: =IFERROR(AVERAGEIFS(RII_Data!$E$5:$E$186,RII_Data!$A$5:$A$186,G$4,RII_Data!$G$5:$G$186,$A16,RII_Data!$H$5:$H$186,"Direct",RII_Data!$C$5:$C$186,"Seed"),"") | H16: =COUNT(C16:G16) -> 1 | I16: =IF(H16=0,"",AVERAGE(C16:G16)) -> 0.736 | J16: =IF(I16="","",RANK(I16,$I$5:$I$42,0)+COUNTIFS($I$5:$I$42,I16,$A$5:$A$42,"<"&$A16)) -> 17 | K16: =IF(J16="","",5-INT((J16-1)*5/$C$44)) -> 3 | L16: =IF(K16="","not seeded","p"&K16&" × i"&K16) -> p3 × i3 | M16: =IF(K16="","",IF(K16^2<=5,"Low",IF(K16^2<=10,"Moderate",IF(K16^2<=15,"High","Extreme")))) -> Moderate
... A42: R-FIN | B42: Contractor financial difficulties | C42: =IFERROR(AVERAGEIFS(RII_Data!$E$5:$E$186,RII_Data!$A$5:$A$186,C$4,RII_Data!$G$5:$G$186,$A42,RII_Data!$H$5:$H$186,"Direct",RII_Data!$C$5:$C$186,"Seed"),"") | D42: =IFERROR(AVERAGEIFS(RII_Data!$E$5:$E$186,RII_Data!$A$5:$A$186,D$4,RII_Data!$G$5:$G$186,$A42,RII_Data!$H$5:$H$186,"Direct",RII_Data!$C$5:$C$186,"Seed"),"") | E42: =IFERROR(AVERAGEIFS(RII_Data!$E$5:$E$186,RII_Data!$A$5:$A$186,E$4,RII_Data!$G$5:$G$186,$A42,RII_Data!$H$5:$H$186,"Direct",RII_Data!$C$5:$C$186,"Seed"),"") | F42: =IFERROR(AVERAGEIFS(RII_Data!$E$5:$E$186,RII_Data!$A$5:$A$186,F$4,RII_Data!$G$5:$G$186,$A42,RII_Data!$H$5:$H$186,"Direct",RII_Data!$C$5:$C$186,"Seed"),"") | G42: =IFERROR(AVERAGEIFS(RII_Data!$E$5:$E$186,RII_Data!$A$5:$A$186,G$4,RII_Data!$G$5:$G$186,$A42,RII_Data!$H$5:$H$186,"Direct",RII_Data!$C$5:$C$186,"Seed"),"") | H42: =COUNT(C42:G42) -> 0 | I42: =IF(H42=0,"",AVERAGE(C42:G42)) | J42: =IF(I42="","",RANK(I42,$I$5:$I$42,0)+COUNTIFS($I$5:$I$42,I42,$A$5:$A$42,"<"&$A42)) | K42: =IF(J42="","",5-INT((J42-1)*5/$C$44)) | L42: =IF(K42="","not seeded","p"&K42&" × i"&K42) -> not seeded | M42: =IF(K42="","",IF(K42^2<=5,"Low",IF(K42^2<=10,"Moderate",IF(K42^2<=15,"High","Extreme"))))
B44: Risks seeded (n) | C44: =COUNT(I5:I42) -> 30
B45: Highest mean RII | C45: =MAX(I5:I42) -> 0.78893333
B46: Lowest mean RII | C46: =MIN(I5:I42) -> 0.59403
B47: Spread (highest - lowest) | C47: =C45-C46 -> 0.19490333
B48: Spread without the lowest risk | C48: =C45-SMALL(I5:I42,2) -> 0.17893333
A51: How to read this sheet:
A52: 1. Study columns: AVERAGEIFS over RII_Data rows with that study, that risk, mapping = Direct and role = Seed. Two direct items in one study are averaged first, so every study counts once.
A53: 2. Seed mean RII = plain average of the study columns that have a value.
A54: 3. Rank 1 = highest mean. Class = 5 - INT((rank - 1) x 5 / n), n = number of seeded risks (cell below). The ranks are cut into five bands of about n/5 risks each; with n = 30, ranks 1-6 -> class 5, 7-12 -> 4, 13-18 -> 3, 19-24 -> 2, 25-30 -> 1. Risks with no seed-study value stay unranked.
A55: 4. The class is used for BOTH axes because an RII is an importance rating, not a probability and not days of delay. Level uses the app's thresholds: score <= 5 Low, <= 10 Moderate, <= 15 High, else Extreme.
A56: 5. In the app, a site-fact rule flag raises the probability class by one (max 5), and entering your own probability and delay replaces the seed completely.
A57: 6. Caution: most mean RIIs lie within a few hundredths of each other (see the spread rows). The bands make small differences look large, so treat the seed as a weak starting order.
A58: 7. Ties: equal means are ordered by risk ID, the same rule the app uses (R-MTH and R-STO tie at 0.700).

Sheet Validation
A1: Validation: does the seed ranking agree with studies the model did NOT use?
A2: Spearman rank correlation between the seed mean RII and each held-out study, over the risks both cover (direct items only).
A4: Study | B4: Region / respondents | C4: Risks in common (n) | D4: Spearman rho | E4: t | F4: p (two-tailed) | G4: Reading
A5: M10 | B5: Middle East (10 studies: Malaysia, Palestine, Kuwait, Qatar, Saudi Arabia, Egypt, Bahrain, Oman, Yemen, Vietnam); Meta-analysis: pooled RII ('effect summary', random model) of 35 factors | C5: =C33 -> 19 | D5: =C32 -> 0.28170253 | E5: =C34 -> 1.2105129 | F5: =C35 -> 0.24264424 | G5: =IF(F5<0.05,IF(D5>0,"Agrees (significant at 5%)","Disagrees (significant at 5%)"),IF(D5>=0.5,"Moderate agreement, not significant (small n)",IF(D5>=0.2,"Weak agreement, not significant",IF(D5<=-0.5,"Moderate disagreement, not significant (small n)",IF(D5<=-0.2,"Weak disagreement, not significant","No clear relation"))))) -> Weak agreement, not significant
A6: M15 | B6: Brazil (Brasilia); Private building companies; directors, managers, engineers | C6: =C52 -> 11 | D6: =C51 -> 0.62727273 | E6: =C53 -> 2.4163058 | F6: =C54 -> 0.038845254 | G6: =IF(F6<0.05,IF(D6>0,"Agrees (significant at 5%)","Disagrees (significant at 5%)"),IF(D6>=0.5,"Moderate agreement, not significant (small n)",IF(D6>=0.2,"Weak agreement, not significant",IF(D6<=-0.5,"Moderate disagreement, not significant (small n)",IF(D6<=-0.2,"Weak disagreement, not significant","No clear relation"))))) -> Agrees (significant at 5%)
A7: M14 | B7: Indonesia (East Java); Construction WORKERS' perspective | C7: =C73 -> 13 | D7: =C72 -> -0.18131868 | E7: =C74 -> -0.61150205 | F7: =C75 -> 0.55329501 | G7: =IF(F7<0.05,IF(D7>0,"Agrees (significant at 5%)","Disagrees (significant at 5%)"),IF(D7>=0.5,"Moderate agreement, not significant (small n)",IF(D7>=0.2,"Weak agreement, not significant",IF(D7<=-0.5,"Moderate disagreement, not significant (small n)",IF(D7<=-0.2,"Weak disagreement, not significant","No clear relation"))))) -> No clear relation
A11: M10: Adebowale & Agumba 2023 (Middle East (10 studies: Malaysia, Palestine, Kuwait, Qatar, Saudi Arabia, Egypt, Bahrain, Oman, Yemen, Vietnam))
A12: Risk ID | B12: Risk | C12: Seed mean RII | D12: Study RII (direct, averaged) | E12: Seed rank | F12: Study rank | G12: Rank difference
A13: R-MAT | B13: Brick / block / mortar material shortage or late delivery | C13: =INDEX(Seed_Calculation!$I$5:$I$42,MATCH(A13,Seed_Calculation!$A$5:$A$42,0)) -> 0.78893333 | D13: =AVERAGEIFS(RII_Data!$E$5:$E$186,RII_Data!$A$5:$A$186,"M10",RII_Data!$G$5:$G$186,A13,RII_Data!$H$5:$H$186,"Direct") -> 0.775 | E13: =RANK(C13,$C$13:$C$31,0)+(COUNTIF($C$13:$C$31,C13)-1)/2 -> 1 | F13: =RANK(D13,$D$13:$D$31,0)+(COUNTIF($D$13:$D$31,D13)-1)/2 -> 5 | G13: =E13-F13 -> -4
A14: R-TOOL | B14: Tools and equipment delay | C14: =INDEX(Seed_Calculation!$I$5:$I$42,MATCH(A14,Seed_Calculation!$A$5:$A$42,0)) -> 0.75275 | D14: =AVERAGEIFS(RII_Data!$E$5:$E$186,RII_Data!$A$5:$A$186,"M10",RII_Data!$G$5:$G$186,A14,RII_Data!$H$5:$H$186,"Direct") -> 0.691 | E14: =RANK(C14,$C$13:$C$31,0)+(COUNTIF($C$13:$C$31,C14)-1)/2 -> 8 | F14: =RANK(D14,$D$13:$D$31,0)+(COUNTIF($D$13:$D$31,D14)-1)/2 -> 14 | G14: =E14-F14 -> -6
A15: R-LAB | B15: Labour absenteeism or shortage | C15: =INDEX(Seed_Calculation!$I$5:$I$42,MATCH(A15,Seed_Calculation!$A$5:$A$42,0)) -> 0.76616667 | D15: =AVERAGEIFS(RII_Data!$E$5:$E$186,RII_Data!$A$5:$A$186,"M10",RII_Data!$G$5:$G$186,A15,RII_Data!$H$5:$H$186,"Direct") -> 0.66 | E15: =RANK(C15,$C$13:$C$31,0)+(COUNTIF($C$13:$C$31,C15)-1)/2 -> 5 | F15: =RANK(D15,$D$13:$D$31,0)+(COUNTIF($D$13:$D$31,D15)-1)/2 -> 18 | G15: =E15-F15 -> -13
A16: R-SKILL | B16: Unskilled or unqualified labour | C16: =INDEX(Seed_Calculation!$I$5:$I$42,MATCH(A16,Seed_Calculation!$A$5:$A$42,0)) -> 0.78311111 | D16: =AVERAGEIFS(RII_Data!$E$5:$E$186,RII_Data!$A$5:$A$186,"M10",RII_Data!$G$5:$G$186,A16,RII_Data!$H$5:$H$186,"Direct") -> 0.801 | E16: =RANK(C16,$C$13:$C$31,0)+(COUNTIF($C$13:$C$31,C16)-1)/2 -> 2 | F16: =RANK(D16,$D$13:$D$31,0)+(COUNTIF($D$13:$D$31,D16)-1)/2 -> 2 | G16: =E16-F16 -> 0
A17: R-PLAN | B17: Poor planning or unrealistic scheduling | C17: =INDEX(Seed_Calculation!$I$5:$I$42,MATCH(A17,Seed_Calculation!$A$5:$A$42,0)) -> 0.777092 | D17: =AVERAGEIFS(RII_Data!$E$5:$E$186,RII_Data!$A$5:$A$186,"M10",RII_Data!$G$5:$G$186,A17,RII_Data!$H$5:$H$186,"Direct") -> 0.698 | E17: =RANK(C17,$C$13:$C$31,0)+(COUNTIF($C$13:$C$31,C17)-1)/2 -> 3 | F17: =RANK(D17,$D$13:$D$31,0)+(COUNTIF($D$13:$D$31,D17)-1)/2 -> 12 | G17: =E17-F17 -> -9
A18: R-WX | B18: Rain / monsoon stoppage | C18: =INDEX(Seed_Calculation!$I$5:$I$42,MATCH(A18,Seed_Calculation!$A$5:$A$42,0)) -> 0.693379 | D18: =AVERAGEIFS(RII_Data!$E$5:$E$186,RII_Data!$A$5:$A$186,"M10",RII_Data!$G$5:$G$186,A18,RII_Data!$H$5:$H$186,"Direct") -> 0.715 | E18: =RANK(C18,$C$13:$C$31,0)+(COUNTIF($C$13:$C$31,C18)-1)/2 -> 16 | F18: =RANK(D18,$D$13:$D$31,0)+(COUNTIF($D$13:$D$31,D18)-1)/2 -> 10 | G18: =E18-F18 -> 6
A19: R-RWK | B19: Rework due to workmanship or defects | C19: =INDEX(Seed_Calculation!$I$5:$I$42,MATCH(A19,Seed_Calculation!$A$5:$A$42,0)) -> 0.7560595 | D19: =AVERAGEIFS(RII_Data!$E$5:$E$186,RII_Data!$A$5:$A$186,"M10",RII_Data!$G$5:$G$186,A19,RII_Data!$H$5:$H$186,"Direct") -> 0.761 | E19: =RANK(C19,$C$13:$C$31,0)+(COUNTIF($C$13:$C$31,C19)-1)/2 -> 7 | F19: =RANK(D19,$D$13:$D$31,0)+(COUNTIF($D$13:$D$31,D19)-1)/2 -> 6 | G19: =E19-F19 -> 1
A20: R-PAY | B20: Payment delay | C20: =INDEX(Seed_Calculation!$I$5:$I$42,MATCH(A20,Seed_Calculation!$A$5:$A$42,0)) -> 0.77331467 | D20: =AVERAGEIFS(RII_Data!$E$5:$E$186,RII_Data!$A$5:$A$186,"M10",RII_Data!$G$5:$G$186,A20,RII_Data!$H$5:$H$186,"Direct") -> 0.751 | E20: =RANK(C20,$C$13:$C$31,0)+(COUNTIF($C$13:$C$31,C20)-1)/2 -> 4 | F20: =RANK(D20,$D$13:$D$31,0)+(COUNTIF($D$13:$D$31,D20)-1)/2 -> 8 | G20: =E20-F20 -> -4
A21: R-DES | B21: Design changes or incomplete documentation | C21: =INDEX(Seed_Calculation!$I$5:$I$42,MATCH(A21,Seed_Calculation!$A$5:$A$42,0)) -> 0.7585375 | D21: =AVERAGEIFS(RII_Data!$E$5:$E$186,RII_Data!$A$5:$A$186,"M10",RII_Data!$G$5:$G$186,A21,RII_Data!$H$5:$H$186,"Direct") -> 0.7755 | E21: =RANK(C21,$C$13:$C$31,0)+(COUNTIF($C$13:$C$31,C21)-1)/2 -> 6 | F21: =RANK(D21,$D$13:$D$31,0)+(COUNTIF($D$13:$D$31,D21)-1)/2 -> 4 | G21: =E21-F21 -> 2
A22: R-SUP | B22: Inadequate supervision or monitoring of workers | C22: =INDEX(Seed_Calculation!$I$5:$I$42,MATCH(A22,Seed_Calculation!$A$5:$A$42,0)) -> 0.744 | D22: =AVERAGEIFS(RII_Data!$E$5:$E$186,RII_Data!$A$5:$A$186,"M10",RII_Data!$G$5:$G$186,A22,RII_Data!$H$5:$H$186,"Direct") -> 0.816 | E22: =RANK(C22,$C$13:$C$31,0)+(COUNTIF($C$13:$C$31,C22)-1)/2 -> 10 | F22: =RANK(D22,$D$13:$D$31,0)+(COUNTIF($D$13:$D$31,D22)-1)/2 -> 1 | G22: =E22-F22 -> 9
A23: R-MOT | B23: Low motivation, morale or labour turnover | C23: =INDEX(Seed_Calculation!$I$5:$I$42,MATCH(A23,Seed_Calculation!$A$5:$A$42,0)) -> 0.736 | D23: =AVERAGEIFS(RII_Data!$E$5:$E$186,RII_Data!$A$5:$A$186,"M10",RII_Data!$G$5:$G$186,A23,RII_Data!$H$5:$H$186,"Direct") -> 0.709 | E23: =RANK(C23,$C$13:$C$31,0)+(COUNTIF($C$13:$C$31,C23)-1)/2 -> 11 | F23: =RANK(D23,$D$13:$D$31,0)+(COUNTIF($D$13:$D$31,D23)-1)/2 -> 11 | G23: =E23-F23 -> 0
A24: R-INC | B24: Inadequate wages or incentives | C24: =INDEX(Seed_Calculation!$I$5:$I$42,MATCH(A24,Seed_Calculation!$A$5:$A$42,0)) -> 0.752 | D24: =AVERAGEIFS(RII_Data!$E$5:$E$186,RII_Data!$A$5:$A$186,"M10",RII_Data!$G$5:$G$186,A24,RII_Data!$H$5:$H$186,"Direct") -> 0.7605 | E24: =RANK(C24,$C$13:$C$31,0)+(COUNTIF($C$13:$C$31,C24)-1)/2 -> 9 | F24: =RANK(D24,$D$13:$D$31,0)+(COUNTIF($D$13:$D$31,D24)-1)/2 -> 7 | G24: =E24-F24 -> 2
... A31: R-ECO | B31: Economic conditions, inflation or interest rates | C31: =INDEX(Seed_Calculation!$I$5:$I$42,MATCH(A31,Seed_Calculation!$A$5:$A$42,0)) -> 0.661194 | D31: =AVERAGEIFS(RII_Data!$E$5:$E$186,RII_Data!$A$5:$A$186,"M10",RII_Data!$G$5:$G$186,A31,RII_Data!$H$5:$H$186,"Direct") -> 0.778 | E31: =RANK(C31,$C$13:$C$31,0)+(COUNTIF($C$13:$C$31,C31)-1)/2 -> 18 | F31: =RANK(D31,$D$13:$D$31,0)+(COUNTIF($D$13:$D$31,D31)-1)/2 -> 3 | G31: =E31-F31 -> 15
B32: Spearman rho (CORREL of the ranks) | C32: =CORREL(E13:E31,F13:F31) -> 0.28170253
B33: n (risks in common) | C33: =COUNT(D13:D31) -> 19
B34: t = rho x SQRT((n-2)/(1-rho^2)) | C34: =C32*SQRT((C33-2)/(1-C32^2)) -> 1.2105129
B35: p-value, two-tailed (t-distribution, n-2 df) | C35: =TDIST(ABS(C34),C33-2,2) -> 0.24264424
A38: M15: de Almeida, Feitoza, Carvalho, Pina, Araujo et al. 2021 (Brazil (Brasilia))
A39: Risk ID | B39: Risk | C39: Seed mean RII | D39: Study RII (direct, averaged) | E39: Seed rank | F39: Study rank | G39: Rank difference
A40: R-MAT | B40: Brick / block / mortar material shortage or late delivery | C40: =INDEX(Seed_Calculation!$I$5:$I$42,MATCH(A40,Seed_Calculation!$A$5:$A$42,0)) -> 0.78893333 | D40: =AVERAGEIFS(RII_Data!$E$5:$E$186,RII_Data!$A$5:$A$186,"M15",RII_Data!$G$5:$G$186,A40,RII_Data!$H$5:$H$186,"Direct") -> 0.56666667 | E40: =RANK(C40,$C$40:$C$50,0)+(COUNTIF($C$40:$C$50,C40)-1)/2 -> 1 | F40: =RANK(D40,$D$40:$D$50,0)+(COUNTIF($D$40:$D$50,D40)-1)/2 -> 6 | G40: =E40-F40 -> -5
A41: R-TOOL | B41: Tools and equipment delay | C41: =INDEX(Seed_Calculation!$I$5:$I$42,MATCH(A41,Seed_Calculation!$A$5:$A$42,0)) -> 0.75275 | D41: =AVERAGEIFS(RII_Data!$E$5:$E$186,RII_Data!$A$5:$A$186,"M15",RII_Data!$G$5:$G$186,A41,RII_Data!$H$5:$H$186,"Direct") -> 0.435 | E41: =RANK(C41,$C$40:$C$50,0)+(COUNTIF($C$40:$C$50,C41)-1)/2 -> 6 | F41: =RANK(D41,$D$40:$D$50,0)+(COUNTIF($D$40:$D$50,D41)-1)/2 -> 11 | G41: =E41-F41 -> -5
A42: R-SKILL | B42: Unskilled or unqualified labour | C42: =INDEX(Seed_Calculation!$I$5:$I$42,MATCH(A42,Seed_Calculation!$A$5:$A$42,0)) -> 0.78311111 | D42: =AVERAGEIFS(RII_Data!$E$5:$E$186,RII_Data!$A$5:$A$186,"M15",RII_Data!$G$5:$G$186,A42,RII_Data!$H$5:$H$186,"Direct") -> 0.715 | E42: =RANK(C42,$C$40:$C$50,0)+(COUNTIF($C$40:$C$50,C42)-1)/2 -> 2 | F42: =RANK(D42,$D$40:$D$50,0)+(COUNTIF($D$40:$D$50,D42)-1)/2 -> 2 | G42: =E42-F42 -> 0
A43: R-PLAN | B43: Poor planning or unrealistic scheduling | C43: =INDEX(Seed_Calculation!$I$5:$I$42,MATCH(A43,Seed_Calculation!$A$5:$A$42,0)) -> 0.777092 | D43: =AVERAGEIFS(RII_Data!$E$5:$E$186,RII_Data!$A$5:$A$186,"M15",RII_Data!$G$5:$G$186,A43,RII_Data!$H$5:$H$186,"Direct") -> 0.64 | E43: =RANK(C43,$C$40:$C$50,0)+(COUNTIF($C$40:$C$50,C43)-1)/2 -> 3 | F43: =RANK(D43,$D$40:$D$50,0)+(COUNTIF($D$40:$D$50,D43)-1)/2 -> 4 | G43: =E43-F43 -> -1
A44: R-WX | B44: Rain / monsoon stoppage | C44: =INDEX(Seed_Calculation!$I$5:$I$42,MATCH(A44,Seed_Calculation!$A$5:$A$42,0)) -> 0.693379 | D44: =AVERAGEIFS(RII_Data!$E$5:$E$186,RII_Data!$A$5:$A$186,"M15",RII_Data!$G$5:$G$186,A44,RII_Data!$H$5:$H$186,"Direct") -> 0.475 | E44: =RANK(C44,$C$40:$C$50,0)+(COUNTIF($C$40:$C$50,C44)-1)/2 -> 11 | F44: =RANK(D44,$D$40:$D$50,0)+(COUNTIF($D$40:$D$50,D44)-1)/2 -> 8 | G44: =E44-F44 -> 3
A45: R-RWK | B45: Rework due to workmanship or defects | C45: =INDEX(Seed_Calculation!$I$5:$I$42,MATCH(A45,Seed_Calculation!$A$5:$A$42,0)) -> 0.7560595 | D45: =AVERAGEIFS(RII_Data!$E$5:$E$186,RII_Data!$A$5:$A$186,"M15",RII_Data!$G$5:$G$186,A45,RII_Data!$H$5:$H$186,"Direct") -> 0.75 | E45: =RANK(C45,$C$40:$C$50,0)+(COUNTIF($C$40:$C$50,C45)-1)/2 -> 5 | F45: =RANK(D45,$D$40:$D$50,0)+(COUNTIF($D$40:$D$50,D45)-1)/2 -> 1 | G45: =E45-F45 -> 4
A46: R-DES | B46: Design changes or incomplete documentation | C46: =INDEX(Seed_Calculation!$I$5:$I$42,MATCH(A46,Seed_Calculation!$A$5:$A$42,0)) -> 0.7585375 | D46: =AVERAGEIFS(RII_Data!$E$5:$E$186,RII_Data!$A$5:$A$186,"M15",RII_Data!$G$5:$G$186,A46,RII_Data!$H$5:$H$186,"Direct") -> 0.6925 | E46: =RANK(C46,$C$40:$C$50,0)+(COUNTIF($C$40:$C$50,C46)-1)/2 -> 4 | F46: =RANK(D46,$D$40:$D$50,0)+(COUNTIF($D$40:$D$50,D46)-1)/2 -> 3 | G46: =E46-F46 -> 1
A47: R-ACC | B47: Accidents and injuries on site | C47: =INDEX(Seed_Calculation!$I$5:$I$42,MATCH(A47,Seed_Calculation!$A$5:$A$42,0)) -> 0.7045 | D47: =AVERAGEIFS(RII_Data!$E$5:$E$186,RII_Data!$A$5:$A$186,"M15",RII_Data!$G$5:$G$186,A47,RII_Data!$H$5:$H$186,"Direct") -> 0.455 | E47: =RANK(C47,$C$40:$C$50,0)+(COUNTIF($C$40:$C$50,C47)-1)/2 -> 9 | F47: =RANK(D47,$D$40:$D$50,0)+(COUNTIF($D$40:$D$50,D47)-1)/2 -> 9 | G47: =E47-F47 -> 0
A48: R-MGT | B48: Poor site management and coordination | C48: =INDEX(Seed_Calculation!$I$5:$I$42,MATCH(A48,Seed_Calculation!$A$5:$A$42,0)) -> 0.733107 | D48: =AVERAGEIFS(RII_Data!$E$5:$E$186,RII_Data!$A$5:$A$186,"M15",RII_Data!$G$5:$G$186,A48,RII_Data!$H$5:$H$186,"Direct") -> 0.52 | E48: =RANK(C48,$C$40:$C$50,0)+(COUNTIF($C$40:$C$50,C48)-1)/2 -> 8 | F48: =RANK(D48,$D$40:$D$50,0)+(COUNTIF($D$40:$D$50,D48)-1)/2 -> 7 | G48: =E48-F48 -> 1
A49: R-CTR | B49: Contractual disputes and claims | C49: =INDEX(Seed_Calculation!$I$5:$I$42,MATCH(A49,Seed_Calculation!$A$5:$A$42,0)) -> 0.746766 | D49: =AVERAGEIFS(RII_Data!$E$5:$E$186,RII_Data!$A$5:$A$186,"M15",RII_Data!$G$5:$G$186,A49,RII_Data!$H$5:$H$186,"Direct") -> 0.61 | E49: =RANK(C49,$C$40:$C$50,0)+(COUNTIF($C$40:$C$50,C49)-1)/2 -> 7 | F49: =RANK(D49,$D$40:$D$50,0)+(COUNTIF($D$40:$D$50,D49)-1)/2 -> 5 | G49: =E49-F49 -> 2
A50: R-MTH | B50: Construction method or design complexity | C50: =INDEX(Seed_Calculation!$I$5:$I$42,MATCH(A50,Seed_Calculation!$A$5:$A$42,0)) -> 0.7 | D50: =AVERAGEIFS(RII_Data!$E$5:$E$186,RII_Data!$A$5:$A$186,"M15",RII_Data!$G$5:$G$186,A50,RII_Data!$H$5:$H$186,"Direct") -> 0.444 | E50: =RANK(C50,$C$40:$C$50,0)+(COUNTIF($C$40:$C$50,C50)-1)/2 -> 10 | F50: =RANK(D50,$D$40:$D$50,0)+(COUNTIF($D$40:$D$50,D50)-1)/2 -> 10 | G50: =E50-F50 -> 0
B51: Spearman rho (CORREL of the ranks) | C51: =CORREL(E40:E50,F40:F50) -> 0.62727273
B52: n (risks in common) | C52: =COUNT(D40:D50) -> 11
B53: t = rho x SQRT((n-2)/(1-rho^2)) | C53: =C51*SQRT((C52-2)/(1-C51^2)) -> 2.4163058
B54: p-value, two-tailed (t-distribution, n-2 df) | C54: =TDIST(ABS(C53),C52-2,2) -> 0.038845254
A57: M14: Loekito, Dani, Zulfikar, Triarso & Prasetyono 2026 (Indonesia (East Java))
A58: Risk ID | B58: Risk | C58: Seed mean RII | D58: Study RII (direct, averaged) | E58: Seed rank | F58: Study rank | G58: Rank difference
A59: R-MAT | B59: Brick / block / mortar material shortage or late delivery | C59: =INDEX(Seed_Calculation!$I$5:$I$42,MATCH(A59,Seed_Calculation!$A$5:$A$42,0)) -> 0.78893333 | D59: =AVERAGEIFS(RII_Data!$E$5:$E$186,RII_Data!$A$5:$A$186,"M14",RII_Data!$G$5:$G$186,A59,RII_Data!$H$5:$H$186,"Direct") -> 0.508 | E59: =RANK(C59,$C$59:$C$71,0)+(COUNTIF($C$59:$C$71,C59)-1)/2 -> 1 | F59: =RANK(D59,$D$59:$D$71,0)+(COUNTIF($D$59:$D$71,D59)-1)/2 -> 9 | G59: =E59-F59 -> -8
A60: R-TOOL | B60: Tools and equipment delay | C60: =INDEX(Seed_Calculation!$I$5:$I$42,MATCH(A60,Seed_Calculation!$A$5:$A$42,0)) -> 0.75275 | D60: =AVERAGEIFS(RII_Data!$E$5:$E$186,RII_Data!$A$5:$A$186,"M14",RII_Data!$G$5:$G$186,A60,RII_Data!$H$5:$H$186,"Direct") -> 0.689 | E60: =RANK(C60,$C$59:$C$71,0)+(COUNTIF($C$59:$C$71,C60)-1)/2 -> 6 | F60: =RANK(D60,$D$59:$D$71,0)+(COUNTIF($D$59:$D$71,D60)-1)/2 -> 4 | G60: =E60-F60 -> 2
A61: R-SKILL | B61: Unskilled or unqualified labour | C61: =INDEX(Seed_Calculation!$I$5:$I$42,MATCH(A61,Seed_Calculation!$A$5:$A$42,0)) -> 0.78311111 | D61: =AVERAGEIFS(RII_Data!$E$5:$E$186,RII_Data!$A$5:$A$186,"M14",RII_Data!$G$5:$G$186,A61,RII_Data!$H$5:$H$186,"Direct") -> 0.523 | E61: =RANK(C61,$C$59:$C$71,0)+(COUNTIF($C$59:$C$71,C61)-1)/2 -> 3 | F61: =RANK(D61,$D$59:$D$71,0)+(COUNTIF($D$59:$D$71,D61)-1)/2 -> 7 | G61: =E61-F61 -> -4
A62: R-PLAN | B62: Poor planning or unrealistic scheduling | C62: =INDEX(Seed_Calculation!$I$5:$I$42,MATCH(A62,Seed_Calculation!$A$5:$A$42,0)) -> 0.777092 | D62: =AVERAGEIFS(RII_Data!$E$5:$E$186,RII_Data!$A$5:$A$186,"M14",RII_Data!$G$5:$G$186,A62,RII_Data!$H$5:$H$186,"Direct") -> 0.475 | E62: =RANK(C62,$C$59:$C$71,0)+(COUNTIF($C$59:$C$71,C62)-1)/2 -> 4 | F62: =RANK(D62,$D$59:$D$71,0)+(COUNTIF($D$59:$D$71,D62)-1)/2 -> 11 | G62: =E62-F62 -> -7
A63: R-SAFE | B63: Unsafe conditions or work at height | C63: =INDEX(Seed_Calculation!$I$5:$I$42,MATCH(A63,Seed_Calculation!$A$5:$A$42,0)) -> 0.7865 | D63: =AVERAGEIFS(RII_Data!$E$5:$E$186,RII_Data!$A$5:$A$186,"M14",RII_Data!$G$5:$G$186,A63,RII_Data!$H$5:$H$186,"Direct") -> 0.46 | E63: =RANK(C63,$C$59:$C$71,0)+(COUNTIF($C$59:$C$71,C63)-1)/2 -> 2 | F63: =RANK(D63,$D$59:$D$71,0)+(COUNTIF($D$59:$D$71,D63)-1)/2 -> 12 | G63: =E63-F63 -> -10
A64: R-WX | B64: Rain / monsoon stoppage | C64: =INDEX(Seed_Calculation!$I$5:$I$42,MATCH(A64,Seed_Calculation!$A$5:$A$42,0)) -> 0.693379 | D64: =AVERAGEIFS(RII_Data!$E$5:$E$186,RII_Data!$A$5:$A$186,"M14",RII_Data!$G$5:$G$186,A64,RII_Data!$H$5:$H$186,"Direct") -> 0.643 | E64: =RANK(C64,$C$59:$C$71,0)+(COUNTIF($C$59:$C$71,C64)-1)/2 -> 11 | F64: =RANK(D64,$D$59:$D$71,0)+(COUNTIF($D$59:$D$71,D64)-1)/2 -> 6 | G64: =E64-F64 -> 5
A65: R-PAY | B65: Payment delay | C65: =INDEX(Seed_Calculation!$I$5:$I$42,MATCH(A65,Seed_Calculation!$A$5:$A$42,0)) -> 0.77331467 | D65: =AVERAGEIFS(RII_Data!$E$5:$E$186,RII_Data!$A$5:$A$186,"M14",RII_Data!$G$5:$G$186,A65,RII_Data!$H$5:$H$186,"Direct") -> 0.716 | E65: =RANK(C65,$C$59:$C$71,0)+(COUNTIF($C$59:$C$71,C65)-1)/2 -> 5 | F65: =RANK(D65,$D$59:$D$71,0)+(COUNTIF($D$59:$D$71,D65)-1)/2 -> 3 | G65: =E65-F65 -> 2
A66: R-SUP | B66: Inadequate supervision or monitoring of workers | C66: =INDEX(Seed_Calculation!$I$5:$I$42,MATCH(A66,Seed_Calculation!$A$5:$A$42,0)) -> 0.744 | D66: =AVERAGEIFS(RII_Data!$E$5:$E$186,RII_Data!$A$5:$A$186,"M14",RII_Data!$G$5:$G$186,A66,RII_Data!$H$5:$H$186,"Direct") -> 0.72 | E66: =RANK(C66,$C$59:$C$71,0)+(COUNTIF($C$59:$C$71,C66)-1)/2 -> 8 | F66: =RANK(D66,$D$59:$D$71,0)+(COUNTIF($D$59:$D$71,D66)-1)/2 -> 2 | G66: =E66-F66 -> 6
A67: R-MOT | B67: Low motivation, morale or labour turnover | C67: =INDEX(Seed_Calculation!$I$5:$I$42,MATCH(A67,Seed_Calculation!$A$5:$A$42,0)) -> 0.736 | D67: =AVERAGEIFS(RII_Data!$E$5:$E$186,RII_Data!$A$5:$A$186,"M14",RII_Data!$G$5:$G$186,A67,RII_Data!$H$5:$H$186,"Direct") -> 0.459 | E67: =RANK(C67,$C$59:$C$71,0)+(COUNTIF($C$59:$C$71,C67)-1)/2 -> 9 | F67: =RANK(D67,$D$59:$D$71,0)+(COUNTIF($D$59:$D$71,D67)-1)/2 -> 13 | G67: =E67-F67 -> -4
A68: R-INC | B68: Inadequate wages or incentives | C68: =INDEX(Seed_Calculation!$I$5:$I$42,MATCH(A68,Seed_Calculation!$A$5:$A$42,0)) -> 0.752 | D68: =AVERAGEIFS(RII_Data!$E$5:$E$186,RII_Data!$A$5:$A$186,"M14",RII_Data!$G$5:$G$186,A68,RII_Data!$H$5:$H$186,"Direct") -> 0.7255 | E68: =RANK(C68,$C$59:$C$71,0)+(COUNTIF($C$59:$C$71,C68)-1)/2 -> 7 | F68: =RANK(D68,$D$59:$D$71,0)+(COUNTIF($D$59:$D$71,D68)-1)/2 -> 1 | G68: =E68-F68 -> 6
A69: R-FAT | B69: Worker fatigue, age or personal problems | C69: =INDEX(Seed_Calculation!$I$5:$I$42,MATCH(A69,Seed_Calculation!$A$5:$A$42,0)) -> 0.61 | D69: =AVERAGEIFS(RII_Data!$E$5:$E$186,RII_Data!$A$5:$A$186,"M14",RII_Data!$G$5:$G$186,A69,RII_Data!$H$5:$H$186,"Direct") -> 0.6615 | E69: =RANK(C69,$C$59:$C$71,0)+(COUNTIF($C$59:$C$71,C69)-1)/2 -> 13 | F69: =RANK(D69,$D$59:$D$71,0)+(COUNTIF($D$59:$D$71,D69)-1)/2 -> 5 | G69: =E69-F69 -> 8
A70: R-COM | B70: Poor communication or misunderstanding on site | C70: =INDEX(Seed_Calculation!$I$5:$I$42,MATCH(A70,Seed_Calculation!$A$5:$A$42,0)) -> 0.6793035 | D70: =AVERAGEIFS(RII_Data!$E$5:$E$186,RII_Data!$A$5:$A$186,"M14",RII_Data!$G$5:$G$186,A70,RII_Data!$H$5:$H$186,"Direct") -> 0.518 | E70: =RANK(C70,$C$59:$C$71,0)+(COUNTIF($C$59:$C$71,C70)-1)/2 -> 12 | F70: =RANK(D70,$D$59:$D$71,0)+(COUNTIF($D$59:$D$71,D70)-1)/2 -> 8 | G70: =E70-F70 -> 4
A71: R-MTH | B71: Construction method or design complexity | C71: =INDEX(Seed_Calculation!$I$5:$I$42,MATCH(A71,Seed_Calculation!$A$5:$A$42,0)) -> 0.7 | D71: =AVERAGEIFS(RII_Data!$E$5:$E$186,RII_Data!$A$5:$A$186,"M14",RII_Data!$G$5:$G$186,A71,RII_Data!$H$5:$H$186,"Direct") -> 0.504 | E71: =RANK(C71,$C$59:$C$71,0)+(COUNTIF($C$59:$C$71,C71)-1)/2 -> 10 | F71: =RANK(D71,$D$59:$D$71,0)+(COUNTIF($D$59:$D$71,D71)-1)/2 -> 10 | G71: =E71-F71 -> 0
B72: Spearman rho (CORREL of the ranks) | C72: =CORREL(E59:E71,F59:F71) -> -0.18131868
B73: n (risks in common) | C73: =COUNT(D59:D71) -> 13
B74: t = rho x SQRT((n-2)/(1-rho^2)) | C74: =C72*SQRT((C73-2)/(1-C72^2)) -> -0.61150205
B75: p-value, two-tailed (t-distribution, n-2 df) | C75: =TDIST(ABS(C74),C73-2,2) -> 0.55329501
A78: Held-out studies not tested (fewer than 4 risks in common, too few for a rank correlation):
A79: A10 (India): 2 risk(s) in common: R-MAT, R-WX
A80: A21 (Thailand): 1 risk(s) in common: R-LAB
A81: HAS25 (Iraq): 1 risk(s) in common: R-PLAN
A83: How to read this sheet:
A84: rho = +1: same order as the seed; 0: unrelated; -1: opposite order. The more risks two studies share, the smaller the rho needed for significance (about 0.7 to 0.8 with 7 to 9 risks, about 0.45 with 20).
A85: M10 pools 10 surveys (mostly managers and engineers); M15 asks managers; M14 asks site WORKERS. Who answers changes the ranking, so compare like with like.
A86: This tests the RANKING only. It cannot test probabilities or days of delay; that needs site records (see docs/Site_Data_Collection_Form.docx).

Sheet Other_indices
A1: Values found in the literature but NOT used (different index or group-level only)
A4: ID | B4: Source | C4: Index | D4: Values | E4: Why not used
A5: A11 | B5: Soundarya et al. (2025), An investigation study on residential buildings for cost overrun, Scientific Reports, DOI 10.1038/s41598-025-95984-x (Chennai, India) | C5: Importance index II (frequency x severity), NOT RII | D5: Overall lag in schedule 0.71 (rank 1); rework/extra work 0.55 (2); inadequate skilled labour 0.53 (3); inadequate design/specification 0.52 (4); climatic variation 0.37 (11); hike in materials cost 0.29 (12) | E5: Different index; mixing it with RII would compare unlike scales.
A6: P1-23 | B6: Karthik & Rao (2019), Identifying the significant factors affecting masonry labour productivity in India, Int. J. Construction Management 22(3): 464-472, DOI 10.1080/15623599.2019.1631978 | C6: RII, factor-group average only | D6: Workforce-related factors: average RII 0.784 (120 site personnel, 38 factors) | E6: Only a group average is available (abstract); item values not read.

Sheet Standardised
A1: Bringing every study to one level: within-study z-scores
A2: z = (RII - mean RII of the study's factors) / SD of the study's factors. Mean 0 and SD 1 in every study, so scale and respondent differences drop out.
A4: Study | B4: Treatment (judgement) | C4: Factors (n) | D4: Mean RII | E4: SD | F4: Why
A5: M01 | B5: Truncated | C5: =COUNTIF(RII_Data!$A$5:$A$186,A5) -> 28 | D5: =AVERAGEIF(RII_Data!$A$5:$A$186,A5,RII_Data!$E$5:$E$186) -> 0.74825 | E5: =IF(C5>1,SQRT(SUMPRODUCT((RII_Data!$A$5:$A$186=A5)*(RII_Data!$E$5:$E$186-D5)^2)/(C5-1)),"") -> 0.027486866 | F5: paper lists only the 28 factors with RII > 0.7 (of 38): the lowest are cut off, so its z-scores are distorted; used only in Analysis B
A6: A02 | B6: Partial | C6: =COUNTIF(RII_Data!$A$5:$A$186,A6) -> 14 | D6: =AVERAGEIF(RII_Data!$A$5:$A$186,A6,RII_Data!$E$5:$E$186) -> 0.70534286 | E6: =IF(C6>1,SQRT(SUMPRODUCT((RII_Data!$A$5:$A$186=A6)*(RII_Data!$E$5:$E$186-D6)^2)/(C6-1)),"") -> 0.070719921 | F6: only some factors recorded (top-ranked or selected): z-scores would be biased, so not standardised
A7: M06 | B7: Complete | C7: =COUNTIF(RII_Data!$A$5:$A$186,A7) -> 40 | D7: =AVERAGEIF(RII_Data!$A$5:$A$186,A7,RII_Data!$E$5:$E$186) -> 0.72315918 | E7: =IF(C7>1,SQRT(SUMPRODUCT((RII_Data!$A$5:$A$186=A7)*(RII_Data!$E$5:$E$186-D7)^2)/(C7-1)),"") -> 0.049662585 | F7: all 40 factors printed
A8: A14 | B8: Partial | C8: =COUNTIF(RII_Data!$A$5:$A$186,A8) -> 5 | D8: =AVERAGEIF(RII_Data!$A$5:$A$186,A8,RII_Data!$E$5:$E$186) -> 0.7811 | E8: =IF(C8>1,SQRT(SUMPRODUCT((RII_Data!$A$5:$A$186=A8)*(RII_Data!$E$5:$E$186-D8)^2)/(C8-1)),"") -> 0.073422476 | F8: only some factors recorded (top-ranked or selected): z-scores would be biased, so not standardised
A9: A15 | B9: Partial | C9: =COUNTIF(RII_Data!$A$5:$A$186,A9) -> 5 | D9: =AVERAGEIF(RII_Data!$A$5:$A$186,A9,RII_Data!$E$5:$E$186) -> 0.802 | E9: =IF(C9>1,SQRT(SUMPRODUCT((RII_Data!$A$5:$A$186=A9)*(RII_Data!$E$5:$E$186-D9)^2)/(C9-1)),"") -> 0.013038405 | F9: only some factors recorded (top-ranked or selected): z-scores would be biased, so not standardised
A10: M10 | B10: Complete | C10: =COUNTIF(RII_Data!$A$5:$A$186,A10) -> 33 | D10: =AVERAGEIF(RII_Data!$A$5:$A$186,A10,RII_Data!$E$5:$E$186) -> 0.70615152 | E10: =IF(C10>1,SQRT(SUMPRODUCT((RII_Data!$A$5:$A$186=A10)*(RII_Data!$E$5:$E$186-D10)^2)/(C10-1)),"") -> 0.078417202 | F10: 33 of 35 pooled factors captured
A11: M15 | B11: Complete | C11: =COUNTIF(RII_Data!$A$5:$A$186,A11) -> 24 | D11: =AVERAGEIF(RII_Data!$A$5:$A$186,A11,RII_Data!$E$5:$E$186) -> 0.59308333 | E11: =IF(C11>1,SQRT(SUMPRODUCT((RII_Data!$A$5:$A$186=A11)*(RII_Data!$E$5:$E$186-D11)^2)/(C11-1)),"") -> 0.10917434 | F11: all 24 factors printed
A12: M14 | B12: Complete | C12: =COUNTIF(RII_Data!$A$5:$A$186,A12) -> 23 | D12: =AVERAGEIF(RII_Data!$A$5:$A$186,A12,RII_Data!$E$5:$E$186) -> 0.58656522 | E12: =IF(C12>1,SQRT(SUMPRODUCT((RII_Data!$A$5:$A$186=A12)*(RII_Data!$E$5:$E$186-D12)^2)/(C12-1)),"") -> 0.10731679 | F12: all 23 factors printed
A13: A10 | B13: Partial | C13: =COUNTIF(RII_Data!$A$5:$A$186,A13) -> 6 | D13: =AVERAGEIF(RII_Data!$A$5:$A$186,A13,RII_Data!$E$5:$E$186) -> 0.585 | E13: =IF(C13>1,SQRT(SUMPRODUCT((RII_Data!$A$5:$A$186=A13)*(RII_Data!$E$5:$E$186-D13)^2)/(C13-1)),"") -> 0.053434072 | F13: only some factors recorded (top-ranked or selected): z-scores would be biased, so not standardised
A14: A21 | B14: Partial | C14: =COUNTIF(RII_Data!$A$5:$A$186,A14) -> 2 | D14: =AVERAGEIF(RII_Data!$A$5:$A$186,A14,RII_Data!$E$5:$E$186) -> 0.755 | E14: =IF(C14>1,SQRT(SUMPRODUCT((RII_Data!$A$5:$A$186=A14)*(RII_Data!$E$5:$E$186-D14)^2)/(C14-1)),"") -> 0.031112698 | F14: only some factors recorded (top-ranked or selected): z-scores would be biased, so not standardised
A15: HAS25 | B15: Partial | C15: =COUNTIF(RII_Data!$A$5:$A$186,A15) -> 2 | D15: =AVERAGEIF(RII_Data!$A$5:$A$186,A15,RII_Data!$E$5:$E$186) -> 0.865 | E15: =IF(C15>1,SQRT(SUMPRODUCT((RII_Data!$A$5:$A$186=A15)*(RII_Data!$E$5:$E$186-D15)^2)/(C15-1)),"") -> 0.012727922 | F15: only some factors recorded (top-ranked or selected): z-scores would be biased, so not standardised
A18: Risk score = mean z of the study's DIRECT factors for the risk. Analysis A = the four complete studies; Analysis B adds M01.
A19: Risk | B19: Name | C19: M06 | D19: M10 | E19: M14 | F19: M15 | G19: M01 | H19: Studies (A) | I19: Pooled z (A) | J19: Rank (A) | K19: Studies (B) | L19: Pooled z (B) | M19: Rank (B)
A20: R-MAT | B20: Brick / block / mortar material shortage or late delivery | C20: =IFERROR(AVERAGEIFS(RII_Data!$K$5:$K$186,RII_Data!$A$5:$A$186,"M06",RII_Data!$G$5:$G$186,$A20,RII_Data!$H$5:$H$186,"Direct"),"") | D20: =IFERROR(AVERAGEIFS(RII_Data!$K$5:$K$186,RII_Data!$A$5:$A$186,"M10",RII_Data!$G$5:$G$186,$A20,RII_Data!$H$5:$H$186,"Direct"),"") -> 0.87797681 | E20: =IFERROR(AVERAGEIFS(RII_Data!$K$5:$K$186,RII_Data!$A$5:$A$186,"M14",RII_Data!$G$5:$G$186,$A20,RII_Data!$H$5:$H$186,"Direct"),"") -> -0.73208692 | F20: =IFERROR(AVERAGEIFS(RII_Data!$K$5:$K$186,RII_Data!$A$5:$A$186,"M15",RII_Data!$G$5:$G$186,$A20,RII_Data!$H$5:$H$186,"Direct"),"") -> -0.24196773 | G20: =IFERROR(AVERAGEIFS(RII_Data!$K$5:$K$186,RII_Data!$A$5:$A$186,"M01",RII_Data!$G$5:$G$186,$A20,RII_Data!$H$5:$H$186,"Direct"),"") -> 1.0459541 | H20: =COUNT(C20:F20) -> 3 | I20: =IF(H20=0,"",AVERAGE(C20:F20)) -> -0.032025945 | J20: =IF(I20="","",RANK(I20,$I$20:$I$57,0)) -> 16 | K20: =COUNT(C20:G20) -> 4 | L20: =IF(K20=0,"",AVERAGE(C20:G20)) -> 0.23746907 | M20: =IF(L20="","",RANK(L20,$L$20:$L$57,0)) -> 15
A21: R-TOOL | B21: Tools and equipment delay | C21: =IFERROR(AVERAGEIFS(RII_Data!$K$5:$K$186,RII_Data!$A$5:$A$186,"M06",RII_Data!$G$5:$G$186,$A21,RII_Data!$H$5:$H$186,"Direct"),"") | D21: =IFERROR(AVERAGEIFS(RII_Data!$K$5:$K$186,RII_Data!$A$5:$A$186,"M10",RII_Data!$G$5:$G$186,$A21,RII_Data!$H$5:$H$186,"Direct"),"") -> -0.19321673 | E21: =IFERROR(AVERAGEIFS(RII_Data!$K$5:$K$186,RII_Data!$A$5:$A$186,"M14",RII_Data!$G$5:$G$186,$A21,RII_Data!$H$5:$H$186,"Direct"),"") -> 0.95450845 | F21: =IFERROR(AVERAGEIFS(RII_Data!$K$5:$K$186,RII_Data!$A$5:$A$186,"M15",RII_Data!$G$5:$G$186,$A21,RII_Data!$H$5:$H$186,"Direct"),"") -> -1.4479898 | G21: =IFERROR(AVERAGEIFS(RII_Data!$K$5:$K$186,RII_Data!$A$5:$A$186,"M01",RII_Data!$G$5:$G$186,$A21,RII_Data!$H$5:$H$186,"Direct"),"") -> -0.10004778 | H21: =COUNT(C21:F21) -> 3 | I21: =IF(H21=0,"",AVERAGE(C21:F21)) -> -0.22889937 | J21: =IF(I21="","",RANK(I21,$I$20:$I$57,0)) -> 20 | K21: =COUNT(C21:G21) -> 4 | L21: =IF(K21=0,"",AVERAGE(C21:G21)) -> -0.19668647 | M21: =IF(L21="","",RANK(L21,$L$20:$L$57,0)) -> 21
A22: R-LAB | B22: Labour absenteeism or shortage | C22: =IFERROR(AVERAGEIFS(RII_Data!$K$5:$K$186,RII_Data!$A$5:$A$186,"M06",RII_Data!$G$5:$G$186,$A22,RII_Data!$H$5:$H$186,"Direct"),"") | D22: =IFERROR(AVERAGEIFS(RII_Data!$K$5:$K$186,RII_Data!$A$5:$A$186,"M10",RII_Data!$G$5:$G$186,$A22,RII_Data!$H$5:$H$186,"Direct"),"") -> -0.58853815 | E22: =IFERROR(AVERAGEIFS(RII_Data!$K$5:$K$186,RII_Data!$A$5:$A$186,"M14",RII_Data!$G$5:$G$186,$A22,RII_Data!$H$5:$H$186,"Direct"),"") | F22: =IFERROR(AVERAGEIFS(RII_Data!$K$5:$K$186,RII_Data!$A$5:$A$186,"M15",RII_Data!$G$5:$G$186,$A22,RII_Data!$H$5:$H$186,"Direct"),"") | G22: =IFERROR(AVERAGEIFS(RII_Data!$K$5:$K$186,RII_Data!$A$5:$A$186,"M01",RII_Data!$G$5:$G$186,$A22,RII_Data!$H$5:$H$186,"Direct"),"") -> -0.91862057 | H22: =COUNT(C22:F22) -> 1 | I22: =IF(H22=0,"",AVERAGE(C22:F22)) -> -0.58853815 | J22: =IF(I22="","",RANK(I22,$I$20:$I$57,0)) -> 26 | K22: =COUNT(C22:G22) -> 2 | L22: =IF(K22=0,"",AVERAGE(C22:G22)) -> -0.75357936 | M22: =IF(L22="","",RANK(L22,$L$20:$L$57,0)) -> 30
A23: R-SKILL | B23: Unskilled or unqualified labour | C23: =IFERROR(AVERAGEIFS(RII_Data!$K$5:$K$186,RII_Data!$A$5:$A$186,"M06",RII_Data!$G$5:$G$186,$A23,RII_Data!$H$5:$H$186,"Direct"),"") | D23: =IFERROR(AVERAGEIFS(RII_Data!$K$5:$K$186,RII_Data!$A$5:$A$186,"M10",RII_Data!$G$5:$G$186,$A23,RII_Data!$H$5:$H$186,"Direct"),"") -> 1.2095367 | E23: =IFERROR(AVERAGEIFS(RII_Data!$K$5:$K$186,RII_Data!$A$5:$A$186,"M14",RII_Data!$G$5:$G$186,$A23,RII_Data!$H$5:$H$186,"Direct"),"") -> -0.59231382 | F23: =IFERROR(AVERAGEIFS(RII_Data!$K$5:$K$186,RII_Data!$A$5:$A$186,"M15",RII_Data!$G$5:$G$186,$A23,RII_Data!$H$5:$H$186,"Direct"),"") -> 1.1167154 | G23: =IFERROR(AVERAGEIFS(RII_Data!$K$5:$K$186,RII_Data!$A$5:$A$186,"M01",RII_Data!$G$5:$G$186,$A23,RII_Data!$H$5:$H$186,"Direct"),"") -> 0.39109588 | H23: =COUNT(C23:F23) -> 3 | I23: =IF(H23=0,"",AVERAGE(C23:F23)) -> 0.57797944 | J23: =IF(I23="","",RANK(I23,$I$20:$I$57,0)) -> 10 | K23: =COUNT(C23:G23) -> 4 | L23: =IF(K23=0,"",AVERAGE(C23:G23)) -> 0.53125855 | M23: =IF(L23="","",RANK(L23,$L$20:$L$57,0)) -> 10
A24: R-PLAN | B24: Poor planning or unrealistic scheduling | C24: =IFERROR(AVERAGEIFS(RII_Data!$K$5:$K$186,RII_Data!$A$5:$A$186,"M06",RII_Data!$G$5:$G$186,$A24,RII_Data!$H$5:$H$186,"Direct"),"") -> 0.8059352 | D24: =IFERROR(AVERAGEIFS(RII_Data!$K$5:$K$186,RII_Data!$A$5:$A$186,"M10",RII_Data!$G$5:$G$186,$A24,RII_Data!$H$5:$H$186,"Direct"),"") -> -0.1039506 | E24: =IFERROR(AVERAGEIFS(RII_Data!$K$5:$K$186,RII_Data!$A$5:$A$186,"M14",RII_Data!$G$5:$G$186,$A24,RII_Data!$H$5:$H$186,"Direct"),"") -> -1.0395877 | F24: =IFERROR(AVERAGEIFS(RII_Data!$K$5:$K$186,RII_Data!$A$5:$A$186,"M15",RII_Data!$G$5:$G$186,$A24,RII_Data!$H$5:$H$186,"Direct"),"") -> 0.42974079 | G24: =IFERROR(AVERAGEIFS(RII_Data!$K$5:$K$186,RII_Data!$A$5:$A$186,"M01",RII_Data!$G$5:$G$186,$A24,RII_Data!$H$5:$H$186,"Direct"),"") -> 1.5552883 | H24: =COUNT(C24:F24) -> 4 | I24: =IF(H24=0,"",AVERAGE(C24:F24)) -> 0.023034416 | J24: =IF(I24="","",RANK(I24,$I$20:$I$57,0)) -> 14 | K24: =COUNT(C24:G24) -> 5 | L24: =IF(K24=0,"",AVERAGE(C24:G24)) -> 0.32948519 | M24: =IF(L24="","",RANK(L24,$L$20:$L$57,0)) -> 13
A25: R-SAFE | B25: Unsafe conditions or work at height | C25: =IFERROR(AVERAGEIFS(RII_Data!$K$5:$K$186,RII_Data!$A$5:$A$186,"M06",RII_Data!$G$5:$G$186,$A25,RII_Data!$H$5:$H$186,"Direct"),"") | D25: =IFERROR(AVERAGEIFS(RII_Data!$K$5:$K$186,RII_Data!$A$5:$A$186,"M10",RII_Data!$G$5:$G$186,$A25,RII_Data!$H$5:$H$186,"Direct"),"") | E25: =IFERROR(AVERAGEIFS(RII_Data!$K$5:$K$186,RII_Data!$A$5:$A$186,"M14",RII_Data!$G$5:$G$186,$A25,RII_Data!$H$5:$H$186,"Direct"),"") -> -1.1793608 | F25: =IFERROR(AVERAGEIFS(RII_Data!$K$5:$K$186,RII_Data!$A$5:$A$186,"M15",RII_Data!$G$5:$G$186,$A25,RII_Data!$H$5:$H$186,"Direct"),"") | G25: =IFERROR(AVERAGEIFS(RII_Data!$K$5:$K$186,RII_Data!$A$5:$A$186,"M01",RII_Data!$G$5:$G$186,$A25,RII_Data!$H$5:$H$186,"Direct"),"") -> 1.3915737 | H25: =COUNT(C25:F25) -> 1 | I25: =IF(H25=0,"",AVERAGE(C25:F25)) -> -1.1793608 | J25: =IF(I25="","",RANK(I25,$I$20:$I$57,0)) -> 31 | K25: =COUNT(C25:G25) -> 2 | L25: =IF(K25=0,"",AVERAGE(C25:G25)) -> 0.10610645 | M25: =IF(L25="","",RANK(L25,$L$20:$L$57,0)) -> 16
A26: R-WX | B26: Rain / monsoon stoppage | C26: =IFERROR(AVERAGEIFS(RII_Data!$K$5:$K$186,RII_Data!$A$5:$A$186,"M06",RII_Data!$G$5:$G$186,$A26,RII_Data!$H$5:$H$186,"Direct"),"") -> -1.337892 | D26: =IFERROR(AVERAGEIFS(RII_Data!$K$5:$K$186,RII_Data!$A$5:$A$186,"M10",RII_Data!$G$5:$G$186,$A26,RII_Data!$H$5:$H$186,"Direct"),"") -> 0.11283857 | E26: =IFERROR(AVERAGEIFS(RII_Data!$K$5:$K$186,RII_Data!$A$5:$A$186,"M14",RII_Data!$G$5:$G$186,$A26,RII_Data!$H$5:$H$186,"Direct"),"") -> 0.52587096 | F26: =IFERROR(AVERAGEIFS(RII_Data!$K$5:$K$186,RII_Data!$A$5:$A$186,"M15",RII_Data!$G$5:$G$186,$A26,RII_Data!$H$5:$H$186,"Direct"),"") -> -1.0816034 | G26: =IFERROR(AVERAGEIFS(RII_Data!$K$5:$K$186,RII_Data!$A$5:$A$186,"M01",RII_Data!$G$5:$G$186,$A26,RII_Data!$H$5:$H$186,"Direct"),"") -> 0.57300095 | H26: =COUNT(C26:F26) -> 4 | I26: =IF(H26=0,"",AVERAGE(C26:F26)) -> -0.44519647 | J26: =IF(I26="","",RANK(I26,$I$20:$I$57,0)) -> 24 | K26: =COUNT(C26:G26) -> 5 | L26: =IF(K26=0,"",AVERAGE(C26:G26)) -> -0.24155698 | M26: =IF(L26="","",RANK(L26,$L$20:$L$57,0)) -> 22
A27: R-RWK | B27: Rework due to workmanship or defects | C27: =IFERROR(AVERAGEIFS(RII_Data!$K$5:$K$186,RII_Data!$A$5:$A$186,"M06",RII_Data!$G$5:$G$186,$A27,RII_Data!$H$5:$H$186,"Direct"),"") -> 1.0663928 | D27: =IFERROR(AVERAGEIFS(RII_Data!$K$5:$K$186,RII_Data!$A$5:$A$186,"M10",RII_Data!$G$5:$G$186,$A27,RII_Data!$H$5:$H$186,"Direct"),"") -> 0.69944455 | E27: =IFERROR(AVERAGEIFS(RII_Data!$K$5:$K$186,RII_Data!$A$5:$A$186,"M14",RII_Data!$G$5:$G$186,$A27,RII_Data!$H$5:$H$186,"Direct"),"") | F27: =IFERROR(AVERAGEIFS(RII_Data!$K$5:$K$186,RII_Data!$A$5:$A$186,"M15",RII_Data!$G$5:$G$186,$A27,RII_Data!$H$5:$H$186,"Direct"),"") -> 1.4373036 | G27: =IFERROR(AVERAGEIFS(RII_Data!$K$5:$K$186,RII_Data!$A$5:$A$186,"M01",RII_Data!$G$5:$G$186,$A27,RII_Data!$H$5:$H$186,"Direct"),"") -> -0.4456674 | H27: =COUNT(C27:F27) -> 3 | I27: =IF(H27=0,"",AVERAGE(C27:F27)) -> 1.0677137 | J27: =IF(I27="","",RANK(I27,$I$20:$I$57,0)) -> 3 | K27: =COUNT(C27:G27) -> 4 | L27: =IF(K27=0,"",AVERAGE(C27:G27)) -> 0.68936839 | M27: =IF(L27="","",RANK(L27,$L$20:$L$57,0)) -> 8
A28: R-PAY | B28: Payment delay | C28: =IFERROR(AVERAGEIFS(RII_Data!$K$5:$K$186,RII_Data!$A$5:$A$186,"M06",RII_Data!$G$5:$G$186,$A28,RII_Data!$H$5:$H$186,"Direct"),"") -> 0.96621683 | D28: =IFERROR(AVERAGEIFS(RII_Data!$K$5:$K$186,RII_Data!$A$5:$A$186,"M10",RII_Data!$G$5:$G$186,$A28,RII_Data!$H$5:$H$186,"Direct"),"") -> 0.57192151 | E28: =IFERROR(AVERAGEIFS(RII_Data!$K$5:$K$186,RII_Data!$A$5:$A$186,"M14",RII_Data!$G$5:$G$186,$A28,RII_Data!$H$5:$H$186,"Direct"),"") -> 1.2061 | F28: =IFERROR(AVERAGEIFS(RII_Data!$K$5:$K$186,RII_Data!$A$5:$A$186,"M15",RII_Data!$G$5:$G$186,$A28,RII_Data!$H$5:$H$186,"Direct"),"") | G28: =IFERROR(AVERAGEIFS(RII_Data!$K$5:$K$186,RII_Data!$A$5:$A$186,"M01",RII_Data!$G$5:$G$186,$A28,RII_Data!$H$5:$H$186,"Direct"),"") -> 0.90043006 | H28: =COUNT(C28:F28) -> 3 | I28: =IF(H28=0,"",AVERAGE(C28:F28)) -> 0.91474612 | J28: =IF(I28="","",RANK(I28,$I$20:$I$57,0)) -> 7 | K28: =COUNT(C28:G28) -> 4 | L28: =IF(K28=0,"",AVERAGE(C28:G28)) -> 0.91116711 | M28: =IF(L28="","",RANK(L28,$L$20:$L$57,0)) -> 3
A29: R-DES | B29: Design changes or incomplete documentation | C29: =IFERROR(AVERAGEIFS(RII_Data!$K$5:$K$186,RII_Data!$A$5:$A$186,"M06",RII_Data!$G$5:$G$186,$A29,RII_Data!$H$5:$H$186,"Direct"),"") -> 1.2467298 | D29: =IFERROR(AVERAGEIFS(RII_Data!$K$5:$K$186,RII_Data!$A$5:$A$186,"M10",RII_Data!$G$5:$G$186,$A29,RII_Data!$H$5:$H$186,"Direct"),"") -> 0.88435296 | E29: =IFERROR(AVERAGEIFS(RII_Data!$K$5:$K$186,RII_Data!$A$5:$A$186,"M14",RII_Data!$G$5:$G$186,$A29,RII_Data!$H$5:$H$186,"Direct"),"") | F29: =IFERROR(AVERAGEIFS(RII_Data!$K$5:$K$186,RII_Data!$A$5:$A$186,"M15",RII_Data!$G$5:$G$186,$A29,RII_Data!$H$5:$H$186,"Direct"),"") -> 0.91062303 | G29: =IFERROR(AVERAGEIFS(RII_Data!$K$5:$K$186,RII_Data!$A$5:$A$186,"M01",RII_Data!$G$5:$G$186,$A29,RII_Data!$H$5:$H$186,"Direct"),"") -> -0.59119145 | H29: =COUNT(C29:F29) -> 3 | I29: =IF(H29=0,"",AVERAGE(C29:F29)) -> 1.0139019 | J29: =IF(I29="","",RANK(I29,$I$20:$I$57,0)) -> 4 | K29: =COUNT(C29:G29) -> 4 | L29: =IF(K29=0,"",AVERAGE(C29:G29)) -> 0.61262859 | M29: =IF(L29="","",RANK(L29,$L$20:$L$57,0)) -> 9
A30: R-SUP | B30: Inadequate supervision or monitoring of workers | C30: =IFERROR(AVERAGEIFS(RII_Data!$K$5:$K$186,RII_Data!$A$5:$A$186,"M06",RII_Data!$G$5:$G$186,$A30,RII_Data!$H$5:$H$186,"Direct"),"") | D30: =IFERROR(AVERAGEIFS(RII_Data!$K$5:$K$186,RII_Data!$A$5:$A$186,"M10",RII_Data!$G$5:$G$186,$A30,RII_Data!$H$5:$H$186,"Direct"),"") -> 1.4008213 | E30: =IFERROR(AVERAGEIFS(RII_Data!$K$5:$K$186,RII_Data!$A$5:$A$186,"M14",RII_Data!$G$5:$G$186,$A30,RII_Data!$H$5:$H$186,"Direct"),"") -> 1.2433729 | F30: =IFERROR(AVERAGEIFS(RII_Data!$K$5:$K$186,RII_Data!$A$5:$A$186,"M15",RII_Data!$G$5:$G$186,$A30,RII_Data!$H$5:$H$186,"Direct"),"") | G30: =IFERROR(AVERAGEIFS(RII_Data!$K$5:$K$186,RII_Data!$A$5:$A$186,"M01",RII_Data!$G$5:$G$186,$A30,RII_Data!$H$5:$H$186,"Direct"),"") -> -0.1546193 | H30: =COUNT(C30:F30) -> 2 | I30: =IF(H30=0,"",AVERAGE(C30:F30)) -> 1.3220971 | J30: =IF(I30="","",RANK(I30,$I$20:$I$57,0)) -> 1 | K30: =COUNT(C30:G30) -> 3 | L30: =IF(K30=0,"",AVERAGE(C30:G30)) -> 0.82985827 | M30: =IF(L30="","",RANK(L30,$L$20:$L$57,0)) -> 4
A31: R-MOT | B31: Low motivation, morale or labour turnover | C31: =IFERROR(AVERAGEIFS(RII_Data!$K$5:$K$186,RII_Data!$A$5:$A$186,"M06",RII_Data!$G$5:$G$186,$A31,RII_Data!$H$5:$H$186,"Direct"),"") | D31: =IFERROR(AVERAGEIFS(RII_Data!$K$5:$K$186,RII_Data!$A$5:$A$186,"M10",RII_Data!$G$5:$G$186,$A31,RII_Data!$H$5:$H$186,"Direct"),"") -> 0.036324745 | E31: =IFERROR(AVERAGEIFS(RII_Data!$K$5:$K$186,RII_Data!$A$5:$A$186,"M14",RII_Data!$G$5:$G$186,$A31,RII_Data!$H$5:$H$186,"Direct"),"") -> -1.188679 | F31: =IFERROR(AVERAGEIFS(RII_Data!$K$5:$K$186,RII_Data!$A$5:$A$186,"M15",RII_Data!$G$5:$G$186,$A31,RII_Data!$H$5:$H$186,"Direct"),"") | G31: =IFERROR(AVERAGEIFS(RII_Data!$K$5:$K$186,RII_Data!$A$5:$A$186,"M01",RII_Data!$G$5:$G$186,$A31,RII_Data!$H$5:$H$186,"Direct"),"") -> -0.4456674 | H31: =COUNT(C31:F31) -> 2 | I31: =IF(H31=0,"",AVERAGE(C31:F31)) -> -0.57617714 | J31: =IF(I31="","",RANK(I31,$I$20:$I$57,0)) -> 25 | K31: =COUNT(C31:G31) -> 3 | L31: =IF(K31=0,"",AVERAGE(C31:G31)) -> -0.5326739 | M31: =IF(L31="","",RANK(L31,$L$20:$L$57,0)) -> 26
... A57: R-FIN | B57: Contractor financial difficulties | C57: =IFERROR(AVERAGEIFS(RII_Data!$K$5:$K$186,RII_Data!$A$5:$A$186,"M06",RII_Data!$G$5:$G$186,$A57,RII_Data!$H$5:$H$186,"Direct"),"") | D57: =IFERROR(AVERAGEIFS(RII_Data!$K$5:$K$186,RII_Data!$A$5:$A$186,"M10",RII_Data!$G$5:$G$186,$A57,RII_Data!$H$5:$H$186,"Direct"),"") | E57: =IFERROR(AVERAGEIFS(RII_Data!$K$5:$K$186,RII_Data!$A$5:$A$186,"M14",RII_Data!$G$5:$G$186,$A57,RII_Data!$H$5:$H$186,"Direct"),"") | F57: =IFERROR(AVERAGEIFS(RII_Data!$K$5:$K$186,RII_Data!$A$5:$A$186,"M15",RII_Data!$G$5:$G$186,$A57,RII_Data!$H$5:$H$186,"Direct"),"") | G57: =IFERROR(AVERAGEIFS(RII_Data!$K$5:$K$186,RII_Data!$A$5:$A$186,"M01",RII_Data!$G$5:$G$186,$A57,RII_Data!$H$5:$H$186,"Direct"),"") | H57: =COUNT(C57:F57) -> 0 | I57: =IF(H57=0,"",AVERAGE(C57:F57)) | J57: =IF(I57="","",RANK(I57,$I$20:$I$57,0)) | K57: =COUNT(C57:G57) -> 0 | L57: =IF(K57=0,"",AVERAGE(C57:G57)) | M57: =IF(L57="","",RANK(L57,$L$20:$L$57,0))
A59: How to read this sheet:
A60: 1. Different rating scales give different RII levels (1-4 studies average about 0.59, 1-5 studies about 0.72 to 0.75). Standardising removes that, so values from different studies can be averaged.
A61: 2. Rank agreement WITHIN pairs of studies does not change under standardisation (z keeps the order inside a study); what changes is the pooled value and its uncertainty.
A62: 3. Treatment (yellow) is a judgement: only studies whose full factor list is available can be standardised honestly. Change it and the sheet recalculates.
A63: 4. Compare Pooled z (A) and (B) with the seed order on Seed_Calculation. They disagree: see docs/Statistical_Analysis_Standardised.docx for the tests (scripts/stats_standardised.py).
